Workbook
Name LISTA_TIPOS_VEHICULO: DATOS!$W$2:INDEX(DATOS!$W:$W,COUNTA(DATOS!$W:$W))

Sheet VEHICULOS
A1: POLICÍA NACIONAL DE ECUADOR
A2: DIRECCIÓN NACIONAL DE CONTROL DE TRÁNSITO Y SEGURIDAD VIAL
A3: CENTRO DE RETENCIÓN VEHICULAR "PORTOVIEJO TRES MARIAS"
B5: INGRESO DEL VEHICULO | V5: SALIDA DE VEHICULO | AM5: ALCOHOCHECK | AO5: INVESTIGACIÓN
A6: ORD. | B6: SUBZONA | C6: CENTRO DE RETENCION VEHICULAR | D6: FECHA DE INGRESO | E6: NÚMERO DE FORMULARIO DE INGRESO VEHICULAR | F6: PLACA | G6: MARCA | H6: TIPO | I6: MODELO | J6: COLOR | K6: AÑO DE FABRICACIÓN | L6: NÚMERO DE CHASIS | M6: NÚMERO DE MOTOR | N6: NÚMERO DE PARTE | O6: PARTE ELABORADO POR | P6: NOMBRE PROPIETARIO/RESPONSABLE DEL VEHICULO | Q6: SITUACIÓN LEGAL (Infracción tránsito) | R6: AUTORIDAD QUE CONOCE (Juzgado Y/O fiscalia que avocó conocimiento) | S6: PLACA-GRUA | T6: NOMBRES CONDUCTOR GRUA | U6: NOMBRE SERVIDOR POLICIAL QUE RECIBE LA CUSTODIA DEL VEHÍCULO | V6: FECHA EGRESO | W6: ORDEN DE LIBERTAD EMITIDA AUTORIDAD COMPETENTE | X6: NOMBRE DEL SEÑOR JEFE QUE EMITE LIBERTAD | Y6: NOMBRES DE PERSONA A QUIEN SE ENTREGA | Z6: NÚMERO DE CEDULA | AA6: NÚMERO DE ORDEN DE PAGO (GARAGE) | AB6: TIPO DE TYRAMITE / PROCESO | AC6: DIAS DE PERMANENCIA | AD6: VALOR TARIFARIO DIARIO | AE6: VALOR CANCELADO POR PARQUEO | AF6: No DE ORDEN DE PAGO | AG6: FECHA DE PAGO EN LA ENTIDA FINANCIERA | AH6: No DE COMPROBANTE DE PAGO DE LA ENTIDAD FINANCIERA | AI6: INSTITUCION FINANCIERA (BANCO, COOPERATIVA, ETC) | AJ6: NOMBRE DE LA INSTITUCIÓN FINANCIERA | AK6: NÚMERO DE FORMULARIO DE EGRESO VEHICULAR | AL6: NOMBRE SERVIDOR POLICIAL QUE ENTREGA EL VEHÍCULO (CUSTODIO) | AM6: NÚMERO DE ORDEN DE PAGO POR ALCOHOCHECK | AN6: VALOR CANCELADO POR ALCOHOCHEK | AO6: PERICIAS REALIZADAS | AP6: NOMBRE DEL PERITO | AQ6: FECHA DE PAGO EN LA ENTIDAD FINANCIERA | AR6: NRO. DE COMPROBANTE DE PAGO DE LA ENTIDAD FINANCIERA | AS6: INSTITUCIÓN FINANCIERA (BANCO-COOPERATIVA)
A7: 1 | B7: SANTO DOMINGO | C7: CONTROL 120 | D7: 45904 | E7: 2018 | F7: PPM0426 | G7: SUZUKI | I7: FORSA 1.0L T/M | J7: AZUL | K7: 1995 | L7: SF3105A11578 | M7: G10445928 | N7: 2025090406533790718 | O7: SGOS. TOAQUIZA MARCO | P7: MALES AULLA GERARDO NICOLAS | Q7: ACCIDENTE DE TRANSITO | R7: FISCALIA | S7: N/A | T7: N/A | U7: SGOS. CHASIPANTA XAVIER | AC7: =(V7-D7)+1 -> -45903 | AD7: =IF(AB7="SERVICIO DE GARAJE LIVIANOS (HASTA 3,5 TN A EXCEPCIÓN DE MOTOCICLETAS) (DIARIOS)",3,IF(AB7="SERVICIO DE GARAJE PESADOS (DE 3,51 TN HASTA 12 TN) (DIARIOS)",9,IF(AB7="SERVICIO DE GARAJE (CENTROS DE RETENCIÓN) MOTOCICLETA",1,IF(AB7="SERVICIO DE GARAJE EXTRA PESADOS (MÁS DE 12 TN) (DIARIOS)",15,0)))) -> 0 | AE7: =IFERROR(AD7*AC7,0) -> 0 | AF7: =AA7 -> 0 | AJ7: =IF(AI7="","",AI7) | AK7: =IF(E7="","",E7) -> 2018 | AM7: N/A | AN7: N/A | AQ7: =AG7 -> 0 | AR7: =AH7 -> 0 | AS7: =AJ7
A8: 31 | B8: SANTO DOMINGO | C8: CONTROL 120 | D8: 45998 | E8: 2031 | F8: PQF0838 | G8: FORD | H8: CISTERNA | I8: B1518TURBO 184HP | J8: BLANCO | K8: 2022 | L8: 9BFYTARB1RD879646 | M8: 5513 | N8: ´202512071018484501 | O8: CBOP. ABATA SANTIAGO | P8: ONTANEDA YEPEZ JORGE ANIBAL | Q8: ACCIDENTE DE TRANSITO | R8: FISCALIA | U8: SGOS. CHASIPANTA XAVIER | V8: 46030 | W8: OFICIO No. FPSD-FEAT1-0258-2026-000018-O | X8: MAYOR. SUAREZ JACOME JUAN CARLOS | Y8: =P8 -> ONTANEDA YEPEZ JORGE ANIBAL | Z8: 1711325496 | AA8: 95747679 | AB8: SERVICIO DE GARAJE PESADOS (DE 3,51 TN HASTA 12 TN) (DIARIOS) | AC8: =(V8-D8)+1 -> 33 | AD8: =IF(AB8="SERVICIO DE GARAJE LIVIANOS (HASTA 3,5 TN A EXCEPCIÓN DE MOTOCICLETAS) (DIARIOS)",3,IF(AB8="SERVICIO DE GARAJE PESADOS (DE 3,51 TN HASTA 12 TN) (DIARIOS)",9,IF(AB8="SERVICIO DE GARAJE (CENTROS DE RETENCIÓN) MOTOCICLETA",1,IF(AB8="SERVICIO DE GARAJE EXTRA PESADOS (MÁS DE 12 TN) (DIARIOS)",15,0)))) -> 9 | AE8: =IFERROR(AD8*AC8,0) -> 297 | AF8: =AA8 -> 95747679 | AG8: 46030 | AH8: 95747679 | AI8: MI NEGOCIO EFECTIVO-MI VECINO BANCO PICHINCHA-MI NEGOCIO EFECTIVO | AJ8: =IF(AI8="","",AI8) -> MI NEGOCIO EFECTIVO-MI VECINO BANCO PICHINCHA-MI NEGOCIO EFECTIVO | AK8: =IF(E8="","",E8) -> 2031 | AL8: SGOS. CHASIPANTA XAVIER | AO8: INORME TECNICO PERICIAL DE EVALUO TECNICO MECANICO Y RECONOCIMIENTO DE DAÑOS MATERIALES | AP8: CBOP. FRANCISCO WLADIMIR NASIMBA GUALPA | AQ8: =AG8 -> 46030 | AR8: =AH8 -> 95747679 | AS8: =AJ8 -> MI NEGOCIO EFECTIVO-MI VECINO BANCO PICHINCHA-MI NEGOCIO EFECTIVO
A9: 18 | B9: SANTO DOMINGO | C9: CONTROL 120 | D9: 46034 | E9: 2034 | F9: MAA3069 | G9: VOLSKWAGEN | H9: BUS | I9: 17210 OD 6.5 4X2 TM | J9: ANARANJADO | K9: 2013 | L9: 9F3GH1JGUAXX13056 | M9: J08CTT39521 | N9: 2026011204060520618 | O9: SGOS. PUCHA BYRON | P9: SABANDO ZAMBRANO MARIA FAVIOLA | Q9: ACCIDENTE DE TRANSITO | R9: FISCALIA | S9: N/A | T9: N/A | U9: SGOS. GUERRERO ALBERTO | V9: 46042 | W9: OFICIO No. FPSD-FEAT2-0608-2026-000227-O | X9: MAYR. GALIANO ANDRADE EDISON EDUARDO | Y9: SABANDO ZAMBRANO MARIA FAVIOLA | Z9: 802191395 | AA9: 95961118 | AB9: SERVICIO DE GARAJE PESADOS (DE 3,51 TN HASTA 12 TN) (DIARIOS) | AC9: =(V9-D9)+1 -> 9 | AD9: 9 | AE9: =IFERROR(AD9*AC9,0) -> 81 | AF9: =AA9 -> 95961118 | AG9: 46042 | AH9: 202601204779420 | AI9: BANCO DEL PACIFICO | AJ9: =IF(AI9="","",AI9) -> BANCO DEL PACIFICO | AK9: =IF(E9="","",E9) -> 2034 | AL9: SGOS. GUERRERO ALBERTO | AM9: N/A | AN9: N/A | AO9: INORME TECNICO PERICIAL DE EVALUO TECNICO MECANICO Y RECONOCIMIENTO DE DAÑOS MATERIALES | AP9: CBOS. GUAMAN JEFFERSON | AQ9: =AG9 -> 46042 | AR9: =AH9 -> 202601204779420 | AS9: =AJ9 -> BANCO DEL PACIFICO
A10: 19 | B10: SANTO DOMINGO | C10: CONTROL 120 | D10: 46038 | E10: 2035 | F10: GBN5890 | G10: HINO | H10: VOLQUETA | I10: FM1JLUD AC 8.0 2P 6X4 TM DIESEL | J10: AMARILLO | K10: 2014 | L10: 9F3FM1JLUEXX13122 | M10: J08CTT49883 | N10: 2026011602201191513 | O10: CBOS. CANGO JEFFERSON | P10: CALDERON BRIONES JORGE LUIS | Q10: ACCIDENTE DE TRANSITO | R10: FISCALIA | S10: N/A | T10: N/A | U10: SGOS. CHASIPANTA XAVIER | V10: 46042 | W10: OFICIO No. FPSD-FEAT1-0258-2026-000196-O | X10: MAYR. GALIANO ANDRADE EDISON EDUARDO | Y10: CALDERON BRIONES JORGE LUIS | Z10: 1714373246 | AA10: 95987084 | AB10: SERVICIO DE GARAJE EXTRA PESADOS (MAS DE 12 TN) (DIARIOS) | AC10: =(V10-D10)+1 -> 5 | AD10: 15 | AE10: =IFERROR(AD10*AC10,0) -> 75 | AF10: =AA10 -> 95987084 | AG10: 46042 | AH10: 17162463 | AI10: MI NEGOCIO EFECTIVO | AJ10: =IF(AI10="","",AI10) -> MI NEGOCIO EFECTIVO | AK10: =IF(E10="","",E10) -> 2035 | AL10: SGOS. GUERRERO ALBERTO | AM10: N/A | AN10: N/A | AO10: INORME TECNICO PERICIAL DE EVALUO TECNICO MECANICO Y RECONOCIMIENTO DE DAÑOS MATERIALES | AP10: CBOP. GAVILANEZ LENIN | AQ10: =AG10 -> 46042 | AR10: =AH10 -> 17162463 | AS10: =AJ10 -> MI NEGOCIO EFECTIVO
A11: 30 | B11: SANTO DOMINGO | C11: CONTROL 120 | D11: 46046 | E11: 2036 | F11: JAA3356 | G11: HINO | H11: BUS | I11: AK8JRSA AC 7.7 1P 4X2 TM DIESEL | J11: AZUL | K11: 2025 | L11: JHDAK8JRSLXX17722 | M11: J08EUD33999 | N11: ´2026012408040460418 | O11: SGOP. CHANGO CARLOS | P11: CAIZALUIZA JURADO CARLOS | Q11: ACCIDENTE DE TRANSITO | R11: FISCALIA | U11: SGOS. GUERRERO ALBERTO | V11: 46058 | W11: OF. No. FPSD-FEAT3-0609-2026-00567-O | X11: MAYOR. SUAREZ JACOME JUAN CARLOS | Y11: =P11 -> CAIZALUIZA JURADO CARLOS | Z11: 1701212001 | AA11: 96297335 | AB11: SERVICIO DE GARAJE EXTRA PESADOS (MÁS DE 12 TN) (DIARIOS) | AC11: =(V11-D11)+1 -> 13 | AD11: =IF(AB11="SERVICIO DE GARAJE LIVIANOS (HASTA 3,5 TN A EXCEPCIÓN DE MOTOCICLETAS) (DIARIOS)",3,IF(AB11="SERVICIO DE GARAJE PESADOS (DE 3,51 TN HASTA 12 TN) (DIARIOS)",9,IF(AB11="SERVICIO DE GARAJE (CENTROS DE RETENCIÓN) MOTOCICLETA",1,IF(AB11="SERVICIO DE GARAJE EXTRA PESADOS (MÁS DE 12 TN) (DIARIOS)",15,0)))) -> 15 | AE11: =IFERROR(AD11*AC11,0) -> 195 | AF11: =AA11 -> 96297335 | AG11: 46058 | AH11: 96297335 | AI11: MI NEGOCIO EFECTIVO-MI VECINO BANCO PICHINCHA-MI NEGOCIO EFECTIVO | AJ11: =IF(AI11="","",AI11) -> MI NEGOCIO EFECTIVO-MI VECINO BANCO PICHINCHA-MI NEGOCIO EFECTIVO | AK11: =IF(E11="","",E11) -> 2036 | AL11: SGOS. GUERRERO ALBERTO | AO11: INORME TECNICO PERICIAL DE EVALUO TECNICO MECANICO Y RECONOCIMIENTO DE DAÑOS MATERIALES | AP11: CBOP. FRANCISCO WLADIMIR NASIMBA GUALPA | AQ11: =AG11 -> 46058 | AR11: =AH11 -> 96297335 | AS11: =AJ11 -> MI NEGOCIO EFECTIVO-MI VECINO BANCO PICHINCHA-MI NEGOCIO EFECTIVO
A12: 23 | B12: SANTO DOMINGO | C12: CONTROL 120 | D12: 46049 | E12: 2037 | F12: PAD2356 | G12: SINOTRUK | H12: PLATAFORMA | I12: HOWO T5G ZZ1167K501GE1 AC 6.9 2P 4X2 | J12: BLANCO | K12: 2026 | L12: LZZ1BBKG3TA196146 | M12: 250307806327 | N12: 2026012700585644911 | O12: SGOP. CHANGO CARLOS | P12: QUIROLA VACA LUIS GONZALO | Q12: ACCIDENTE DE TRANSITO | R12: FISCALIA | U12: SGOS. CHASIPANTA XAVIER | V12: 46066 | W12: OF. No. FPSD-FEAT2-0608-2026-000622-O | X12: MAYOR. GALIANO ANDRADE EDISON EDUARDO | Y12: LUIS GONZALO QUIROLA VACA | Z12: 12711739902 | AA12: 96327232 | AB12: SERVICIO DE GARAJE PESADOS (DE 3,51 TN HASTA 12 TN) (DIARIOS) | AC12: =(V12-D12)+1 -> 18 | AD12: 9 | AE12: =IFERROR(AD12*AC12,0) -> 162 | AF12: =AA12 -> 96327232 | AG12: 46066 | AH12: 2026021383227820 | AI12: BANCO DEL PACIFICO | AJ12: =IF(AI12="","",AI12) -> BANCO DEL PACIFICO | AK12: =IF(E12="","",E12) -> 2037 | AL12: POLI. TIPAN KEVIN | AO12: INORME TECNICO PERICIAL DE EVALUO TECNICO MECANICO Y RECONOCIMIENTO DE DAÑOS MATERIALES | AP12: CBOP. REA FREIRE JULIO ERNESTO | AQ12: =AG12 -> 46066 | AR12: =AH12 -> 2026021383227820 | AS12: =AJ12 -> BANCO DEL PACIFICO
A13: 24 | B13: SANTO DOMINGO | C13: CONTROL 120 | D13: 46049 | E13: 2038 | F13: IAK0630 | G13: HINO | H13: CAMIÓN | I13: GH1JMUA | J13: BLANCO | K13: 2009 | L13: JHDGH1JMU9XX13743 | M13: J08CTT34551 | N13: 2026012700585644911 | O13: SGOP. CHANGO CARLOS | P13: COLCHA GUNSHA ERIK ALEXANDER | Q13: ACCIDENTE DE TRANSITO | R13: FISCALIA | U13: SGOS. CHASIPANTA XAVIER | V13: 46077 | W13: OF. No. FPSD-FEAT2-0608-2026-000740-O | X13: MAYOR. SUAREZ JACOME JUAN CARLOS | Y13: =P13 -> COLCHA GUNSHA ERIK ALEXANDER | Z13: 0605787365 | AA13: 96374559 | AB13: SERVICIO DE GARAJE EXTRA PESADOS (MAS DE 12 TN) (DIARIOS) | AC13: =(V13-D13)+1 -> 29 | AD13: 15 | AE13: =IFERROR(AD13*AC13,0) -> 435 | AF13: =AA13 -> 96374559 | AG13: 46077 | AH13: 96374559 | AI13: BANCO DEL PICHINCHA | AJ13: =IF(AI13="","",AI13) -> BANCO DEL PICHINCHA | AK13: =IF(E13="","",E13) -> 2038 | AL13: SGOS. GUERRERO ALBERTO | AO13: INORME TECNICO PERICIAL DE EVALUO TECNICO MECANICO Y RECONOCIMIENTO DE DAÑOS MATERIALES | AP13: CBOP. REA FREIRE JULIO ERNESTO | AQ13: =AG13 -> 46077 | AR13: =AH13 -> 96374559 | AS13: =AJ13 -> BANCO DEL PICHINCHA
A14: 21 | B14: SANTO DOMINGO | C14: CONTROL 120 | D14: 46052 | E14: 2039 | F14: GPX0484 | G14: HINO | H14: CAMIÓN | I14: GH1JMUA | J14: AZUL | K14: 2008 | L14: JHDGH1JMU8XX11914 | M14: J08CTT27435 | N14: 2026013009255363017 | O14: CBOS. CHASI DAVID | P14: CAIZAGUANO CHICAIZA ANGEL DIEGO | Q14: ACCIDENTE DE TRANSITO | R14: FISCALIA | S14: N/A | T14: N/A | U14: SGOS. CHASIPANTA XAVIER | V14: 46101 | W14: OFICIO No. FPSD-FEAT3-0609-2026-001045-O | X14: MAYR. SOLIS MAYORGA PABLO ENRIQUE | Y14: CAIZAGUANO CHICAIZA ANGEL DIEGO | Z14: 0604415398 | AA14: 96697197 | AB14: SERVICIO DE GARAJE EXTRA PESADOS (MAS DE 12 TN) (DIARIOS) | AC14: =(V14-D14)+1 -> 50 | AD14: 15 | AE14: =IFERROR(AD14*AC14,0) -> 750 | AF14: =AA14 -> 96697197 | AG14: 46101 | AH14: 202603209352820 | AI14: BANCO DEL PACIFICO | AJ14: =IF(AI14="","",AI14) -> BANCO DEL PACIFICO | AK14: =IF(E14="","",E14) -> 2039 | AL14: SGOS. GUERRERO ALBERTO | AM14: N/A | AN14: N/A | AO14: INORME TECNICO PERICIAL DE EVALUO TECNICO MECANICO Y RECONOCIMIENTO DE DAÑOS MATERIALES | AP14: CBOP. NASIMBA FRANCISCO | AQ14: =AG14 -> 46101 | AR14: =AH14 -> 202603209352820 | AS14: =AJ14 -> BANCO DEL PACIFICO
A15: 22 | B15: SANTO DOMINGO | C15: CONTROL 120 | D15: 46052 | E15: 2040 | F15: GBO7773 | G15: HINO | H15: FURGON | I15: GH8JM7A-XG3 AC 7.7 2P 4X2 TM DIESEL | J15: BLANCO | K15: 2019 | L15: 9F3GH8JM7KXX10505 | M15: J08EWG10725 | N15: 2.026013e+18 | O15: CBOS. CHASI DAVID | P15: NUÑEZ MORENO JAIME PATRICIO | Q15: ACCIDENTE DE TRANSITO | R15: FISCALIA | S15: N/A | T15: N/A | U15: SGOS. CHASIPANTA XAVIER | V15: 46077 | W15: OFICIO No. FPSD-FEAT3-0609-2026-000735-O | X15: MAYR. SUAREZ JACOME JUAN | Y15: NUÑEZ MORENO JAIME PATRICIO | Z15: 1707104111 | AA15: 96373751 | AB15: SERVICIO DE GARAJE EXTRA PESADOS (MAS DE 12 TN) (DIARIOS) | AC15: =(V15-D15)+1 -> 26 | AD15: 15 | AE15: =IFERROR(AD15*AC15,0) -> 390 | AF15: =AA15 -> 96373751 | AG15: 46077 | AH15: 202602246615320 | AI15: BANCO DEL PACIFICO | AJ15: =IF(AI15="","",AI15) -> BANCO DEL PACIFICO | AK15: =IF(E15="","",E15) -> 2040 | AL15: SGOS. GUERRERO ALBERTO | AM15: N/A | AN15: N/A | AO15: INORME TECNICO PERICIAL DE EVALUO TECNICO MECANICO Y RECONOCIMIENTO DE DAÑOS MATERIALES | AP15: CBOP. DIAZ STALIN | AQ15: =AG15 -> 46077 | AR15: =AH15 -> 202602246615320 | AS15: =AJ15 -> BANCO DEL PACIFICO
A16: 20 | B16: SANTO DOMINGO | C16: CONTROL 120 | D16: 46052 | E16: 2041 | F16: PAB1690 | G16: KENWORTH | H16: TRACTO CAMIÓN | I16: T800 6X4 | J16: NEGRO | K16: 2012 | L16: 1XKDD40X2CR706062 | M16: 79513534 | N16: 2026013009255363017 | O16: CBOS. CHASI DAVID | P16: PERALVO GARCIA MARCO VINIVIO | Q16: ACCIDENTE DE TRANSITO | R16: FISCALIA | S16: N/A | T16: N/A | U16: SGOS. CHASIPANTA XAVIER | V16: 46058 | W16: OFICIO No. FPSD-FEAT3-0609-2026-000574-O | X16: MAYR. SUAREZ JACOME JUAN | Y16: PERALVO GARCIA MARCO VINICIO | Z16: 1716186547 | AA16: 96297232 | AB16: SERVICIO DE GARAJE EXTRA PESADOS (MAS DE 12 TN) (DIARIOS) | AC16: =(V16-D16)+1 -> 7 | AD16: 15 | AE16: =IFERROR(AD16*AC16,0) -> 105 | AF16: =AA16 -> 96297232 | AG16: 46058 | AH16: 17252935 | AI16: SERVIPAGOS | AJ16: =IF(AI16="","",AI16) -> SERVIPAGOS | AK16: =IF(E16="","",E16) -> 2041 | AL16: SGOS. GUERRERO ALBERTO | AM16: N/A | AN16: N/A | AO16: INORME TECNICO PERICIAL DE EVALUO TECNICO MECANICO Y RECONOCIMIENTO DE DAÑOS MATERIALES | AP16: CBOP. SARANGO ROBERTO | AQ16: =AG16 -> 46058 | AR16: =AH16 -> 17252935 | AS16: =AJ16 -> SERVIPAGOS
A17: 25 | B17: SANTO DOMINGO | C17: CONTROL 120 | D17: 46055 | E17: 2042 | F17: PAB3354 | G17: JAC | H17: CANASTILLA | I17: HFC1134KR1 AC 6.7 2P 4X2 TM DIESEL | J17: BLANCO | K17: 2021 | L17: LJ11R2DG9M3200159 | M17: 82068908 | N17: 2026020207283196113 | O17: SGOP. CHANGO CARLOS | P17: MEDINA AROCA LUIS DANIEL | Q17: ACCIDENTE DE TRANSITO | R17: FISCALIA | U17: SGOS. CHASIPANTA XAVIER | V17: 46094 | W17: OF. No. FPSD-FEAT3-0609-2026-000953-O | X17: CPTN. IZA VILLENA RODNEY ESTEBAN | Y17: =P17 -> MEDINA AROCA LUIS DANIEL | Z17: 1717382491 | AB17: SERVICIO DE GARAJE PESADOS (DE 3,51 TN HASTA 12 TN) (DIARIOS) | AC17: =(V17-D17)+1 -> 40 | AD17: 9 | AE17: =IFERROR(AD17*AC17,0) -> 360 | AF17: =AA17 -> 0 | AG17: 46094 | AH17: 96502041-STO-SOL-031301007927594-17305788-7927594 | AI17: BANCO DEL PACIFICO-BANCO DEL PACIFICO | AJ17: =IF(AI17="","",AI17) -> BANCO DEL PACIFICO-BANCO DEL PACIFICO | AK17: =IF(E17="","",E17) -> 2042 | AL17: SGOS. CHASIPANTA XAVIER | AO17: INORME TECNICO PERICIAL DE EVALUO TECNICO MECANICO Y RECONOCIMIENTO DE DAÑOS MATERIALES | AP17: CBOP. GAVILANEZ AZOGUE LENIN | AQ17: =AG17 -> 46094 | AR17: =AH17 -> 96502041-STO-SOL-031301007927594-17305788-7927594 | AS17: =AJ17 -> BANCO DEL PACIFICO-BANCO DEL PACIFICO
A18: 26 | B18: SANTO DOMINGO | C18: CONTROL 120 | D18: 46058 | E18: 2043 | F18: CAE0442 | G18: CHEVROLET | H18: PLATAFORMA | I18: FVR 32P CHASIS CABINADO | J18: BLANCO | K18: 2003 | L18: JALFVR32P33000006 | M18: 6HE1900582 | N18: 2026020503164428108 | O18: SGOP. LOPEZ RICHARD | P18: CAZA MENDEZ JOSE LUIS | Q18: ACCIDENTE DE TRANSITO | R18: FISCALIA | U18: SGOS. GUERRERO ALBEFRTO | V18: 46128 | W18: OF. No. FPSD-FEAT3-0609-2026-001013-O | X18: MAYOR. SUAREZ JACOME JUAN CARLOS | Y18: =P18 -> CAZA MENDEZ JOSE LUIS | Z18: 1721866018 | AA18: 97283471/96689377 | AB18: SERVICIO DE GARAJE PESADOS (DE 3,51 TN HASTA 12 TN) (DIARIOS) | AC18: =(V18-D18)+1 -> 71 | AD18: 9 | AE18: =IFERROR(AD18*AC18,0) -> 639 | AF18: =AA18 -> 97283471/96689377 | AG18: 46128 | AH18: 202604163646507 | AI18: BANCO DEL PACIFICO-BANCO DEL PACIFICO | AJ18: =IF(AI18="","",AI18) -> BANCO DEL PACIFICO-BANCO DEL PACIFICO | AK18: =IF(E18="","",E18) -> 2043 | AL18: POLI. ESCOBAR NIXON | AO18: INORME TECNICO PERICIAL DE EVALUO TECNICO MECANICO Y RECONOCIMIENTO DE DAÑOS MATERIALES | AP18: CBOP. REA FREIRE JULIO ERNESTO | AQ18: =AG18 -> 46128 | AR18: =AH18 -> 202604163646507 | AS18: =AJ18 -> BANCO DEL PACIFICO-BANCO DEL PACIFICO
A19: 27 | B19: SANTO DOMINGO | C19: CONTROL 120 | D19: 46059 | E19: 2044 | F19: POT0362 | G19: NISSAN | H19: FURGON | I19: PKC212MHLB | J19: BLANCO | K19: 2005 | L19: JNBPKC212AM00690 | M19: FE6003685H | N19: 202602060046268501 | O19: SGOP. INCA VICTOR | P19: NELSON ENRIQUE REYES MENA | Q19: ACCIDENTE DE TRANSITO | R19: FISCALIA | U19: SGOS. GUERRERO ALBEFRTO | V19: 46091 | W19: OF. No. FPSD-FEAT2-0608-2026-000872-O | X19: MAYOR SOLIS MAYORGA PABLO | Y19: =P19 -> NELSON ENRIQUE REYES MENA | Z19: 0500450473 | AA19: 96455066 | AB19: SERVICIO DE GARAJE EXTRA PESADOS (MAS DE 12 TN) (DIARIOS) | AC19: =(V19-D19)+1 -> 33 | AD19: 15 | AE19: =IFERROR(AD19*AC19,0) -> 495 | AF19: =AA19 -> 96455066 | AG19: 44995 | AH19: 202603107899120 | AI19: BANCO DEL PACIFICO-BANCO DEL PACIFICO | AJ19: =IF(AI19="","",AI19) -> BANCO DEL PACIFICO-BANCO DEL PACIFICO | AK19: =IF(E19="","",E19) -> 2044 | AL19: SGOS. GUERRERO ALBERTO | AO19: INORME TECNICO PERICIAL DE EVALUO TECNICO MECANICO Y RECONOCIMIENTO DE DAÑOS MATERIALES | AP19: CPTN. RAMIREZ VELASTEGUI SANTIAGO RUBEN | AQ19: =AG19 -> 44995 | AR19: =AH19 -> 202603107899120 | AS19: =AJ19 -> BANCO DEL PACIFICO-BANCO DEL PACIFICO
A20: 33 | B20: SANTO DOMINGO | C20: CONTROL 120 | D20: 46059 | E20: 2045 | F20: GTT9096 | G20: SINOTRUK | H20: CABEZAL | I20: SITRAK C7H ZZ4256V324HC1B AC 12,4 | J20: BLANCO | K20: 2025 | L20: LZZ7CLXB6TC695392 | M20: 250417006807 | N20: ´202602060046268510 | O20: SGOP.MUÑOZ VERA EDWIN JAVIER | P20: ORIENTAL ALIMENTICIA S.A. | Q20: ACCIDENTE DE TRANSITO | R20: FISCALIA | U20: SGOS. GUERRERO ALBERTO | V20: 46106 | W20: OF. No. FPSD-FEAT2-0608-2026-001128-O | X20: MAYOR. SUAREZ JACOME JUAN CARLOS | Y20: BARRAGAN PROAÑO YUDITH NARCISA | Z20: 1206209627 | AA20: 9680021 | AB20: SERVICIO DE GARAJE EXTRA PESADOS (MÁS DE 12 TN) (DIARIOS) | AC20: =(V20-D20)+1 -> 48 | AD20: =IF(AB20="SERVICIO DE GARAJE LIVIANOS (HASTA 3,5 TN A EXCEPCIÓN DE MOTOCICLETAS) (DIARIOS)",3,IF(AB20="SERVICIO DE GARAJE PESADOS (DE 3,51 TN HASTA 12 TN) (DIARIOS)",9,IF(AB20="SERVICIO DE GARAJE (CENTROS DE RETENCIÓN) MOTOCICLETA",1,IF(AB20="SERVICIO DE GARAJE EXTRA PESADOS (MÁS DE 12 TN) (DIARIOS)",15,0)))) -> 15 | AE20: =IFERROR(AD20*AC20,0) -> 720 | AF20: =AA20 -> 9680021 | AG20: 46106 | AH20: 202603255394920 | AI20: BANCO PACIFICO | AJ20: =IF(AI20="","",AI20) -> BANCO PACIFICO | AK20: =IF(E20="","",E20) -> 2045 | AL20: SGOS. GUERRERO ALBERTO | AO20: INORME TECNICO PERICIAL DE EVALUO TECNICO MECANICO Y RECONOCIMIENTO DE DAÑOS MATERIALES | AP20: CPTN. RAMIREZ VELASTEGUI SANTIAGO RUBEN | AQ20: =AG20 -> 46106 | AR20: =AH20 -> 202603255394920 | AS20: =AJ20 -> BANCO PACIFICO
A21: 35 | B21: SANTO DOMINGO | C21: CONTROL 120 | D21: 46064 | E21: 2046 | F21: PAE5673 | G21: JAC | H21: FURGON | I21: CN HFC1063KN 4,5 2P 4X2 TM DIESEL | J21: BLANCO | K21: 2025 | L21: LJ11KRCE8T1901086 | M21: 84635711 | N21: ´2026021110150224117 | O21: SGOP. LOPEZ RICHARD | P21: RODRIGUEZ YUQUI CARMEN AMELIA | Q21: ACCIDENTE DE TRANSITO | R21: FISCALIA | U21: POLI. TIPAN KEVIN | V21: 46086 | W21: OFICIO No. FPSD-FEAT1-0258-2026-001028-O | X21: MAYOR. SUAREZ JACOME JUAN CARLOS | Y21: =P21 -> RODRIGUEZ YUQUI CARMEN AMELIA | Z21: 913220786 | AA21: 96419706 | AB21: SERVICIO DE GARAJE PESADOS (DE 3,51 TN HASTA 12 TN) (DIARIOS) | AC21: =(V21-D21)+1 -> 23 | AD21: =IF(AB21="SERVICIO DE GARAJE LIVIANOS (HASTA 3,5 TN A EXCEPCIÓN DE MOTOCICLETAS) (DIARIOS)",3,IF(AB21="SERVICIO DE GARAJE PESADOS (DE 3,51 TN HASTA 12 TN) (DIARIOS)",9,IF(AB21="SERVICIO DE GARAJE (CENTROS DE RETENCIÓN) MOTOCICLETA",1,IF(AB21="SERVICIO DE GARAJE EXTRA PESADOS (MÁS DE 12 TN) (DIARIOS)",15,0)))) -> 9 | AE21: =IFERROR(AD21*AC21,0) -> 207 | AF21: =AA21 -> 96419706 | AG21: 46085 | AH21: 96419706 | AI21: MI NEGOCIO EFECTIVO BANCO PICHINCHA | AJ21: =IF(AI21="","",AI21) -> MI NEGOCIO EFECTIVO BANCO PICHINCHA | AK21: =IF(E21="","",E21) -> 2046 | AL21: SGOS. GUERRERO ALBERTO | AO21: INORME TECNICO PERICIAL DE EVALUO TECNICO MECANICO Y RECONOCIMIENTO DE DAÑOS MATERIALES | AP21: CBOP. SARANGO ROBERTO | AQ21: =AG21 -> 46085 | AR21: =AH21 -> 96419706 | AS21: =AJ21 -> MI NEGOCIO EFECTIVO BANCO PICHINCHA
A22: 34 | B22: SANTO DOMINGO | C22: CONTROL 120 | D22: 46064 | E22: 2047 | F22: RAA6300 | G22: FOTON | H22: TRACTO CAMIÓN | I22: AUMAN BJ4259 AC 11,8 2P 6X4 TM DIESEL | J22: AMARILLO | K22: 2024 | L22: LVBS6PEBXJT009981 | M22: ISGE343076216065 | N22: ´2026021110150224117 | O22: SGOP. LOPEZ RICHARD | P22: RAMOS ARGUELLO HOLGER ROLANDO | Q22: ACCIDENTE DE TRANSITO | R22: FISCALIA | U22: SGOS. GUERRERO ALBERTO | V22: 46085 | W22: OFICIO No. FPSD-FEAT1-0258-2026-001029-O | X22: MAYOR. SUAREZ JACOME JUAN CARLOS | Y22: =P22 -> RAMOS ARGUELLO HOLGER ROLANDO | Z22: 201455029 | AA22: 96419609 | AB22: SERVICIO DE GARAJE EXTRA PESADOS (MÁS DE 12 TN) (DIARIOS) | AC22: =(V22-D22)+1 -> 22 | AD22: =IF(AB22="SERVICIO DE GARAJE LIVIANOS (HASTA 3,5 TN A EXCEPCIÓN DE MOTOCICLETAS) (DIARIOS)",3,IF(AB22="SERVICIO DE GARAJE PESADOS (DE 3,51 TN HASTA 12 TN) (DIARIOS)",9,IF(AB22="SERVICIO DE GARAJE (CENTROS DE RETENCIÓN) MOTOCICLETA",1,IF(AB22="SERVICIO DE GARAJE EXTRA PESADOS (MÁS DE 12 TN) (DIARIOS)",15,0)))) -> 15 | AE22: =IFERROR(AD22*AC22,0) -> 330 | AF22: =AA22 -> 96419609 | AG22: 46085 | AH22: 96419609 | AI22: BANCO DEL PICHINCHA | AJ22: =IF(AI22="","",AI22) -> BANCO DEL PICHINCHA | AK22: =IF(E22="","",E22) -> 2047 | AL22: SGOS. GUERRERO ALBERTO | AO22: INORME TECNICO PERICIAL DE EVALUO TECNICO MECANICO Y RECONOCIMIENTO DE DAÑOS MATERIALES | AP22: CBOP. SARANGO ROBERTO | AQ22: =AG22 -> 46085 | AR22: =AH22 -> 96419609 | AS22: =AJ22 -> BANCO DEL PICHINCHA
A23: 36 | B23: SANTO DOMINGO | C23: CONTROL 120 | D23: 46074 | E23: 2048 | F23: PCD3784 | G23: HINO | H23: TRACTO CAMIÓN | I23: S81EKVA TM 12,9 2P 6X4 | J23: BLANCO | K23: 2023 | L23: JHDSS1EK701S13321 | M23: E13CTR17378 | N23: ´2026022101231431508 | O23: CBOP. ABATA SANTIAGO | P23: JIMENEZ VACA LEONEL ISRAEL | Q23: ACCIDENTE DE TRANSITO | R23: FISCALIA | U23: SGOS. GUERRERO ALBERTO | V23: 46080 | W23: OF. No. FPSD-FEAT3-0609-2026-00820-O | X23: MAYOR. GALIANO ANDRADE EDISON EDUARDO | Y23: =P23 -> JIMENEZ VACA LEONEL ISRAEL | Z23: 503404246 | AA23: 96398097 | AB23: SERVICIO DE GARAJE EXTRA PESADOS (MÁS DE 12 TN) (DIARIOS) | AC23: =(V23-D23)+1 -> 7 | AD23: =IF(AB23="SERVICIO DE GARAJE LIVIANOS (HASTA 3,5 TN A EXCEPCIÓN DE MOTOCICLETAS) (DIARIOS)",3,IF(AB23="SERVICIO DE GARAJE PESADOS (DE 3,51 TN HASTA 12 TN) (DIARIOS)",9,IF(AB23="SERVICIO DE GARAJE (CENTROS DE RETENCIÓN) MOTOCICLETA",1,IF(AB23="SERVICIO DE GARAJE EXTRA PESADOS (MÁS DE 12 TN) (DIARIOS)",15,0)))) -> 15 | AE23: =IFERROR(AD23*AC23,0) -> 105 | AF23: =AA23 -> 96398097 | AG23: 46080 | AH23: 2542207 | AI23: BANCO DEL PACIFICO | AJ23: =IF(AI23="","",AI23) -> BANCO DEL PACIFICO | AK23: =IF(E23="","",E23) -> 2048 | AL23: POLI. TIPAN KEVIN | AO23: INORME TECNICO PERICIAL DE EVALUO TECNICO MECANICO Y RECONOCIMIENTO DE DAÑOS MATERIALES | AP23: CBOP. ESTALIN PATRICIO DIAZ FUENTES | AQ23: =AG23 -> 46080 | AR23: =AH23 -> 2542207 | AS23: =AJ23 -> BANCO DEL PACIFICO
A24: 38 | B24: SANTO DOMINGO | C24: CONTROL 120 | D24: 46078 | E24: 2050 | F24: RCF0072 | G24: HINO | H24: FURGON | I24: XZ413L-HKMMD | J24: BLANCO | K24: 2025 | L24: JHFUT13H172000027 | M24: N04CTT10139 | N24: ´2026022511524258300 | O24: CBOP. PASPUEL WILSON | P24: DISTRIBUIDORA IMPORTADORA DIPORT | Q24: ACCIDENTE DE TRANSITO | R24: FISCALIA | U24: POLI. TIPAN KEVIN | V24: 46122 | W24: OF. No. PN-SZSDT-JPCTV-DIG-2026-096-O | X24: MAYOR. JARA POZO KERLEY EDUARDO | Y24: GARCES RAMIREZ XIMENA DEL PILAR | Z24: 1706508155 | AA24: 97132574 | AB24: SERVICIO DE GARAJE PESADOS (DE 3,51 TN HASTA 12 TN) (DIARIOS) | AC24: =(V24-D24)+1 -> 45 | AD24: =IF(AB24="SERVICIO DE GARAJE LIVIANOS (HASTA 3,5 TN A EXCEPCIÓN DE MOTOCICLETAS) (DIARIOS)",3,IF(AB24="SERVICIO DE GARAJE PESADOS (DE 3,51 TN HASTA 12 TN) (DIARIOS)",9,IF(AB24="SERVICIO DE GARAJE (CENTROS DE RETENCIÓN) MOTOCICLETA",1,IF(AB24="SERVICIO DE GARAJE EXTRA PESADOS (MÁS DE 12 TN) (DIARIOS)",15,0)))) -> 9 | AE24: =IFERROR(AD24*AC24,0) -> 405 | AF24: =AA24 -> 97132574 | AG24: 46122 | AH24: 202604102635920 | AI24: BANCO DEL PACIFICO | AJ24: =IF(AI24="","",AI24) -> BANCO DEL PACIFICO | AK24: =IF(E24="","",E24) -> 2050 | AL24: SGOS. CHASIPANTA XAVIER | AO24: INORME TECNICO PERICIAL DE EVALUO TECNICO MECANICO Y RECONOCIMIENTO DE DAÑOS MATERIALES | AP24: SGOS. CRUZ CALDERON DANILO FABRICIO | AQ24: =AG24 -> 46122 | AR24: =AH24 -> 202604102635920 | AS24: =AJ24 -> BANCO DEL PACIFICO
A25: 37 | B25: SANTO DOMINGO | C25: CONTROL 120 | D25: 46078 | E25: 2049 | F25: PAB7793 | G25: HINO | H25: FURGON | I25: FM2PR7A-SG3 AC 10,5 2P 6X4 TM DIESEL | J25: BLANCO | K25: 2025 | L25: 9F3FM2PR7MXX10407 | M25: P11CVT21007 | N25: ´2026022607544979807 | O25: SGOP. VIRACOCHA RODOLFO | P25: ALCOCER ZAPATA LUIS GUSTAVO | Q25: ACCIDENTE DE TRANSITO | R25: FISCALIA | U25: POLI. TIPAN KEVIN | V25: 46093 | W25: OF. No. FPSD-FEAT3-0609-2026-000919-O | X25: MAYOR SOLIS MAYORGA PABLO | Y25: =P25 -> ALCOCER ZAPATA LUIS GUSTAVO | Z25: 1710361179 | AA25: 96484775 | AB25: SERVICIO DE GARAJE PESADOS (DE 3,51 TN HASTA 12 TN) (DIARIOS) | AC25: =(V25-D25)+1 -> 16 | AD25: =IF(AB25="SERVICIO DE GARAJE LIVIANOS (HASTA 3,5 TN A EXCEPCIÓN DE MOTOCICLETAS) (DIARIOS)",3,IF(AB25="SERVICIO DE GARAJE PESADOS (DE 3,51 TN HASTA 12 TN) (DIARIOS)",9,IF(AB25="SERVICIO DE GARAJE (CENTROS DE RETENCIÓN) MOTOCICLETA",1,IF(AB25="SERVICIO DE GARAJE EXTRA PESADOS (MÁS DE 12 TN) (DIARIOS)",15,0)))) -> 9 | AE25: =IFERROR(AD25*AC25,0) -> 144 | AF25: =AA25 -> 96484775 | AG25: 46093 | AH25: 96484775 | AI25: MI NEGOCIO EFECTIVO-MI NEGOCIO EFECTIVO | AJ25: =IF(AI25="","",AI25) -> MI NEGOCIO EFECTIVO-MI NEGOCIO EFECTIVO | AK25: =IF(E25="","",E25) -> 2049 | AL25: SGOS. CHASIPANTA XAVIER | AO25: INORME TECNICO PERICIAL DE EVALUO TECNICO MECANICO Y RECONOCIMIENTO DE DAÑOS MATERIALES | AP25: CPTN. RAMIREZ VELASTEGUI SANTIAGO RUBEN | AQ25: =AG25 -> 46093 | AR25: =AH25 -> 96484775 | AS25: =AJ25 -> MI NEGOCIO EFECTIVO-MI NEGOCIO EFECTIVO
A26: 39 | B26: SANTO DOMINGO | C26: CONTROL 120 | D26: 46081 | E26: 2051 | F26: EAA1221 | G26: VOLKSWAGEN | H26: AUTOBUS | I26: 17210 OO 6,5 4X2 TM DIESEL | J26: AZUL | K26: 2023 | L26: 9532F82W3DR313998 | M26: G1T145457 | N26: ´2026022802031976305 | O26: SGOS. CALDERON PABLO | P26: VILATUÑA PINTO LIVIA MARUJA | Q26: ACCIDENTE DE TRANSITO | R26: FISCALIA | U26: POLI. TIPAN KEVIN | V26: 46101 | W26: OF. No. FPSD-FEAT2-0608-2026-0000087-O | X26: MAYOR SOLIS MAYORGA PABLO | Y26: =P26 -> VILATUÑA PINTO LIVIA MARUJA | Z26: 1704123031 | AA26: 96678325 | AB26: SERVICIO DE GARAJE PESADOS (DE 3,51 TN HASTA 12 TN) (DIARIOS) | AC26: =(V26-D26)+1 -> 21 | AD26: =IF(AB26="SERVICIO DE GARAJE LIVIANOS (HASTA 3,5 TN A EXCEPCIÓN DE MOTOCICLETAS) (DIARIOS)",3,IF(AB26="SERVICIO DE GARAJE PESADOS (DE 3,51 TN HASTA 12 TN) (DIARIOS)",9,IF(AB26="SERVICIO DE GARAJE (CENTROS DE RETENCIÓN) MOTOCICLETA",1,IF(AB26="SERVICIO DE GARAJE EXTRA PESADOS (MÁS DE 12 TN) (DIARIOS)",15,0)))) -> 9 | AE26: =IFERROR(AD26*AC26,0) -> 189 | AF26: =AA26 -> 96678325 | AG26: 46101 | AH26: 202603206199420 | AI26: BANCO DEL PACIFICO | AJ26: =IF(AI26="","",AI26) -> BANCO DEL PACIFICO | AK26: =IF(E26="","",E26) -> 2051 | AL26: SGOS. GUERRERO ALBERTO | AO26: INORME TECNICO PERICIAL DE EVALUO TECNICO MECANICO Y RECONOCIMIENTO DE DAÑOS MATERIALES | AP26: CBOP. ESTALIN PATRICIO DIAZ FUENTES | AQ26: =AG26 -> 46101 | AR26: =AH26 -> 202603206199420 | AS26: =AJ26 -> BANCO DEL PACIFICO
A27: 40 | B27: SANTO DOMINGO | C27: CONTROL 120 | D27: 46087 | E27: 2052 | F27: XAA1180 | G27: KENWORTH | H27: TRACTO CAMIÓN | I27: T800 ESPECIAL EDITION AERODYNAME | J27: ANARANJADO | K27: 2022 | L27: 3WKDD40XXEF718448 | M27: 79657554 | N27: ´2026030607392661603 | O27: CBOS. CUÑEZ GUALOMOTO BRYAN OSWALDO | P27: CHACON MOLINA PABLO ALFREDO | Q27: ACCIDENTE DE TRANSITO | R27: FISCALIA | U27: CBOP. BRAULIO ACUÑA | V27: 46093 | W27: OF. No. FPSD-FEAT1-3009-2026-000034-O | X27: MAYOR SOLIS MAYORGA PABLO | Y27: =P27 -> CHACON MOLINA PABLO ALFREDO | Z27: ´0502119522 | AA27: 96482810 | AB27: SERVICIO DE GARAJE EXTRA PESADOS (MÁS DE 12 TN) (DIARIOS) | AC27: =(V27-D27)+1 -> 7 | AD27: =IF(AB27="SERVICIO DE GARAJE LIVIANOS (HASTA 3,5 TN A EXCEPCIÓN DE MOTOCICLETAS) (DIARIOS)",3,IF(AB27="SERVICIO DE GARAJE PESADOS (DE 3,51 TN HASTA 12 TN) (DIARIOS)",9,IF(AB27="SERVICIO DE GARAJE (CENTROS DE RETENCIÓN) MOTOCICLETA",1,IF(AB27="SERVICIO DE GARAJE EXTRA PESADOS (MÁS DE 12 TN) (DIARIOS)",15,0)))) -> 15 | AE27: =IFERROR(AD27*AC27,0) -> 105 | AF27: =AA27 -> 96482810 | AG27: 46093 | AH27: 202603122529220 | AI27: BANCO DEL PACIFICO | AJ27: =IF(AI27="","",AI27) -> BANCO DEL PACIFICO | AK27: =IF(E27="","",E27) -> 2052 | AL27: SGOS. CHASIPANTA XAVIER | AO27: INORME TECNICO PERICIAL DE EVALUO TECNICO MECANICO Y RECONOCIMIENTO DE DAÑOS MATERIALES | AP27: AGENTE GAROFALO ROBERTO | AQ27: =AG27 -> 46093 | AR27: =AH27 -> 202603122529220 | AS27: =AJ27 -> BANCO DEL PACIFICO
A28: 41 | B28: SANTO DOMINGO | C28: CONTROL 120 | D28: 46091 | E28: 2053 | F28: JAA1725 | G28: HINO | H28: BUS | I28: AK8JRSA AC 7.7 1P 4X2 TM DIESEL | J28: AZUL | K28: 2022 | L28: JHDAK8JRSEXX12015 | M28: J08EUD19818 | N28: ´2026031001195636511 | O28: SGOP.MUÑOZ VERA EDWIN JAVIER | P28: MONTERO PINOS EDUARDO ANGEL | Q28: ACCIDENTE DE TRANSITO | R28: FISCALIA | U28: SGOS. GUERRERO ALBERTO | V28: 46093 | W28: OF. No. 1157-2026-FGE-UFSDT | X28: CPTN. IZA VILLENA RODNEY ESTEBAN | Y28: =P28 -> MONTERO PINOS EDUARDO ANGEL | Z28: 1500421878 | AA28: 96499759 | AB28: SERVICIO DE GARAJE EXTRA PESADOS (MÁS DE 12 TN) (DIARIOS) | AC28: =(V28-D28)+1 -> 3 | AD28: =IF(AB28="SERVICIO DE GARAJE LIVIANOS (HASTA 3,5 TN A EXCEPCIÓN DE MOTOCICLETAS) (DIARIOS)",3,IF(AB28="SERVICIO DE GARAJE PESADOS (DE 3,51 TN HASTA 12 TN) (DIARIOS)",9,IF(AB28="SERVICIO DE GARAJE (CENTROS DE RETENCIÓN) MOTOCICLETA",1,IF(AB28="SERVICIO DE GARAJE EXTRA PESADOS (MÁS DE 12 TN) (DIARIOS)",15,0)))) -> 15 | AE28: =IFERROR(AD28*AC28,0) -> 45 | AF28: =AA28 -> 96499759 | AG28: 46093 | AH28: 96499759 | AI28: MI NEGOCIO EFECTIVO-MI VECINO BANCO PICHINCHA-MI NEGOCIO EFECTIVO | AJ28: =IF(AI28="","",AI28) -> MI NEGOCIO EFECTIVO-MI VECINO BANCO PICHINCHA-MI NEGOCIO EFECTIVO | AK28: =IF(E28="","",E28) -> 2053 | AL28: SGOS. CHASIPANTA XAVIER | AO28: INORME TECNICO PERICIAL DE EVALUO TECNICO MECANICO Y RECONOCIMIENTO DE DAÑOS MATERIALES | AP28: CBOP. LENIN ORLANDO GAVILANEZ AZOGUE | AQ28: =AG28 -> 46093 | AR28: =AH28 -> 96499759 | AS28: =AJ28 -> MI NEGOCIO EFECTIVO-MI VECINO BANCO PICHINCHA-MI NEGOCIO EFECTIVO
A29: 42 | B29: SANTO DOMINGO | C29: CONTROL 120 | D29: 46094 | E29: 2054 | F29: IBA1861 | G29: CHEVROLET | H29: CAMIÓN | I29: FVR 23P CHASIS CABINADO | J29: BLANCO | K29: 2026 | L29: JALFVR23P970000093 | M29: 6SD1416579 | N29: ´202603130919564104 | O29: SGOP. LOPEZ RICHARD | P29: CHINGAL ZUÑIGA DALY VANESSA | Q29: ACCIDENTE DE TRANSITO | R29: FISCALIA | U29: SGOS. CHASIPANTA XAVIER | V29: 46100 | W29: OF. No. FPSD-FEAT3-0609-2026-0001037-O | X29: MAYOR SOLIS MAYORGA PABLO | Y29: =P29 -> CHINGAL ZUÑIGA DALY VANESSA | Z29: 1758756249 | AA29: 96656269 | AB29: SERVICIO DE GARAJE PESADOS (DE 3,51 TN HASTA 12 TN) (DIARIOS) | AC29: =(V29-D29)+1 -> 7 | AD29: =IF(AB29="SERVICIO DE GARAJE LIVIANOS (HASTA 3,5 TN A EXCEPCIÓN DE MOTOCICLETAS) (DIARIOS)",3,IF(AB29="SERVICIO DE GARAJE PESADOS (DE 3,51 TN HASTA 12 TN) (DIARIOS)",9,IF(AB29="SERVICIO DE GARAJE (CENTROS DE RETENCIÓN) MOTOCICLETA",1,IF(AB29="SERVICIO DE GARAJE EXTRA PESADOS (MÁS DE 12 TN) (DIARIOS)",15,0)))) -> 9 | AE29: =IFERROR(AD29*AC29,0) -> 63 | AF29: =AA29 -> 96656269 | AG29: 46100 | AH29: 202603199742220 | AI29: BANCO DEL PACIFICO | AJ29: =IF(AI29="","",AI29) -> BANCO DEL PACIFICO | AK29: =IF(E29="","",E29) -> 2054 | AL29: SGOS. GUERRERO ALBERTO | AO29: INORME TECNICO PERICIAL DE EVALUO TECNICO MECANICO Y RECONOCIMIENTO DE DAÑOS MATERIALES | AP29: CBOS. GUAMAN FREIRE JEFFERSON GUILLERMO | AQ29: =AG29 -> 46100 | AR29: =AH29 -> 202603199742220 | AS29: =AJ29 -> BANCO DEL PACIFICO
A30: 43 | B30: SANTO DOMINGO | C30: CONTROL 120 | D30: 46094 | E30: 2055 | F30: PAE1001 | G30: KENWORTH | H30: TRACTO CAMIÓN | I30: T880 AC 15,0 2P 6X4 | J30: AZUL | K30: 2023 | L30: 3WKZD40X4PF203924 | M30: 80414982 | N30: ´202603130919564104 | O30: SGOP. LOPEZ RICHARD | P30: PERALVO GARCIA MARCO VINIVIO | Q30: ACCIDENTE DE TRANSITO | R30: FISCALIA | U30: SGOS. GUERRERO ALBERTO | V30: 46100 | W30: OF. No. FPSD-FEAT3-0609-2026-0001038-O | X30: MAYOR SOLIS MAYORGA PABLO | Y30: =P30 -> PERALVO GARCIA MARCO VINIVIO | Z30: 1716186547 | AA30: 96668135 | AB30: SERVICIO DE GARAJE EXTRA PESADOS (MÁS DE 12 TN) (DIARIOS) | AC30: =(V30-D30)+1 -> 7 | AD30: =IF(AB30="SERVICIO DE GARAJE LIVIANOS (HASTA 3,5 TN A EXCEPCIÓN DE MOTOCICLETAS) (DIARIOS)",3,IF(AB30="SERVICIO DE GARAJE PESADOS (DE 3,51 TN HASTA 12 TN) (DIARIOS)",9,IF(AB30="SERVICIO DE GARAJE (CENTROS DE RETENCIÓN) MOTOCICLETA",1,IF(AB30="SERVICIO DE GARAJE EXTRA PESADOS (MÁS DE 12 TN) (DIARIOS)",15,0)))) -> 15 | AE30: =IFERROR(AD30*AC30,0) -> 105 | AF30: =AA30 -> 96668135 | AG30: 46100 | AH30: NO LEGIBLE | AI30: NO LEGIBLE | AJ30: =IF(AI30="","",AI30) -> NO LEGIBLE | AK30: =IF(E30="","",E30) -> 2055 | AL30: SGOS. GUERRERO ALBERTO | AO30: INORME TECNICO PERICIAL DE EVALUO TECNICO MECANICO Y RECONOCIMIENTO DE DAÑOS MATERIALES | AP30: CBOS. GUAMAN FREIRE JEFFERSON GUILLERMO | AQ30: =AG30 -> 46100 | AR30: =AH30 -> NO LEGIBLE | AS30: =AJ30 -> NO LEGIBLE
A31: 44 | B31: SANTO DOMINGO | C31: CONTROL 120 | D31: 46095 | E31: 2056 | F31: JAA3530 | G31: HINO | H31: BUS | I31: AK8JRSA AC 7.7 1P 4X2 TM DIESEL | J31: PLATEADO | K31: 2025 | L31: JHDAK8JRSPXX19028 | M31: J08EUD36562 | N31: ´202603140924020503 | O31: SGOS. PINZON DIEGO | P31: HARO OÑATE MARTHA CECILIA | Q31: ACCIDENTE DE TRANSITO | R31: FISCALIA | U31: SGOS. CHASIPANTA XAVIER | V31: 46101 | W31: OF. No. FPSD-FEAT2-0608-2026-0001094-O | X31: MAYOR SOLIS MAYORGA PABLO | Y31: =P31 -> HARO OÑATE MARTHA CECILIA | Z31: ´0601972102 | AA31: 96698265 | AB31: SERVICIO DE GARAJE EXTRA PESADOS (MÁS DE 12 TN) (DIARIOS) | AC31: =(V31-D31)+1 -> 7 | AD31: =IF(AB31="SERVICIO DE GARAJE LIVIANOS (HASTA 3,5 TN A EXCEPCIÓN DE MOTOCICLETAS) (DIARIOS)",3,IF(AB31="SERVICIO DE GARAJE PESADOS (DE 3,51 TN HASTA 12 TN) (DIARIOS)",9,IF(AB31="SERVICIO DE GARAJE (CENTROS DE RETENCIÓN) MOTOCICLETA",1,IF(AB31="SERVICIO DE GARAJE EXTRA PESADOS (MÁS DE 12 TN) (DIARIOS)",15,0)))) -> 15 | AE31: =IFERROR(AD31*AC31,0) -> 105 | AF31: =AA31 -> 96698265 | AG31: 46101 | AH31: 96698265 | AI31: MI NEGOCIO EFECTIVO-MI VECINO BANCO PICHINCHA-MI NEGOCIO EFECTIVO | AJ31: =IF(AI31="","",AI31) -> MI NEGOCIO EFECTIVO-MI VECINO BANCO PICHINCHA-MI NEGOCIO EFECTIVO | AK31: =IF(E31="","",E31) -> 2056 | AL31: SGOS. GUERRERO ALBERTO | AO31: INORME TECNICO PERICIAL DE EVALUO TECNICO MECANICO Y RECONOCIMIENTO DE DAÑOS MATERIALES | AP31: CBOP. LENIN ORLANDO GAVILANEZ AZOGUE | AQ31: =AG31 -> 46101 | AR31: =AH31 -> 96698265 | AS31: =AJ31 -> MI NEGOCIO EFECTIVO-MI VECINO BANCO PICHINCHA-MI NEGOCIO EFECTIVO
A32: 29 | B32: SANTO DOMINGO | C32: CONTROL 120 | D32: 46098 | E32: 2057 | F32: QAA3010 | G32: MERCEDEZ BENZ | H32: CABEZAL | I32: ACTROS 2645 AC | J32: PLOMO | K32: 2024 | L32: W1T954414R0732992 | M32: 460972U1147075 | N32: 20260311709433770701 | O32: SGOP. LOPEZ RICHARD | P32: AGILA LALANGUI OLGA ISABEL | Q32: ACCIDENTE DE TRANSITO | R32: FISCALIA | U32: SGOS. GUERRERO ALBERTO | V32: 46108 | W32: OF. No. FPSD-FEAT2-0608-2026-001221-O | X32: MAYOR. JARA POZO KERLEY EDUARDO | Y32: =P32 -> AGILA LALANGUI OLGA ISABEL | Z32: 1718853326 | AA32: 96859148 | AB32: SERVICIO DE GARAJE EXTRA PESADOS (MAS DE 12 TN) (DIARIOS) | AC32: =(V32-D32)+1 -> 11 | AD32: 15 | AE32: =IFERROR(AD32*AC32,0) -> 165 | AF32: =AA32 -> 96859148 | AG32: 46108 | AH32: 021238 | AI32: BANCO PICHINCHA - MI NEGOCIO EFECTIVO | AJ32: =IF(AI32="","",AI32) -> BANCO PICHINCHA - MI NEGOCIO EFECTIVO | AK32: =IF(E32="","",E32) -> 2057 | AL32: SGOS. CHASIPANTA XAVIER | AO32: INORME TECNICO PERICIAL DE EVALUO TECNICO MECANICO Y RECONOCIMIENTO DE DAÑOS MATERIALES | AP32: CBOP. SARANGO ROBERTO | AQ32: =AG32 -> 46108 | AR32: =AH32 -> 021238 | AS32: =AJ32 -> BANCO PICHINCHA - MI NEGOCIO EFECTIVO
A33: 45 | B33: SANTO DOMINGO | C33: CONTROL 120 | D33: 46098 | E33: 2060 | F33: XCB0016 | G33: HINO | H33: CAMIÓN | I33: FC4JJUA | J33: BLANCO | K33: 2023 | L33: JHDFC4JJU6XX13474 | M33: J05CTF17658 | N33: ´2026031810551959409 | O33: POLI. CACOANGO ALEX | P33: MURILLO VELAZQUEZ STALIN LEONEL | Q33: ACCIDENTE DE TRANSITO | R33: FISCALIA | U33: SGOS. GUERRERO ALBERTO | V33: 46113 | W33: OF. No. FPSD-FEAT3-0609-2026-0001127-O | X33: MAYOR SOLIS MAYORGA PABLO | Y33: =P33 -> MURILLO VELAZQUEZ STALIN LEONEL | Z33: 2350595589 | AA33: 96937060 | AB33: SERVICIO DE GARAJE PESADOS (DE 3,51 TN HASTA 12 TN) (DIARIOS) | AC33: =(V33-D33)+1 -> 16 | AD33: =IF(AB33="SERVICIO DE GARAJE LIVIANOS (HASTA 3,5 TN A EXCEPCIÓN DE MOTOCICLETAS) (DIARIOS)",3,IF(AB33="SERVICIO DE GARAJE PESADOS (DE 3,51 TN HASTA 12 TN) (DIARIOS)",9,IF(AB33="SERVICIO DE GARAJE (CENTROS DE RETENCIÓN) MOTOCICLETA",1,IF(AB33="SERVICIO DE GARAJE EXTRA PESADOS (MÁS DE 12 TN) (DIARIOS)",15,0)))) -> 9 | AE33: =IFERROR(AD33*AC33,0) -> 144 | AF33: =AA33 -> 96937060 | AG33: 46113 | AH33: 3263695 | AI33: BANCO DEL PACIFICO | AJ33: =IF(AI33="","",AI33) -> BANCO DEL PACIFICO | AK33: =IF(E33="","",E33) -> 2060 | AL33: SGOS. CHASIPANTA XAVIER | AO33: INORME TECNICO PERICIAL DE EVALUO TECNICO MECANICO Y RECONOCIMIENTO DE DAÑOS MATERIALES | AP33: CBOS. GUAMAN JEFFERSON | AQ33: =AG33 -> 46113 | AR33: =AH33 -> 3263695 | AS33: =AJ33 -> BANCO DEL PACIFICO
A34: 16 | B34: SANTO DOMINGO | C34: CONTROL 120 | D34: 46103 | E34: 2058 | F34: CAA1101 | G34: INTERNATIONAL | H34: TRACTO CAMIÓN | I34: PROSTAR 6X4 | J34: ROJO | K34: 2012 | L34: 3HSDJAPT8CN121141 | M34: 79529239 | N34: 2026032310204179007 | O34: CBOS. CHASI DAVID | P34: TAPIA LOPEZ EDGAR FERNANDO | Q34: ACCIDENTE DE TRANSITO | R34: FISCALIA | S34: N/A | T34: N/A | U34: SGOS. GUERRERO ALBERTO | V34: 46113 | W34: OFICIO No. FPSD-FEAT3-0609-2026-001130-O | X34: MAYR. SOLIS MAYORGA PABLO ENRIQUE | Y34: TAPIA LOPEZ EDGAR FERNANDO | Z34: 0502060635 | AA34: 96956780 | AB34: SERVICIO DE GARAJE EXTRA PESADOS (MAS DE 12 TN) (DIARIOS) | AC34: =(V34-D34)+1 -> 11 | AD34: 15 | AE34: =IFERROR(AD34*AC34,0) -> 165 | AF34: =AA34 -> 96956780 | AG34: 46113 | AH34: 17427986 | AI34: MI NEGOCIO EFECTIVO | AJ34: =IF(AI34="","",AI34) -> MI NEGOCIO EFECTIVO | AK34: =IF(E34="","",E34) -> 2058 | AL34: SGOS. CHASIPANTA XAVIER | AM34: N/A | AN34: N/A | AO34: INORME TECNICO PERICIAL DE EVALUO TECNICO MECANICO Y RECONOCIMIENTO DE DAÑOS MATERIALES | AP34: CBOP. NASIMBA FABRICIO | AQ34: =AG34 -> 46113 | AR34: =AH34 -> 17427986 | AS34: =AJ34 -> MI NEGOCIO EFECTIVO
A35: 14 | B35: SANTO DOMINGO | C35: CONTROL 120 | D35: 46103 | E35: 2059 | F35: CBL0337 | G35: CHEVROLET | H35: FURGON | I35: FTR 32M | J35: ROJO | K35: 2003 | L35: JALFTR32M37000024 | M35: 6HE1900984 | N35: 202603237112163205 | O35: POLI. SANCHEZ JOSE | P35: CHANGOLUISA VENEGAS OSCAR ROLANDO | Q35: ART. 160 | R35: JUZGADO | S35: N/A | T35: N/A | U35: SGOS. GUERRERO ALBERTO | V35: 46104 | W35: N/A | X35: N/A | Y35: CHANGOLUISA VENEGAS OSACAR RO,ANDO | Z35: 1713838694 | AA35: 96734834 | AB35: SERVICIO DE GARAJE PESADOS (DE 3,51 TN HASTA 12 TN) (DIARIOS) | AC35: =(V35-D35)+1 -> 2 | AD35: 9 | AE35: =IFERROR(AD35*AC35,0) -> 18 | AF35: =AA35 -> 96734834 | AG35: 46104 | AH35: 202603238895620 | AI35: BANCO DEL PACIFICO | AJ35: =IF(AI35="","",AI35) -> BANCO DEL PACIFICO | AK35: =IF(E35="","",E35) -> 2059 | AL35: SGOS. GUERRERO ALBERTO | AM35: N/A | AN35: N/A | AO35: N/A | AP35: N/A | AQ35: =AG35 -> 46104 | AR35: =AH35 -> 202603238895620 | AS35: =AJ35 -> BANCO DEL PACIFICO
A36: 2 | B36: SANTO DOMINGO | C36: CONTROL 120 | D36: 46108 | E36: 2061 | F36: CAE0061 | G36: HINO | I36: FF1JPTZ | J36: BLANCO | K36: 2002 | L36: JHDFF1JPT2XX10220 | M36: J08CTT11016 | N36: 2026032703225956301 | O36: SGOS. BRAVO HENRY | P36: LARA PAREDES PABLO WILMER | Q36: ACCIDENTE DE TRANSITO | R36: FISCALIA | S36: N/A | T36: N/A | U36: SGOS. CHASIPANTA XAVIER | AC36: =(V36-D36)+1 -> -46107 | AD36: =IF(AB36="SERVICIO DE GARAJE LIVIANOS (HASTA 3,5 TN A EXCEPCIÓN DE MOTOCICLETAS) (DIARIOS)",3,IF(AB36="SERVICIO DE GARAJE PESADOS (DE 3,51 TN HASTA 12 TN) (DIARIOS)",9,IF(AB36="SERVICIO DE GARAJE (CENTROS DE RETENCIÓN) MOTOCICLETA",1,IF(AB36="SERVICIO DE GARAJE EXTRA PESADOS (MÁS DE 12 TN) (DIARIOS)",15,0)))) -> 0 | AE36: =IFERROR(AD36*AC36,0) -> 0 | AF36: =AA36 -> 0 | AJ36: =IF(AI36="","",AI36) | AK36: =IF(E36="","",E36) -> 2061 | AM36: N/A | AN36: N/A | AQ36: =AG36 -> 0 | AR36: =AH36 -> 0 | AS36: =AJ36
A37: 3 | B37: SANTO DOMINGO | C37: CONTROL 120 | D37: 46109 | E37: 2062 | F37: TBB2616 | G37: JAC | H37: CAMIÓN | I37: HFC1035KD | J37: BLANCO | K37: 2010 | L37: LJ11KBACXA6000780 | M37: 94011328 | N37: 2026032809402780510 | O37: CBOP. GARCIA MANUEL | P37: VALERA VILLAVICENCIO CHISTIAN | Q37: ACCIDENTE DE TRANSITO | R37: FISCALIA | S37: N/A | T37: N/A | U37: POLI. TIPAN KEVIN | V37: 46156 | W37: OF. No. FPSD-FEAT3-0609-2026-001632-O | X37: MAYR. SUAREZ JACOME JUAN CARLOS | Y37: VALERA VILLAVICENCIO CHRISTIAN EMMANUEL | Z37: 1726674011 | AB37: SERVICIO DE GARAJE LIVIANOS (HASTA 3,5 TN A EXCEPCIÓN DE MOTOCICLETAS) (DIARIOS) | AC37: =(V37-D37)+1 -> 48 | AD37: =IF(AB37="SERVICIO DE GARAJE LIVIANOS (HASTA 3,5 TN A EXCEPCIÓN DE MOTOCICLETAS) (DIARIOS)",3,IF(AB37="SERVICIO DE GARAJE PESADOS (DE 3,51 TN HASTA 12 TN) (DIARIOS)",9,IF(AB37="SERVICIO DE GARAJE (CENTROS DE RETENCIÓN) MOTOCICLETA",1,IF(AB37="SERVICIO DE GARAJE EXTRA PESADOS (MÁS DE 12 TN) (DIARIOS)",15,0)))) -> 3 | AE37: =IFERROR(AD37*AC37,0) -> 144 | AF37: =AA37 -> 0 | AG37: 46156 | AH37: 98092628 | AI37: SERVIPAGOS AGENTE | AJ37: =IF(AI37="","",AI37) -> SERVIPAGOS AGENTE | AK37: =IF(E37="","",E37) -> 2062 | AL37: POLI. ESCOBAR NIXON | AM37: N/A | AN37: N/A | AQ37: =AG37 -> 46156 | AR37: =AH37 -> 98092628 | AS37: =AJ37 -> SERVIPAGOS AGENTE
A38: 15 | B38: SANTO DOMINGO | C38: CONTROL 120 | D38: 46109 | E38: 2063 | F38: JEI1029 | G38: HINO | H38: VOLQUETA | I38: GH1JGUD | J38: AMARILLO | K38: 2010 | L38: 9F3GH1JGUAXX13056 | M38: J08CTT39521 | N38: 2026032809402780510 | O38: CBOP. GARCIA MANUEL | P38: GAD STO. DOMINGO | Q38: ACCIDENTE TRANSITO | R38: FISCALIA | S38: N/A | T38: N/A | U38: POLI. TIPAN KEVIN | V38: 46121 | W38: OFICIO No. FPSD-FEAT3-0609-2026-001190-O | X38: MAYR. SUAREZ JACOME JUAN | Y38: ROJAS PEDRERA ADRIANA ALEXANDRA | Z38: 1719428508 | AA38: 97116636 | AB38: SERVICIO DE GARAJE EXTRA PESADOS (MAS DE 12 TN) (DIARIOS) | AC38: =(V38-D38)+1 -> 13 | AD38: 15 | AE38: =IFERROR(AD38*AC38,0) -> 195 | AF38: =AA38 -> 97116636 | AG38: 46121 | AH38: 17473943 | AI38: MI NEGOCIO EFECTIVO | AJ38: =IF(AI38="","",AI38) -> MI NEGOCIO EFECTIVO | AK38: =IF(E38="","",E38) -> 2063 | AL38: POLI. ESCOBAR NIXON | AM38: N/A | AN38: N/A | AO38: INORME TECNICO PERICIAL DE EVALUO TECNICO MECANICO Y RECONOCIMIENTO DE DAÑOS MATERIALES | AP38: SGOS. CRUZ DANILO | AQ38: =AG38 -> 46121 | AR38: =AH38 -> 17473943 | AS38: =AJ38 -> MI NEGOCIO EFECTIVO
A39: 4 | B39: SANTO DOMINGO | C39: CONTROL 120 | D39: 46116 | E39: 2064 | F39: GBQ1564 | G39: HINO | I39: FC9JJ7A-BBAHFAA AC 5.1 2P 4X2 TM DIESEL | J39: BLANCO | K39: 2025 | L39: 9F3FC9JJ7SXX12899 | M39: J05EVC14384 | O39: SGOS. ANDAGOYA GERMAN | P39: TORRES NIETO JORGE ABRAHAM | Q39: ART. 160 | R39: N/A | S39: N/A | T39: N/A | U39: POLI. HURTADO KLEVER | AC39: =(V39-D39)+1 -> -46115 | AD39: =IF(AB39="SERVICIO DE GARAJE LIVIANOS (HASTA 3,5 TN A EXCEPCIÓN DE MOTOCICLETAS) (DIARIOS)",3,IF(AB39="SERVICIO DE GARAJE PESADOS (DE 3,51 TN HASTA 12 TN) (DIARIOS)",9,IF(AB39="SERVICIO DE GARAJE (CENTROS DE RETENCIÓN) MOTOCICLETA",1,IF(AB39="SERVICIO DE GARAJE EXTRA PESADOS (MÁS DE 12 TN) (DIARIOS)",15,0)))) -> 0 | AE39: =IFERROR(AD39*AC39,0) -> 0 | AF39: =AA39 -> 0 | AJ39: =IF(AI39="","",AI39) | AK39: =IF(E39="","",E39) -> 2064 | AM39: N/A | AN39: N/A | AQ39: =AG39 -> 0 | AR39: =AH39 -> 0 | AS39: =AJ39
A40: 28 | B40: SANTO DOMINGO | C40: CONTROL 120 | D40: 46117 | E40: 2065 | F40: TAT0311 | G40: HINO | H40: AUTOBUS | I40: GD1JPTZ | J40: AZUL | K40: 2005 | L40: JHDGD1JPT5XX11460 | M40: J08CTW13590 | N40: 2026040610455152911 | O40: POLI. MENDOZA LEONEL | P40: GUANOQUIZA VALIENTE MILTON PATRICIO | Q40: ART. 386 INCISO 3 #1 | R40: N/A | U40: POLI. LUNA XAVIER | V40: 46137 | W40: OF. No PN-SZSDT-JPCTSV-DIG-2026-0108-O | X40: CBOS. MONAR GUAÑA GENESIS ELIZABETH | Y40: =P40 -> GUANOQUIZA VALIENTE MILTON PATRICIO | Z40: 0502919780 | AA40: 97524839/97528534 | AB40: SERVICIO DE GARAJE EXTRA PESADOS (MAS DE 12 TN) (DIARIOS) | AC40: =(V40-D40)+1 -> 21 | AD40: 15 | AE40: =IFERROR(AD40*AC40,0) -> 315 | AF40: =AA40 -> 97524839/97528534 | AG40: 24/04/2026 25/04/2026 | AH40: 202604243613480 202604253816371 | AI40: BANCO GUAYAQUIL | AJ40: =IF(AI40="","",AI40) -> BANCO GUAYAQUIL | AK40: =IF(E40="","",E40) -> 2065 | AL40: SGOS. CHASIPANTA XAVIER | AO40: N/A | AP40: N/A | AQ40: 24/04/2026 25/04/2026 | AR40: =AH40 -> 202604243613480 202604253816371 | AS40: =AJ40 -> BANCO GUAYAQUIL
A41: 17 | B41: SANTO DOMINGO | C41: CONTROL 120 | D41: 46122 | E41: 2066 | F41: PAA8922 | G41: CHEVROLET | H41: CAMIÓN | I41: FRR 90L 5 2 2P 4X2 TM DIESEL | J41: BLANCO | K41: 2019 | L41: JALFRR90LK7000011 | M41: 4HK1682249 | N41: 202604100449574102 | O41: CBOS. MERIZALDE NICK | P41: PAEZ MIÑIZ JORGE REINALDO | Q41: ACCIDENTE DE TRANSITO | R41: FISCALIA | S41: N/A | T41: N/A | U41: SGOS. CHASIPANTA XAVIER | V41: 46134 | W41: OFICIO No. FPSD-FEAT3-0609-2026-001325-O | X41: MAYR. SUAREZ JACOME JUAN | Y41: PAEZ MUÑIZ JORGE REINALDO | Z41: 1723853600 | AA41: 97420031 | AB41: SERVICIO DE GARAJE PESADOS (DE 3,51 TN HASTA 12 TN) (DIARIOS) | AC41: =(V41-D41)+1 -> 13 | AD41: 9 | AE41: =IFERROR(AD41*AC41,0) -> 117 | AF41: =AA41 -> 97420031 | AG41: 46134 | AH41: 17555437 | AI41: MI NEGOCIO EFECTIVO | AJ41: =IF(AI41="","",AI41) -> MI NEGOCIO EFECTIVO | AK41: =IF(E41="","",E41) -> 2066 | AL41: POLI. ESCOBAR NIXON | AM41: N/A | AN41: N/A | AO41: INORME TECNICO PERICIAL DE EVALUO TECNICO MECANICO Y RECONOCIMIENTO DE DAÑOS MATERIALES | AP41: CBOS. GUAMAN JEFFERSON | AQ41: =AG41 -> 46134 | AR41: =AH41 -> 17555437 | AS41: =AJ41 -> MI NEGOCIO EFECTIVO
A42: 5 | B42: SANTO DOMINGO | C42: CONTROL 120 | D42: 46123 | E42: 2067 | F42: B8K0897 | G42: FREIGHTLINER | J42: BLANCO | L42: 3AKJA6CG7BDAW4524 | M42: 06R1037992 | N42: 202604100449574102 | O42: SGOS. PILCO EDGAR | P42: TERRACARGO S.A. CERRADA | Q42: ACCIDENTE DE TRANSITO | R42: FISCALIA | S42: N/A | T42: N/A | U42: SGOS. CHASIPANTA XAVIER | AC42: =(V42-D42)+1 -> -46122 | AD42: =IF(AB42="SERVICIO DE GARAJE LIVIANOS (HASTA 3,5 TN A EXCEPCIÓN DE MOTOCICLETAS) (DIARIOS)",3,IF(AB42="SERVICIO DE GARAJE PESADOS (DE 3,51 TN HASTA 12 TN) (DIARIOS)",9,IF(AB42="SERVICIO DE GARAJE (CENTROS DE RETENCIÓN) MOTOCICLETA",1,IF(AB42="SERVICIO DE GARAJE EXTRA PESADOS (MÁS DE 12 TN) (DIARIOS)",15,0)))) -> 0 | AE42: =IFERROR(AD42*AC42,0) -> 0 | AF42: =AA42 -> 0 | AJ42: =IF(AI42="","",AI42) | AK42: =IF(E42="","",E42) -> 2067 | AM42: N/A | AN42: N/A | AQ42: =AG42 -> 0 | AR42: =AH42 -> 0 | AS42: =AJ42
A43: 6 | B43: SANTO DOMINGO | C43: CONTROL 120 | D43: 46128 | E43: 2068 | F43: LBX0099 | G43: HINO | H43: PLATAFORMA | I43: FS1KRTA | J43: BLANCO | K43: 2002 | L43: JHDFS1KRT2XX10022 | M43: K13CTU10136 | N43: 2026041603160431611 | O43: SGOS. BRAVO HENRY | P43: CORTEZ ROGEL ELIZABETH | Q43: ACCIDENTE DE TRANSITO | R43: FISCALIA | S43: N/A | T43: N/A | U43: POLI. ESCOBAR NIXON | V43: 46162 | W43: OF. No. FPSD-FEAT2-0608-2026-001636-O | X43: MAYR. SUAREZ JACOME JUAN CARLOS | Y43: CORTEZ ROGEL ELIZABETH AMALIA | Z43: 0802740647 | AA43: 98167105 | AB43: SERVICIO DE GARAJE EXTRA PESADOS (MÁS DE 12 TN) (DIARIOS) | AC43: =(V43-D43)+1 -> 35 | AD43: =IF(AB43="SERVICIO DE GARAJE LIVIANOS (HASTA 3,5 TN A EXCEPCIÓN DE MOTOCICLETAS) (DIARIOS)",3,IF(AB43="SERVICIO DE GARAJE PESADOS (DE 3,51 TN HASTA 12 TN) (DIARIOS)",9,IF(AB43="SERVICIO DE GARAJE (CENTROS DE RETENCIÓN) MOTOCICLETA",1,IF(AB43="SERVICIO DE GARAJE EXTRA PESADOS (MÁS DE 12 TN) (DIARIOS)",15,0)))) -> 15 | AE43: =IFERROR(AD43*AC43,0) -> 525 | AF43: =AA43 -> 98167105 | AG43: 46162 | AH43: 202605203864720 | AI43: MI NEGOCIO EFECTIVO BANCO PACIFICO | AJ43: =IF(AI43="","",AI43) -> MI NEGOCIO EFECTIVO BANCO PACIFICO | AK43: =IF(E43="","",E43) -> 2068 | AL43: SGOS. CHASIPANTA XAVIER | AM43: N/A | AN43: N/A | AO43: INORME TECNICO PERICIAL DE EVALUO TECNICO MECANICO Y RECONOCIMIENTO DE DAÑOS MATERIALES | AQ43: =AG43 -> 46162 | AR43: =AH43 -> 202605203864720 | AS43: =AJ43 -> MI NEGOCIO EFECTIVO BANCO PACIFICO
A44: 32 | B44: SANTO DOMINGO | C44: CONTROL 120 | D44: 46134 | E44: 2069 | F44: XAA1507 | G44: FOTON | H44: TRACTO CAMIÓN | I44: BJ41183SLFJA-2 AC 11,6 2P 4X2 TM DIESEL | J44: DORADO | K44: 2025 | L44: LVBS6PEB9EH200011 | M44: 1112S012789 | N44: ´2026042208143572112 | O44: CBOP. GUALLPA HECTOR | P44: PINANGO JUAN FRANCISCO | Q44: ACCIDENTE DE TRANSITO | R44: FISCALIA | U44: POLI. ESCOBAR NIXON | V44: 46139 | W44: OF. No. FPSD-FEAT3-0609-2026-001456-O | X44: MAYOR. JARA POZO KERLEY EDUARDO | Y44: =P44 -> PINANGO JUAN FRANCISCO | Z44: 1709076234 | AA44: 97576553 | AB44: SERVICIO DE GARAJE EXTRA PESADOS (MÁS DE 12 TN) (DIARIOS) | AC44: =(V44-D44)+1 -> 6 | AD44: =IF(AB44="SERVICIO DE GARAJE LIVIANOS (HASTA 3,5 TN A EXCEPCIÓN DE MOTOCICLETAS) (DIARIOS)",3,IF(AB44="SERVICIO DE GARAJE PESADOS (DE 3,51 TN HASTA 12 TN) (DIARIOS)",9,IF(AB44="SERVICIO DE GARAJE (CENTROS DE RETENCIÓN) MOTOCICLETA",1,IF(AB44="SERVICIO DE GARAJE EXTRA PESADOS (MÁS DE 12 TN) (DIARIOS)",15,0)))) -> 15 | AE44: =IFERROR(AD44*AC44,0) -> 90 | AF44: =AA44 -> 97576553 | AG44: 46139 | AH44: 3858074 | AI44: BANCO PACIFICO | AJ44: =IF(AI44="","",AI44) -> BANCO PACIFICO | AK44: =IF(E44="","",E44) -> 2069 | AL44: SGOS. CHASIPANTA XAVIER | AO44: INORME TECNICO PERICIAL DE EVALUO TECNICO MECANICO Y RECONOCIMIENTO DE DAÑOS MATERIALES | AP44: CBOS. GUAMAN FREIRE JEFFERSON GUILLERMO | AQ44: =AG44 -> 46139 | AR44: =AH44 -> 3858074 | AS44: =AJ44 -> BANCO PACIFICO
A45: 12 | B45: SANTO DOMINGO | C45: CONTROL 120 | D45: 46135 | E45: 2070 | F45: TDV0954 | G45: HINO | H45: CAMIÓN | I45: FVR 23P | J45: BLANCO | K45: 2009 | L45: JALFVR23P97000107 | M45: 6SD1418711 | N45: 2026042310012581806 | O45: SGOS. SANTILLAN CARLOS | P45: LEVERONE ARBOLEDA GARY CRISTHOPER | Q45: ACCIDENTE DE TRANSITO | R45: FISCALIA | S45: N/A | T45: N/A | U45: SGOS. CHASIPANTA XAVIER | V45: 46148 | W45: OFICIO No. FPSD-FEAT1-0258-2026-001603-O | X45: MAYR. SUAREZ JACOME JUAN CARLOS | Y45: LEVERONE ARBOLEDA GARY CRISTHOPER | Z45: 0802813675 | AA45: 97801223 | AB45: SERVICIO DE GARAJE PESADOS (DE 3,51 TN HASTA 12 TN) (DIARIOS) | AC45: =(V45-D45)+1 -> 14 | AD45: 9 | AE45: =IFERROR(AD45*AC45,0) -> 126 | AF45: =AA45 -> 97801223 | AG45: 46148 | AH45: 17650247 | AI45: MI NEGOCIO EFECTIVO | AJ45: =IF(AI45="","",AI45) -> MI NEGOCIO EFECTIVO | AK45: =IF(E45="","",E45) -> 2070 | AL45: POLI. ESCOBAR NIXON | AM45: N/A | AN45: N/A | AO45: INORME TECNICO PERICIAL DE EVALUO TECNICO MECANICO Y RECONOCIMIENTO DE DAÑOS MATERIALES | AP45: ICAZA DANIEL | AQ45: =AG45 -> 46148 | AR45: =AH45 -> 17650247 | AS45: =AJ45 -> MI NEGOCIO EFECTIVO
A46: 13 | B46: SANTO DOMINGO | C46: CONTROL 120 | D46: 46145 | E46: 2071 | F46: IAI0267 | G46: CHEVROLET | H46: BUS | I46: FTR32M | J46: ANARANJADO | K46: 2006 | L46: 8LHFTR32M67000129 | M46: 6HE1406615 | N46: 2026050302104185307 | O46: SGOS. BRAVO HENRY | P46: BARONA FIALLOS ANGEL GUSTAVO | Q46: ACCIDENTE DE TRANSITO | R46: FISCALIA | S46: N/A | T46: N/A | U46: SGOS. CHASIPANTA XAVIER | V46: 46148 | W46: OFICIO No. FPSD-FEAT2-3072-2026-000163-O | X46: MAYR. SUAREZ JACOME JUAN CARLOS | Y46: BARONA FIALLOS ANGEL GUSTAVO | Z46: 1711484004 | AA46: 97803749 | AB46: SERVICIO DE GARAJE PESADOS (DE 3,51 TN HASTA 12 TN) (DIARIOS) | AC46: =(V46-D46)+1 -> 4 | AD46: 9 | AE46: =IFERROR(AD46*AC46,0) -> 36 | AF46: =AA46 -> 97803749 | AG46: 46148 | AH46: 17650939 | AI46: SERVIPAGOS | AJ46: =IF(AI46="","",AI46) -> SERVIPAGOS | AK46: =IF(E46="","",E46) -> 2071 | AL46: POLI. ESCOBAR NIXON | AM46: N/A | AN46: N/A | AO46: INORME TECNICO PERICIAL DE EVALUO TECNICO MECANICO Y RECONOCIMIENTO DE DAÑOS MATERIALES | AP46: CBOS. SANTILLAN CASTILLO | AQ46: =AG46 -> 46148 | AR46: =AH46 -> 17650939 | AS46: =AJ46 -> SERVIPAGOS
A47: 7 | B47: SANTO DOMINGO | C47: CONTROL 120 | D47: 46148 | E47: 2072 | F47: KAA1690 | G47: HINO | H47: CAMIÓN | I47: FM2PL7D-SG3 AC 10.5 2P 6X4 TM DIESEL | J47: AMARILLO | K47: 2018 | L47: 9F3FM2PL7JXX10071 | M47: P11CVT20240 | N47: 2026050611324782113 | O47: CBOP. RENGEL JULIO | P47: CAMACHO CAMACHO RENE WILFRIDO | Q47: ACCIDENTE DE TRANSITO | R47: FISCALIA | S47: N/A | T47: N/A | U47: POLI. ESCOBAR NIXON | V47: 46162 | W47: OF. No. FPSD-FEAT2-0608-2026-001866-O | X47: MAYR. SUAREZ JACOME JUAN CARLOS | Y47: CAMACHO CAMACHO RENE WILFRIDO | Z47: 1707682702 | AA47: 98187956 | AB47: SERVICIO DE GARAJE EXTRA PESADOS (MÁS DE 12 TN) (DIARIOS) | AC47: =(V47-D47)+1 -> 15 | AD47: =IF(AB47="SERVICIO DE GARAJE LIVIANOS (HASTA 3,5 TN A EXCEPCIÓN DE MOTOCICLETAS) (DIARIOS)",3,IF(AB47="SERVICIO DE GARAJE PESADOS (DE 3,51 TN HASTA 12 TN) (DIARIOS)",9,IF(AB47="SERVICIO DE GARAJE (CENTROS DE RETENCIÓN) MOTOCICLETA",1,IF(AB47="SERVICIO DE GARAJE EXTRA PESADOS (MÁS DE 12 TN) (DIARIOS)",15,0)))) -> 15 | AE47: =IFERROR(AD47*AC47,0) -> 225 | AF47: =AA47 -> 98187956 | AG47: 46162 | AH47: 98187956 | AI47: MI NEGOCIO EFECTIVO BANCO PICHINCHA | AJ47: =IF(AI47="","",AI47) -> MI NEGOCIO EFECTIVO BANCO PICHINCHA | AK47: =IF(E47="","",E47) -> 2072 | AL47: SGOS. CHASIPANTA XAVIER | AM47: N/A | AN47: N/A | AO47: INORME TECNICO PERICIAL DE EVALUO TECNICO MECANICO Y RECONOCIMIENTO DE DAÑOS MATERIALES | AP47: CBOS. JONATHAN ISMAEL ARMIJOS MEJIA | AQ47: =AG47 -> 46162 | AR47: =AH47 -> 98187956 | AS47: =AJ47 -> MI NEGOCIO EFECTIVO BANCO PICHINCHA
A48: 8 | B48: SANTO DOMINGO | C48: CONTROL 120 | D48: 46150 | E48: 2073 | F48: JAA1756 | G48: HINO | H48: BUS | I48: AK8JRSA AC 7.7 1P 4X2 TM DIESEL | J48: ROJO | K48: 2016 | L48: JHDAK8JRSGXX13605 | M48: J08EUD25342 | N48: 2026050907541948413 | O48: SGOS. BRAVO HENRY | P48: COQUE TONATO JUAN | Q48: ACCIDENTE DE TRANSITO | R48: FISCALIA | S48: N/A | T48: N/A | U48: POLI. ESCOBAR NIXON | V48: 46157 | W48: OF. No. FPSD-FEAT3-0609-2026-001663-O | X48: MAYR. SUAREZ JACOME JUAN CARLOS | Y48: COQUE TONATO JUAN JOSE | Z48: 0500720537 | AB48: SERVICIO DE GARAJE PESADOS (DE 3,51 TN HASTA 12 TN) (DIARIOS) | AC48: =(V48-D48)+1 -> 8 | AD48: =IF(AB48="SERVICIO DE GARAJE LIVIANOS (HASTA 3,5 TN A EXCEPCIÓN DE MOTOCICLETAS) (DIARIOS)",3,IF(AB48="SERVICIO DE GARAJE PESADOS (DE 3,51 TN HASTA 12 TN) (DIARIOS)",9,IF(AB48="SERVICIO DE GARAJE (CENTROS DE RETENCIÓN) MOTOCICLETA",1,IF(AB48="SERVICIO DE GARAJE EXTRA PESADOS (MÁS DE 12 TN) (DIARIOS)",15,0)))) -> 9 | AE48: =IFERROR(AD48*AC48,0) -> 72 | AF48: 98134670 | AG48: 46157 | AH48: 98134670 | AI48: MI NEGOCIO EFECTIVO BANCO PICHINCHA | AJ48: =IF(AI48="","",AI48) -> MI NEGOCIO EFECTIVO BANCO PICHINCHA | AK48: =IF(E48="","",E48) -> 2073 | AL48: POLI. ESCOBAR NIXON | AM48: N/A | AN48: N/A | AO48: INORME TECNICO PERICIAL DE EVALUO TECNICO MECANICO Y RECONOCIMIENTO DE DAÑOS MATERIALES | AP48: CBOP. LENIN ORLANDO GAVILANEZ AZOGUE | AQ48: =AG48 -> 46157 | AR48: =AH48 -> 98134670 | AS48: =AJ48 -> MI NEGOCIO EFECTIVO BANCO PICHINCHA
A49: 9 | B49: SANTO DOMINGO | C49: CONTROL 120 | D49: 46154 | E49: 2074 | F49: PUK0033 | G49: FREIGHTLINER | H49: TRACTO CAMIÓN | I49: FLD 120 | J49: BLANCO | K49: 2008 | L49: 3AKJALCG98DZ68539 | M49: 06R0982790 | N49: 20260512095053535006 | O49: SGOS. BONILLA PAUL | P49: MEDRANO JARRIN FERNANDO | Q49: ACCIDENTE DE TRANSITO | R49: FISCALIA | S49: N/A | T49: N/A | U49: SGOS. CHASIPANTA XAVIER | V49: 46182 | W49: OF. No. FPSD-FEAT2-0608-2026-002039-O | X49: CPTN. IZA VILLENA RODNEY ESTEBAN | Y49: MATA GUZMAN PABLO SANTIAGO | Z49: 1719633438 | AA49: 98757315 | AB49: SERVICIO DE GARAJE EXTRA PESADOS (MÁS DE 12 TN) (DIARIOS) | AC49: =(V49-D49)+1 -> 29 | AD49: =IF(AB49="SERVICIO DE GARAJE LIVIANOS (HASTA 3,5 TN A EXCEPCIÓN DE MOTOCICLETAS) (DIARIOS)",3,IF(AB49="SERVICIO DE GARAJE PESADOS (DE 3,51 TN HASTA 12 TN) (DIARIOS)",9,IF(AB49="SERVICIO DE GARAJE (CENTROS DE RETENCIÓN) MOTOCICLETA",1,IF(AB49="SERVICIO DE GARAJE EXTRA PESADOS (MÁS DE 12 TN) (DIARIOS)",15,0)))) -> 15 | AE49: =IFERROR(AD49*AC49,0) -> 435 | AF49: =AA49 -> 98757315 | AG49: 46182 | AH49: 4871034 | AI49: BANCO PACIFICO | AJ49: =IF(AI49="","",AI49) -> BANCO PACIFICO | AK49: =IF(E49="","",E49) -> 2074 | AL49: SGOS. CHASIPANTA XAVIER | AM49: N/A | AN49: N/A | AO49: INORME TECNICO PERICIAL DE EVALUO TECNICO MECANICO Y RECONOCIMIENTO DE DAÑOS MATERIALES | AP49: POLI. HERRERA ORDOÑEZ ANTHONY STEEVEN | AQ49: =AG49 -> 46182 | AR49: =AH49 -> 4871034 | AS49: =AJ49 -> BANCO PACIFICO
A50: 11 | B50: SANTO DOMINGO | C50: CONTROL 120 | D50: 46154 | E50: 2075 | F50: MBE7165 | G50: HINO | H50: CAMIÓN | I50: XZU640L-HKMLJ3 AC 4.0 2P 4X2 TM DIESEL | J50: BLANCO | K50: 2020 | L50: 9F3BCJ4H5L2108076 | M50: N04CUY18288 | N50: 20260512095053535006 | O50: SGOS. BONILLA PAUL | P50: MEDRANO JARRIN FERNANDO | Q50: ACCIDENTE DE TRANSITO | R50: FISCALIA | S50: N/A | T50: N/A | U50: SGOS. CHASIPANTA XAVIER | V50: 46168 | W50: OFICIO No. FPSD-FEAT2-0608-2026-001909-O | X50: MAYR. SUAREZ JACOME JUAN CARLOS | Y50: FERNANDEZ MEZA GEAN KAISSUS | Z50: 1307161321 | AA50: 98310705 | AB50: SERVICIO DE GARAJE LIVIANOS (HASTA 3,5 TN A EXCEPCIÓN DE MOTOCICLETAS) (DIARIOS) | AC50: =(V50-D50)+1 -> 15 | AD50: 3 | AE50: =IFERROR(AD50*AC50,0) -> 45 | AF50: =AA50 -> 98310705 | AG50: 46168 | AH50: 98310705 | AI50: MI NEGOCIO EFECTIVO BANCO PICHINCHA | AJ50: =IF(AI50="","",AI50) -> MI NEGOCIO EFECTIVO BANCO PICHINCHA | AK50: =IF(E50="","",E50) -> 2075 | AL50: SGOS. CHASIPANTA XAVIER | AM50: N/A | AN50: N/A | AO50: INORME TECNICO PERICIAL DE EVALUO TECNICO MECANICO Y RECONOCIMIENTO DE DAÑOS MATERIALES | AP50: POLI. HERRERA ORDOÑEZ ANTHONY STEEVEN | AQ50: =AG50 -> 46168 | AR50: =AH50 -> 98310705 | AS50: =AJ50 -> MI NEGOCIO EFECTIVO BANCO PICHINCHA
A51: 10 | B51: SANTO DOMINGO | C51: CONTROL 120 | D51: 46154 | E51: 2077 | F51: MAA7271 | G51: FREIGHTLINER | I51: M2112C AC 12,8 2P 6X4 TM DIESEL | J51: ROJO | L51: 3AKJC5CV2MDKY3443 | M51: 460908U1050334 | N51: 20260529094550100000 | O51: CBOP. CEDEÑO ITALO | P51: CONFORME LOPEZ DARWIN DAVID | Q51: ACCIDENTE DE TRANSITO | R51: FISCALIA | S51: N/A | T51: N/A | U51: SGOS. CHASIPANTA XAVIER | AC51: =(V51-D51)+1 -> -46153 | AD51: =IF(AB51="SERVICIO DE GARAJE LIVIANOS (HASTA 3,5 TN A EXCEPCIÓN DE MOTOCICLETAS) (DIARIOS)",3,IF(AB51="SERVICIO DE GARAJE PESADOS (DE 3,51 TN HASTA 12 TN) (DIARIOS)",9,IF(AB51="SERVICIO DE GARAJE (CENTROS DE RETENCIÓN) MOTOCICLETA",1,IF(AB51="SERVICIO DE GARAJE EXTRA PESADOS (MÁS DE 12 TN) (DIARIOS)",15,0)))) -> 0 | AE51: =IFERROR(AD51*AC51,0) -> 0 | AF51: =AA51 -> 0 | AJ51: =IF(AI51="","",AI51) | AK51: =IF(E51="","",E51) -> 2077 | AM51: N/A | AN51: N/A | AQ51: =AG51 -> 0 | AR51: =AH51 -> 0 | AS51: =AJ51
A52: 46 | B52: SANTO DOMINGO | C52: CONTROL 120 | D52: 46164 | E52: 2076 | F52: PAD2382 | G52: SINOTRUK | H52: FURGON | I52: HOWO NQS ZZ1067G421CD165 | J52: BLANCO | K52: 2026 | L52: LZZ1BAFE6TF141793 | M52: 77770110 | N52: ´2026052210240013908 | O52: SGOS. PUCUJI EDGAR | P52: ALARCON GUERRERO HUGO LANDIVER | Q52: ART. 386 INCISO 2.1 | R52: N/A | U52: SGOS. CHASIPANTA XAVIER | V52: 46184 | W52: 23281-2026-07967-OFICIO-05409-2026 | X52: TNTE. JORDAN STALIN JAYA VARGAS | Y52: =P52 -> ALARCON GUERRERO HUGO LANDIVER | Z52: 1250443957 | AA52: 98831481 | AB52: SERVICIO DE GARAJE PESADOS (DE 3,51 TN HASTA 12 TN) (DIARIOS) | AC52: =(V52-D52)+1 -> 21 | AD52: =IF(AB52="SERVICIO DE GARAJE LIVIANOS (HASTA 3,5 TN A EXCEPCIÓN DE MOTOCICLETAS) (DIARIOS)",3,IF(AB52="SERVICIO DE GARAJE PESADOS (DE 3,51 TN HASTA 12 TN) (DIARIOS)",9,IF(AB52="SERVICIO DE GARAJE (CENTROS DE RETENCIÓN) MOTOCICLETA",1,IF(AB52="SERVICIO DE GARAJE EXTRA PESADOS (MÁS DE 12 TN) (DIARIOS)",15,0)))) -> 9 | AE52: =IFERROR(AD52*AC52,0) -> 189 | AF52: =AA52 -> 98831481 | AG52: 46184 | AH52: 4921568 | AI52: BANCO DEL PACIFICO | AJ52: =IF(AI52="","",AI52) -> BANCO DEL PACIFICO | AK52: =IF(E52="","",E52) -> 2076 | AL52: POLI. ESCOBAR NIXON | AM52: 98764761 | AN52: 85 | AO52: N/A | AP52: N/A | AQ52: =AG52 -> 46184 | AR52: =AH52 -> 4921568 | AS52: =AJ52 -> BANCO DEL PACIFICO
A53: 47 | B53: SANTO DOMINGO | C53: CONTROL 120 | D53: 46174 | E53: 2078 | F53: JAA1752 | G53: HINO | H53: BUS | I53: AK8JRSA-RETARD AC 7.7 1P 4X2 TM DIESEL | J53: ROJO | K53: 2016 | L53: JHDAK8JRSGXX13635 | M53: J08EUD25396 | N53: 2.0260601e+18 | O53: SGOS. PINZON DIEGO | P53: SUAREZ CONTRERA YANET MARYURU | Q53: ACCIDENTE DE TRANSITO | R53: FISCALIA | U53: POLI. ESCOBAR NIXON | V53: 46178 | W53: OF. No. FPSD-FEAT1-0258-2026-0001966-O | X53: CPTN. IZA VILLENA RODNEY ESTEBAN | Y53: =P53 -> SUAREZ CONTRERA YANET MARYURU | Z53: 0801624610 | AA53: 98674599 | AB53: SERVICIO DE GARAJE PESADOS (DE 3,51 TN HASTA 12 TN) (DIARIOS) | AC53: =(V53-D53)+1 -> 5 | AD53: =IF(AB53="SERVICIO DE GARAJE LIVIANOS (HASTA 3,5 TN A EXCEPCIÓN DE MOTOCICLETAS) (DIARIOS)",3,IF(AB53="SERVICIO DE GARAJE PESADOS (DE 3,51 TN HASTA 12 TN) (DIARIOS)",9,IF(AB53="SERVICIO DE GARAJE (CENTROS DE RETENCIÓN) MOTOCICLETA",1,IF(AB53="SERVICIO DE GARAJE EXTRA PESADOS (MÁS DE 12 TN) (DIARIOS)",15,0)))) -> 9 | AE53: =IFERROR(AD53*AC53,0) -> 45 | AF53: =AA53 -> 98674599 | AG53: 46178 | AH53: 48646959 | AI53: MI NEGOCIO EFECTIVO BANCO PACIFICO | AJ53: =IF(AI53="","",AI53) -> MI NEGOCIO EFECTIVO BANCO PACIFICO | AK53: =IF(E53="","",E53) -> 2078 | AL53: POLI. ESCOBAR NIXON | AO53: INORME TECNICO PERICIAL DE EVALUO TECNICO MECANICO Y RECONOCIMIENTO DE DAÑOS MATERIALES | AP53: CBOP. SARANGO ROBERTO | AQ53: =AG53 -> 46178 | AR53: 48646959 | AS53: =AJ53 -> MI NEGOCIO EFECTIVO BANCO PACIFICO
A54: 48 | B54: SANTO DOMINGO | C54: CONTROL 120 | D54: 46190 | E54: 2079 | F54: TAA3401 | G54: YUTONG | H54: BUS | I54: ZK6129HE EXTENDIDO AC 10.8 1P 4X2 TM DIESEL | J54: AMARILLO | K54: 2014 | L54: LZYTNTF62E1001183 | M54: 71027389 | N54: ´2026061800331883308 | O54: CBOS. MADRUÑERO ALEX | P54: HECTOR ISRAEL BABAYO HARO | Q54: ART. 386 INCISO 2.1 | R54: N/A | S54: N/A | T54: N/A | U54: POLI. LUNA XAVIER | V54: 46204 | W54: 18461-2026-02227-OFICIO-02600-2026 | X54: MAYOR SOLIS MAYORGA PABLO | Y54: =P54 -> HECTOR ISRAEL BABAYO HARO | Z54: 1803891226 | AA54: 99317114 | AB54: SERVICIO DE GARAJE EXTRA PESADOS (MÁS DE 12 TN) (DIARIOS) | AC54: =(V54-D54)+1 -> 15 | AD54: =IF(AB54="SERVICIO DE GARAJE LIVIANOS (HASTA 3,5 TN A EXCEPCIÓN DE MOTOCICLETAS) (DIARIOS)",3,IF(AB54="SERVICIO DE GARAJE PESADOS (DE 3,51 TN HASTA 12 TN) (DIARIOS)",9,IF(AB54="SERVICIO DE GARAJE (CENTROS DE RETENCIÓN) MOTOCICLETA",1,IF(AB54="SERVICIO DE GARAJE EXTRA PESADOS (MÁS DE 12 TN) (DIARIOS)",15,0)))) -> 15 | AE54: =IFERROR(AD54*AC54,0) -> 225 | AF54: =AA54 -> 99317114 | AG54: 46204 | AH54: 99317114 | AI54: BANCO PICHINCHA | AJ54: =IF(AI54="","",AI54) -> BANCO PICHINCHA | AK54: =IF(E54="","",E54) -> 2079 | AL54: CBOP. ITALO CEDEÑO | AM54: N/A | AN54: N/A | AO54: N/A | AP54: N/A | AQ54: =AG54 -> 46204 | AR54: =AH54 -> 99317114 | AS54: =AJ54 -> BANCO PICHINCHA
A55: 49 | B55: SANTO DOMINGO | C55: CONTROL 120 | D55: 46190 | E55: 2080 | F55: GBO5004 | G55: FOTON | H55: TRAILER | I55: AUMAN EST BJ4189 HIGH ROOF AC 10.5 2P 4X2 TM DIESE | J55: PLOMO | L55: LVBS6PEBXRT500725 | M55: ISGE335077512280 | N55: ´2026061800550850208 | O55: SGOS. BONILLA PAUL | P55: MOYA GOMEZ JOSE DANIEL | Q55: ACCIDENTE DE TRANSITO | R55: FISCALIA | U55: POLI. LUNA XAVIER | V55: 46192 | W55: OF. No . 2844-2026-FGE-UFSDT | X55: TCRNL. GALEANO ANDRADE EDISON EDUARDO | Y55: =P55 -> MOYA GOMEZ JOSE DANIEL | Z55: 1721611174 | AA55: 99041653 | AB55: SERVICIO DE GARAJE EXTRA PESADOS (MÁS DE 12 TN) (DIARIOS) | AC55: =(V55-D55)+1 -> 3 | AD55: =IF(AB55="SERVICIO DE GARAJE LIVIANOS (HASTA 3,5 TN A EXCEPCIÓN DE MOTOCICLETAS) (DIARIOS)",3,IF(AB55="SERVICIO DE GARAJE PESADOS (DE 3,51 TN HASTA 12 TN) (DIARIOS)",9,IF(AB55="SERVICIO DE GARAJE (CENTROS DE RETENCIÓN) MOTOCICLETA",1,IF(AB55="SERVICIO DE GARAJE EXTRA PESADOS (MÁS DE 12 TN) (DIARIOS)",15,0)))) -> 15 | AE55: =IFERROR(AD55*AC55,0) -> 45 | AF55: =AA55 -> 99041653 | AG55: 46182 | AH55: 99044653 | AI55: MI NEGOCIO EFECTIVO BANCO PICHINCHA | AJ55: =IF(AI55="","",AI55) -> MI NEGOCIO EFECTIVO BANCO PICHINCHA | AK55: =IF(E55="","",E55) -> 2080 | AL55: SGOS. CHASIPANTA XAVIER | AO55: INORME TECNICO PERICIAL DE EVALUO TECNICO MECANICO Y RECONOCIMIENTO DE DAÑOS MATERIALES | AP55: SGOS. CRUZ CALDERON DANILO FABRICIO | AQ55: =AG55 -> 46182 | AR55: =AH55 -> 99044653 | AS55: =AJ55 -> MI NEGOCIO EFECTIVO BANCO PICHINCHA
A56: 50 | B56: SANTO DOMINGO | C56: CONTROL 120 | D56: 46191 | E56: 2081 | F56: PTL0970 | G56: INTERNACIONAL | H56: VOLQUETA | I56: 4700 4X2 | J56: BLANCO | K56: 2023 | L56: 1HTSCARR2WH548534 | M56: S9HM2U1067427 | N56: ´2026061809194716316 | O56: SGOS. PILCO EDGAR | P56: EXTRACTORA AGRICOLA RIO MANSO EXA S.A. | Q56: ACCIDENTE DE TRANSITO | R56: FISCALIA | S56: N/A | T56: N/A | U56: SGOS. CHASIPANTA XAVIER | V56: 46235 | W56: OF. No. FPSD-FEAT1-0258-2026-0002443-O | X56: TCRNL. GALEANO ANDRADE EDISON EDUARDO | Y56: SEGOVIA RUIZ CARLOS ALBERTO | Z56: 1307482693 | AA56: 100233456 | AB56: SERVICIO DE GARAJE PESADOS (DE 3,51 TN HASTA 12 TN) (DIARIOS) | AC56: =(V56-D56)+1 -> 45 | AD56: =IF(AB56="SERVICIO DE GARAJE LIVIANOS (HASTA 3,5 TN A EXCEPCIÓN DE MOTOCICLETAS) (DIARIOS)",3,IF(AB56="SERVICIO DE GARAJE PESADOS (DE 3,51 TN HASTA 12 TN) (DIARIOS)",9,IF(AB56="SERVICIO DE GARAJE (CENTROS DE RETENCIÓN) MOTOCICLETA",1,IF(AB56="SERVICIO DE GARAJE EXTRA PESADOS (MÁS DE 12 TN) (DIARIOS)",15,0)))) -> 9 | AE56: =IFERROR(AD56*AC56,0) -> 405 | AF56: =AA56 -> 100233456 | AG56: 46235 | AH56: 202608012320820 | AI56: BANCO DEL PACIFICO | AJ56: =IF(AI56="","",AI56) -> BANCO DEL PACIFICO | AK56: =IF(E56="","",E56) -> 2081 | AL56: SGOS. CHASIPANTA XAVIER | AM56: N/A | AN56: N/A | AO56: INORME TECNICO PERICIAL DE EVALUO TECNICO MECANICO Y RECONOCIMIENTO DE DAÑOS MATERIALES | AP56: AGENTE JONATHAN MAURICIO VAICILLAGAROFALO | AQ56: =AG56 -> 46235 | AR56: =AH56 -> 202608012320820 | AS56: =AJ56 -> BANCO DEL PACIFICO
A57: 51 | B57: SANTO DOMINGO | C57: CONTROL 120 | D57: 46191 | E57: 2082 | F57: PAE5655 | G57: SINOTRUK | I57: HOWO T5G ZZ1167M501GC1 AC 6.9 2P 4X2 TM DIESEL | J57: BLANCO | L57: LZZ1BBKF4TA195949 | M57: 250307806307 | N57: ´2026061809194716316 | O57: SGOS. PILCO EDGAR | P57: ORTIZ GARCIA VALERIA ALEJANDRA | Q57: ACCIDENTE DE TRANSITO | R57: FISCALIA | U57: SGOS. CHASIPANTA XAVIER | Y57: =P57 -> ORTIZ GARCIA VALERIA ALEJANDRA | AC57: =(V57-D57)+1 -> -46190 | AD57: =IF(AB57="SERVICIO DE GARAJE LIVIANOS (HASTA 3,5 TN A EXCEPCIÓN DE MOTOCICLETAS) (DIARIOS)",3,IF(AB57="SERVICIO DE GARAJE PESADOS (DE 3,51 TN HASTA 12 TN) (DIARIOS)",9,IF(AB57="SERVICIO DE GARAJE (CENTROS DE RETENCIÓN) MOTOCICLETA",1,IF(AB57="SERVICIO DE GARAJE EXTRA PESADOS (MÁS DE 12 TN) (DIARIOS)",15,0)))) -> 0 | AE57: =IFERROR(AD57*AC57,0) -> 0 | AF57: =AA57 -> 0 | AJ57: =IF(AI57="","",AI57) | AK57: =IF(E57="","",E57) -> 2082 | AQ57: =AG57 -> 0 | AR57: =AH57 -> 0 | AS57: =AJ57
A58: 52 | B58: SANTO DOMINGO | C58: CONTROL 120 | D58: 46199 | E58: 2083 | F58: XAG0291 | G58: HINO | H58: BUS | I58: AK8JRSA AC 7.7 2P 4X2 TM DIESEL | J58: AZUL | K58: 2014 | L58: JHDAK8JRSEXX11946 | M58: J08EUD19611 | N58: ´2026062608132225302 | O58: SGOP. ROJAS WALTER ROBINSON | P58: CEDEÑO YANEZ HUGO FABIAN | Q58: ACCIDENTE DE TRANSITO | R58: FISCALIA | U58: CBOP. ITALO CEDEÑO | V58: 46210 | W58: OF. No. FPSD-FEAT3-0609-2026-002142-O | X58: TCRNL. GALEANO ANDRADE EDISON EDUARDO | Y58: =P58 -> CEDEÑO YANEZ HUGO FABIAN | Z58: 1309276648 | AA58: 99465612 | AB58: SERVICIO DE GARAJE PESADOS (DE 3,51 TN HASTA 12 TN) (DIARIOS) | AC58: =(V58-D58)+1 -> 12 | AD58: =IF(AB58="SERVICIO DE GARAJE LIVIANOS (HASTA 3,5 TN A EXCEPCIÓN DE MOTOCICLETAS) (DIARIOS)",3,IF(AB58="SERVICIO DE GARAJE PESADOS (DE 3,51 TN HASTA 12 TN) (DIARIOS)",9,IF(AB58="SERVICIO DE GARAJE (CENTROS DE RETENCIÓN) MOTOCICLETA",1,IF(AB58="SERVICIO DE GARAJE EXTRA PESADOS (MÁS DE 12 TN) (DIARIOS)",15,0)))) -> 9 | AE58: =IFERROR(AD58*AC58,0) -> 108 | AF58: =AA58 -> 99465612 | AG58: 46210 | AH58: 25646805 | AI58: BANCO DEL PICHINCHA | AJ58: =IF(AI58="","",AI58) -> BANCO DEL PICHINCHA | AK58: =IF(E58="","",E58) -> 2083 | AL58: CBOP. ITALO CEDEÑO | AM58: N/A | AN58: N/A | AO58: INORME TECNICO PERICIAL DE EVALUO TECNICO MECANICO Y RECONOCIMIENTO DE DAÑOS MATERIALES | AP58: CBOP. SARANGO ROBERTO | AQ58: =AG58 -> 46210 | AR58: =AH58 -> 25646805 | AS58: =AJ58 -> BANCO DEL PICHINCHA
A59: 53 | B59: SANTO DOMINGO | C59: CONTROL 120 | D59: 46200 | E59: 2084 | F59: JBE1438 | G59: HINO | H59: CAMIÓN | I59: XZU423L-HKMRD3 | J59: BLANCO | K59: 2011 | L59: 9F3YT20H6B6000370 | M59: N04CTT21100 | N59: ´202606270306365907 | O59: CBOP. IZURIETA MERINO DENNIS | P59: JOSE MARIO ZAMBRANO MENDOZA | Q59: ART. 160 | R59: N/A | S59: N/A | T59: N/A | U59: CBOP. ITALO CEDEÑO | V59: 46202 | W59: OF. No. PN-SZSDT-JPCTV-DIG-2026-096-O | Y59: =P59 -> JOSE MARIO ZAMBRANO MENDOZA | Z59: 1715321350 | AA59: 99244944 | AB59: SERVICIO DE GARAJE PESADOS (DE 3,51 TN HASTA 12 TN) (DIARIOS) | AC59: =(V59-D59)+1 -> 3 | AD59: =IF(AB59="SERVICIO DE GARAJE LIVIANOS (HASTA 3,5 TN A EXCEPCIÓN DE MOTOCICLETAS) (DIARIOS)",3,IF(AB59="SERVICIO DE GARAJE PESADOS (DE 3,51 TN HASTA 12 TN) (DIARIOS)",9,IF(AB59="SERVICIO DE GARAJE (CENTROS DE RETENCIÓN) MOTOCICLETA",1,IF(AB59="SERVICIO DE GARAJE EXTRA PESADOS (MÁS DE 12 TN) (DIARIOS)",15,0)))) -> 9 | AE59: =IFERROR(AD59*AC59,0) -> 27 | AF59: =AA59 -> 99244944 | AG59: 46202 | AH59: 99244944 | AI59: MI NEGOCIO EFECTIVO | AJ59: =IF(AI59="","",AI59) -> MI NEGOCIO EFECTIVO | AK59: =IF(E59="","",E59) -> 2084 | AL59: CBOP. ITALO CEDEÑO | AQ59: =AG59 -> 46202 | AR59: =AH59 -> 99244944 | AS59: =AJ59 -> MI NEGOCIO EFECTIVO
A60: 54 | B60: SANTO DOMINGO | C60: CONTROL 120 | D60: 46200 | E60: 2085 | F60: IAI3101 | G60: HINO | H60: AUTOBUS | I60: AK8JRSA 7,7 4X2 TM DIESEL | J60: AZUL | K60: 2020 | L60: JHDAK8JRSLXX18174 | M60: J08EUD34642 | N60: ´2026062708383249212 | O60: POLI. NEVAREZ MENDOZA LUIS ANGEL | P60: MENDOZA RENDON ORLANDO ALEJANDRO | Q60: ART. 389 NUMERAL 7 | R60: N/A | S60: N/A | T60: N/A | U60: CBOP. ITALO CEDEÑO | V60: 46218 | W60: OF. No. PN-SZSDT-JPCTV-DIG-2026-186-O | X60: TCRNL. GALEANO ANDRADE EDISON EDUARDO | Y60: GUANOTUÑA QUINALUISA MANUEL ISAIAS | Z60: 0502246978 | AA60: 99680762 | AB60: SERVICIO DE GARAJE EXTRA PESADOS (MÁS DE 12 TN) (DIARIOS) | AC60: =(V60-D60)+1 -> 19 | AD60: =IF(AB60="SERVICIO DE GARAJE LIVIANOS (HASTA 3,5 TN A EXCEPCIÓN DE MOTOCICLETAS) (DIARIOS)",3,IF(AB60="SERVICIO DE GARAJE PESADOS (DE 3,51 TN HASTA 12 TN) (DIARIOS)",9,IF(AB60="SERVICIO DE GARAJE (CENTROS DE RETENCIÓN) MOTOCICLETA",1,IF(AB60="SERVICIO DE GARAJE EXTRA PESADOS (MÁS DE 12 TN) (DIARIOS)",15,0)))) -> 15 | AE60: =IFERROR(AD60*AC60,0) -> 285 | AF60: =AA60 -> 99680762 | AG60: 46208 | AH60: 99680762 | AI60: MI NEGOCIO EFECTIVO | AJ60: =IF(AI60="","",AI60) -> MI NEGOCIO EFECTIVO | AK60: =IF(E60="","",E60) -> 2085 | AL60: SGOS. CHASIPANTA XAVIER | AM60: N/A | AN60: N/A | AO60: N/A | AP60: N/A | AQ60: =AG60 -> 46208 | AR60: =AH60 -> 99680762 | AS60: =AJ60 -> MI NEGOCIO EFECTIVO
A61: 55 | B61: SANTO DOMINGO | C61: CONTROL 120 | D61: 46203 | E61: 2086 | F61: KAA2251 | G61: SINOTRUK | H61: CAMIÓN | I61: HOWO T5G ZZ1167N501GC1R AC 6.9 2P | J61: BLANCO | K61: 2023 | L61: LZZ1BBMG5PW962884 | M61: 220107804107 | N61: ´2026063001540128411 | O61: POLI. MENDOZA LEONEL | P61: ARMIJOS GODOY JAHANNA NOEMI | Q61: ART. 160 | R61: N/A | S61: N/A | T61: N/A | U61: SGOS. CHASIPANTA XAVIER | V61: 46211 | W61: OF. No. PN-SZSDT-JPCTV-DIG-2026-169-O | X61: TCRNL. GALEANO ANDRADE EDISON EDUARDO | Y61: =P61 -> ARMIJOS GODOY JAHANNA NOEMI | Z61: 0703663534 | AA61: 99487913 | AB61: SERVICIO DE GARAJE EXTRA PESADOS (MÁS DE 12 TN) (DIARIOS) | AC61: =(V61-D61)+1 -> 9 | AD61: =IF(AB61="SERVICIO DE GARAJE LIVIANOS (HASTA 3,5 TN A EXCEPCIÓN DE MOTOCICLETAS) (DIARIOS)",3,IF(AB61="SERVICIO DE GARAJE PESADOS (DE 3,51 TN HASTA 12 TN) (DIARIOS)",9,IF(AB61="SERVICIO DE GARAJE (CENTROS DE RETENCIÓN) MOTOCICLETA",1,IF(AB61="SERVICIO DE GARAJE EXTRA PESADOS (MÁS DE 12 TN) (DIARIOS)",15,0)))) -> 15 | AE61: =IFERROR(AD61*AC61,0) -> 135 | AF61: =AA61 -> 99487913 | AG61: 46211 | AH61: 8154364 | AI61: BANCO PICHINCHA | AJ61: =IF(AI61="","",AI61) -> BANCO PICHINCHA | AK61: =IF(E61="","",E61) -> 2086 | AL61: SGOS. CHASIPANTA XAVIER | AO61: N/A | AP61: N/A | AQ61: =AG61 -> 46211 | AR61: =AH61 -> 8154364 | AS61: =AJ61 -> BANCO PICHINCHA
A62: 56 | B62: SANTO DOMINGO | C62: CONTROL 120 | D62: 46209 | E62: 2087 | F62: AAA2132 | G62: KENWORTH | H62: TRACTO CAMIÓN | I62: T800 CLASSIC | J62: AZUL | K62: 2013 | L62: 1XKDD40X1DJ717098 | M62: 79602151 | N62: ´2026070610334185509 | O62: SGOS. RODRIGUES JORGE | P62: GUERRA NARVAEZ YOLANDA ROSARIO | Q62: ACCIDENTE DE TRANSITO | R62: FISCALIA | S62: N/A | T62: N/A | U62: SGOS. CHASIPANTA XAVIER | V62: 46215 | W62: OF. No. PN-SZSDT-JPCTV-DIG-2026-179-O | X62: MAYOR SOLIS MAYORGA PABLO | Y62: =P62 -> GUERRA NARVAEZ YOLANDA ROSARIO | Z62: 0401069794 | AA62: 99586702 | AB62: SERVICIO DE GARAJE EXTRA PESADOS (MÁS DE 12 TN) (DIARIOS) | AC62: =(V62-D62)+1 -> 7 | AD62: =IF(AB62="SERVICIO DE GARAJE LIVIANOS (HASTA 3,5 TN A EXCEPCIÓN DE MOTOCICLETAS) (DIARIOS)",3,IF(AB62="SERVICIO DE GARAJE PESADOS (DE 3,51 TN HASTA 12 TN) (DIARIOS)",9,IF(AB62="SERVICIO DE GARAJE (CENTROS DE RETENCIÓN) MOTOCICLETA",1,IF(AB62="SERVICIO DE GARAJE EXTRA PESADOS (MÁS DE 12 TN) (DIARIOS)",15,0)))) -> 15 | AE62: =IFERROR(AD62*AC62,0) -> 105 | AF62: =AA62 -> 99586702 | AG62: 46213 | AH62: 995867702 | AI62: MI NEGOCIO EFECTIVO | AJ62: =IF(AI62="","",AI62) -> MI NEGOCIO EFECTIVO | AK62: =IF(E62="","",E62) -> 2087 | AL62: CBOP. SOLORZANO PEDRO | AM62: N/A | AN62: N/A | AO62: INORME TECNICO PERICIAL DE EVALUO TECNICO MECANICO Y RECONOCIMIENTO DE DAÑOS MATERIALES | AP62: CBOS. GUAMAN JEFFERSON | AQ62: =AG62 -> 46213 | AR62: =AH62 -> 995867702 | AS62: =AJ62 -> MI NEGOCIO EFECTIVO
A63: 57 | B63: SANTO DOMINGO | C63: CONTROL 120 | D63: 46212 | E63: 2088 | F63: PQQ0425 | G63: HINO | H63: CAMIÓN | I63: FC4JJUA | J63: BLANCO | K63: 2007 | L63: JHDFC4JJU7XX12233 | M63: J05CTF14877 | N63: 2026070910554584516 | O63: SGOS. CASTRO CONCHA CARLOS ELIAS | P63: CABSCANGO CHAVEZ LUIS GERMAN | Q63: ART. 160 | R63: N/A | S63: N/A | T63: N/A | U63: CBOP. ITALO CEDEÑO | V63: 46223 | W63: N/A | X63: TCRNL. GALEANO ANDRADE EDISON EDUARDO | Y63: =P63 -> CABSCANGO CHAVEZ LUIS GERMAN | Z63: 1002879417 | AA63: 998363245 | AB63: SERVICIO DE GARAJE PESADOS (DE 3,51 TN HASTA 12 TN) (DIARIOS) | AC63: =(V63-D63)+1 -> 12 | AD63: =IF(AB63="SERVICIO DE GARAJE LIVIANOS (HASTA 3,5 TN A EXCEPCIÓN DE MOTOCICLETAS) (DIARIOS)",3,IF(AB63="SERVICIO DE GARAJE PESADOS (DE 3,51 TN HASTA 12 TN) (DIARIOS)",9,IF(AB63="SERVICIO DE GARAJE (CENTROS DE RETENCIÓN) MOTOCICLETA",1,IF(AB63="SERVICIO DE GARAJE EXTRA PESADOS (MÁS DE 12 TN) (DIARIOS)",15,0)))) -> 9 | AE63: =IFERROR(AD63*AC63,0) -> 108 | AF63: =AA63 -> 998363245 | AG63: 46223 | AH63: 99836324 | AI63: MI NEGOCIO EFECTIVO | AJ63: =IF(AI63="","",AI63) -> MI NEGOCIO EFECTIVO | AK63: =IF(E63="","",E63) -> 2088 | AL63: SGOS. CHASIPANTA XAVIER | AM63: N/A | AN63: N/A | AO63: N/A | AP63: N/A | AQ63: =AG63 -> 46223 | AR63: =AH63 -> 99836324 | AS63: =AJ63 -> MI NEGOCIO EFECTIVO
A64: 58 | B64: SANTO DOMINGO | C64: CONTROL 120 | D64: 46212 | E64: 2089 | F64: PDX5967 | G64: CHEVROLET | H64: FURGON | I64: FVR 1730 EIII LARGO AC 7.8 2P 4X2 TM | J64: BLANCO | K64: Z2022 | L64: JALFWR347N7000577 | M64: 6HK1249552 | N64: 2026070901480898413 | O64: SGOP.MUÑOZ VERA EDWIN JAVIER | P64: SIGMAEC CIA. LTDA. | Q64: ACCIDENTE DE TRANSITO | R64: FISCALIA | S64: N/A | T64: N/A | U64: CBOP. ITALO CEDEÑO | V64: 46231 | W64: OF. No. FPSD-FEAT1-0258-2026-0002450-O | X64: TCRNL. GALEANO ANDRADE EDISON EDUARDO | Y64: MATA GUZMAN PABLO SANTIAGO | Z64: 1719633438 | AA64: 100091780 | AB64: SERVICIO DE GARAJE PESADOS (DE 3,51 TN HASTA 12 TN) (DIARIOS) | AC64: =(V64-D64)+1 -> 20 | AD64: =IF(AB64="SERVICIO DE GARAJE LIVIANOS (HASTA 3,5 TN A EXCEPCIÓN DE MOTOCICLETAS) (DIARIOS)",3,IF(AB64="SERVICIO DE GARAJE PESADOS (DE 3,51 TN HASTA 12 TN) (DIARIOS)",9,IF(AB64="SERVICIO DE GARAJE (CENTROS DE RETENCIÓN) MOTOCICLETA",1,IF(AB64="SERVICIO DE GARAJE EXTRA PESADOS (MÁS DE 12 TN) (DIARIOS)",15,0)))) -> 9 | AE64: =IFERROR(AD64*AC64,0) -> 180 | AF64: =AA64 -> 100091780 | AG64: 46231 | AH64: 5909858 | AI64: BANCO DEL PACIFICO | AJ64: =IF(AI64="","",AI64) -> BANCO DEL PACIFICO | AK64: =IF(E64="","",E64) -> 2089 | AL64: SGOS. CHASIPANTA XAVIER | AM64: N/A | AN64: N/A | AO64: INORME TECNICO PERICIAL DE EVALUO TECNICO MECANICO Y RECONOCIMIENTO DE DAÑOS MATERIALES | AP64: CBOS. GUAMAN JEFFERSON | AQ64: =AG64 -> 46231 | AR64: =AH64 -> 5909858 | AS64: =AJ64 -> BANCO DEL PACIFICO
A65: 59 | B65: SANTO DOMINGO | C65: CONTROL 120 | D65: 46217 | E65: 2090 | F65: XAA4034 | G65: HINO | H65: BUS | I65: AK8JRSA AC 7.7 2P 4X2 TM DIESEL | J65: AZUL | K65: 2020 | L65: JHDAK8JRSLXX18135 | M65: J08EUD34600 | N65: 2026071409104162713 | O65: SGOS. ROJAS ROSAS GANDY DANIEL | P65: ROMERO ABARCA DENNISE ESTEFANIA | Q65: ACCIDENTE DE TRANSITO | R65: FISCALIA | S65: N/A | T65: N/A | U65: SGOS. CHASIPANTA XAVIER | V65: 46218 | W65: OF. No. PN-SZSDT-JPCTV-DIG-2026-188-O | X65: TCRNL. GALEANO ANDRADE EDISON EDUARDO | Y65: =P65 -> ROMERO ABARCA DENNISE ESTEFANIA | Z65: 1714988795 | AA65: 99680196 | AB65: SERVICIO DE GARAJE PESADOS (DE 3,51 TN HASTA 12 TN) (DIARIOS) | AC65: =(V65-D65)+1 -> 2 | AD65: =IF(AB65="SERVICIO DE GARAJE LIVIANOS (HASTA 3,5 TN A EXCEPCIÓN DE MOTOCICLETAS) (DIARIOS)",3,IF(AB65="SERVICIO DE GARAJE PESADOS (DE 3,51 TN HASTA 12 TN) (DIARIOS)",9,IF(AB65="SERVICIO DE GARAJE (CENTROS DE RETENCIÓN) MOTOCICLETA",1,IF(AB65="SERVICIO DE GARAJE EXTRA PESADOS (MÁS DE 12 TN) (DIARIOS)",15,0)))) -> 9 | AE65: =IFERROR(AD65*AC65,0) -> 18 | AF65: =AA65 -> 99680196 | AG65: 46218 | AH65: 202607157843420 | AI65: BANCO PACIFICO | AJ65: =IF(AI65="","",AI65) -> BANCO PACIFICO | AK65: =IF(E65="","",E65) -> 2090 | AL65: SGOS. CHASIPANTA XAVIER | AM65: N/A | AN65: N/A | AO65: INORME TECNICO PERICIAL DE EVALUO TECNICO MECANICO Y RECONOCIMIENTO DE DAÑOS MATERIALES | AQ65: =AG65 -> 46218 | AR65: =AH65 -> 202607157843420 | AS65: =AJ65 -> BANCO PACIFICO
A66: 60 | B66: SANTO DOMINGO | C66: CONTROL 120 | D66: 46220 | E66: 2091 | F66: PPC3401 | G66: HYUNDAI | H66: FURGON | I66: D4DB5240396 | J66: BLANCO | K66: 2025 | L66: KMFGA17BP5C013270 | M66: D4DB5240396 | N66: 2026071703415419318 | O66: SGOS. RODRIGUES JORGE | P66: GUACHICULLCA ARIAS LUIS | Q66: ART. 386 INCISO 2 #2 | R66: N/A | S66: N/A | T66: N/A | U66: SGOS. CHASIPANTA XAVIER | V66: 46239 | W66: 23281-2026-10124-OFICIO-08198-2026 | X66: TCRNL. GALEANO ANDRADE EDISON EDUARDO | Y66: =P66 -> GUACHICULLCA ARIAS LUIS | Z66: 1723801773 | AA66: 100316628 | AB66: SERVICIO DE GARAJE PESADOS (DE 3,51 TN HASTA 12 TN) (DIARIOS) | AC66: =(V66-D66)+1 -> 20 | AD66: =IF(AB66="SERVICIO DE GARAJE LIVIANOS (HASTA 3,5 TN A EXCEPCIÓN DE MOTOCICLETAS) (DIARIOS)",3,IF(AB66="SERVICIO DE GARAJE PESADOS (DE 3,51 TN HASTA 12 TN) (DIARIOS)",9,IF(AB66="SERVICIO DE GARAJE (CENTROS DE RETENCIÓN) MOTOCICLETA",1,IF(AB66="SERVICIO DE GARAJE EXTRA PESADOS (MÁS DE 12 TN) (DIARIOS)",15,0)))) -> 9 | AE66: =IFERROR(AD66*AC66,0) -> 180 | AF66: =AA66 -> 100316628 | AG66: 46239 | AH66: 100316628 | AI66: MI NEGOCIO EFECTIVO | AJ66: =IF(AI66="","",AI66) -> MI NEGOCIO EFECTIVO | AK66: =IF(E66="","",E66) -> 2091 | AL66: SGOS. CHASIPANTA XAVIER | AM66: N/A | AN66: N/A | AO66: N/A | AP66: N/A | AQ66: =AG66 -> 46239 | AR66: =AH66 -> 100316628 | AS66: =AJ66 -> MI NEGOCIO EFECTIVO
A67: 61 | B67: SANTO DOMINGO | C67: CONTROL 120 | D67: 46235 | E67: 2092 | F67: PFU5200 | G67: SINOTRUK | H67: CAMIÓN | I67: HOWO NKS ZZ1048D3314C145 AC 2.3 2P | J67: BLANCO | K67: 2027 | M67: D226C009031 | N67: 202608010108376010 | O67: SGOS. RODRIGUES JORGE | P67: MONTESDEOCA CEDEÑO JENNY | Q67: ART. 386 INCISO 2 #2 | R67: N/A | S67: N/A | T67: N/A | U67: SGOS. CHASIPANTA XAVIER | Y67: =P67 -> MONTESDEOCA CEDEÑO JENNY | AC67: =(V67-D67)+1 -> -46234 | AD67: =IF(AB67="SERVICIO DE GARAJE LIVIANOS (HASTA 3,5 TN A EXCEPCIÓN DE MOTOCICLETAS) (DIARIOS)",3,IF(AB67="SERVICIO DE GARAJE PESADOS (DE 3,51 TN HASTA 12 TN) (DIARIOS)",9,IF(AB67="SERVICIO DE GARAJE (CENTROS DE RETENCIÓN) MOTOCICLETA",1,IF(AB67="SERVICIO DE GARAJE EXTRA PESADOS (MÁS DE 12 TN) (DIARIOS)",15,0)))) -> 0 | AE67: =IFERROR(AD67*AC67,0) -> 0 | AF67: =AA67 -> 0 | AJ67: =IF(AI67="","",AI67) | AK67: =IF(E67="","",E67) -> 2092 | AQ67: =AG67 -> 0 | AR67: =AH67 -> 0 | AS67: =AJ67
A68: 62 | B68: SANTO DOMINGO | C68: CONTROL 120 | D68: 46235 | E68: 2093 | F68: ABC6106 | G68: CHEVROLET | H68: CAMIÓN | I68: NHR 2.7 2P 4X2 TM DIESEL | J68: BLANCO | K68: 2009 | M68: 707191 | N68: 2026080101021636711 | O68: SGOS. RODRIGUES JORGE | P68: GOMEZ TORRES FRANCISCO | Q68: ART. 160 | R68: N/A | S68: N/A | T68: N/A | U68: SGOS. CHASIPANTA XAVIER | Y68: =P68 -> GOMEZ TORRES FRANCISCO | AC68: =(V68-D68)+1 -> -46234 | AD68: =IF(AB68="SERVICIO DE GARAJE LIVIANOS (HASTA 3,5 TN A EXCEPCIÓN DE MOTOCICLETAS) (DIARIOS)",3,IF(AB68="SERVICIO DE GARAJE PESADOS (DE 3,51 TN HASTA 12 TN) (DIARIOS)",9,IF(AB68="SERVICIO DE GARAJE (CENTROS DE RETENCIÓN) MOTOCICLETA",1,IF(AB68="SERVICIO DE GARAJE EXTRA PESADOS (MÁS DE 12 TN) (DIARIOS)",15,0)))) -> 0 | AE68: =IFERROR(AD68*AC68,0) -> 0 | AF68: =AA68 -> 0 | AJ68: =IF(AI68="","",AI68) | AK68: =IF(E68="","",E68) -> 2093 | AQ68: =AG68 -> 0 | AR68: =AH68 -> 0 | AS68: =AJ68
A69: 63 | B69: SANTO DOMINGO | C69: CONTROL 120 | D69: 46236 | E69: 2094 | F69: PDE3588 | G69: HINO | H69: CAMIÓN | I69: GD8JL7A AC 7.7 2P 4X2 TM DIESEL | J69: BLANCO | K69: 2021 | M69: J08EWH12777 | N69: 2026080211584378801 | O69: CBOP. MEZA CARLOS | P69: CHARIGUAMAN CHILENO WILLIAM ROLANDO | Q69: ACCIDENTE DE TRANSITO | R69: FISCALIA | S69: N/A | T69: N/A | U69: SGOS. CHASIPANTA XAVIER | Y69: =P69 -> CHARIGUAMAN CHILENO WILLIAM ROLANDO | AC69: =(V69-D69)+1 -> -46235 | AD69: =IF(AB69="SERVICIO DE GARAJE LIVIANOS (HASTA 3,5 TN A EXCEPCIÓN DE MOTOCICLETAS) (DIARIOS)",3,IF(AB69="SERVICIO DE GARAJE PESADOS (DE 3,51 TN HASTA 12 TN) (DIARIOS)",9,IF(AB69="SERVICIO DE GARAJE (CENTROS DE RETENCIÓN) MOTOCICLETA",1,IF(AB69="SERVICIO DE GARAJE EXTRA PESADOS (MÁS DE 12 TN) (DIARIOS)",15,0)))) -> 0 | AE69: =IFERROR(AD69*AC69,0) -> 0 | AF69: =AA69 -> 0 | AJ69: =IF(AI69="","",AI69) | AK69: =IF(E69="","",E69) -> 2094 | AQ69: =AG69 -> 0 | AR69: =AH69 -> 0 | AS69: =AJ69
A70: 64 | B70: SANTO DOMINGO | C70: CONTROL 120 | D70: 46237 | E70: 2095 | F70: PAB3080 | G70: CHEVROLET | H70: CAMIÓN | I70: FTR 34P 7.8 2P 4X2 TM DIESEL | J70: BLANCO | K70: 2019 | M70: 6HK1214815 | N70: 2026080310181236512 | O70: SGOS. BRAVO HENRY | P70: CARANQUI PAUCAR MARIA PIEDAD | Q70: ACCIDENTE DE TRANSITO | R70: FISCALIA | S70: N/A | T70: N/A | U70: SGOS. CHASIPANTA XAVIER | Y70: =P70 -> CARANQUI PAUCAR MARIA PIEDAD | AC70: =(V70-D70)+1 -> -46236 | AD70: =IF(AB70="SERVICIO DE GARAJE LIVIANOS (HASTA 3,5 TN A EXCEPCIÓN DE MOTOCICLETAS) (DIARIOS)",3,IF(AB70="SERVICIO DE GARAJE PESADOS (DE 3,51 TN HASTA 12 TN) (DIARIOS)",9,IF(AB70="SERVICIO DE GARAJE (CENTROS DE RETENCIÓN) MOTOCICLETA",1,IF(AB70="SERVICIO DE GARAJE EXTRA PESADOS (MÁS DE 12 TN) (DIARIOS)",15,0)))) -> 0 | AE70: =IFERROR(AD70*AC70,0) -> 0 | AF70: =AA70 -> 0 | AJ70: =IF(AI70="","",AI70) | AK70: =IF(E70="","",E70) -> 2095 | AQ70: =AG70 -> 0 | AR70: =AH70 -> 0 | AS70: =AJ70
A71: 65 | B71: SANTO DOMINGO | C71: CONTROL 120 | D71: 46238 | E71: 2096 | F71: ICL0476 | G71: MITSUBISHI | H71: CAMIÓN | I71: CANTER 6.5 TON | J71: BLANCO | K71: 2007 | M71: 4D34L06754 | N71: 2026080400594175009 | O71: CBOP. IZURIETA MERINO DENNIS | P71: MIRIAN MARLENE YANEZ GUIZADO | Q71: ACCIDENTE DE TRANSITO | R71: FISCALIA | S71: N/A | T71: N/A | U71: CBOS. CHALA ANDERSON | Y71: =P71 -> MIRIAN MARLENE YANEZ GUIZADO | AC71: =(V71-D71)+1 -> -46237 | AD71: =IF(AB71="SERVICIO DE GARAJE LIVIANOS (HASTA 3,5 TN A EXCEPCIÓN DE MOTOCICLETAS) (DIARIOS)",3,IF(AB71="SERVICIO DE GARAJE PESADOS (DE 3,51 TN HASTA 12 TN) (DIARIOS)",9,IF(AB71="SERVICIO DE GARAJE (CENTROS DE RETENCIÓN) MOTOCICLETA",1,IF(AB71="SERVICIO DE GARAJE EXTRA PESADOS (MÁS DE 12 TN) (DIARIOS)",15,0)))) -> 0 | AE71: =IFERROR(AD71*AC71,0) -> 0 | AF71: =AA71 -> 0 | AJ71: =IF(AI71="","",AI71) | AK71: =IF(E71="","",E71) -> 2096 | AQ71: =AG71 -> 0 | AR71: =AH71 -> 0 | AS71: =AJ71
A72: 66 | B72: SANTO DOMINGO | C72: CONTROL 120 | Y72: =P72 -> 0 | AC72: =(V72-D72)+1 -> 1 | AD72: =IF(AB72="SERVICIO DE GARAJE LIVIANOS (HASTA 3,5 TN A EXCEPCIÓN DE MOTOCICLETAS) (DIARIOS)",3,IF(AB72="SERVICIO DE GARAJE PESADOS (DE 3,51 TN HASTA 12 TN) (DIARIOS)",9,IF(AB72="SERVICIO DE GARAJE (CENTROS DE RETENCIÓN) MOTOCICLETA",1,IF(AB72="SERVICIO DE GARAJE EXTRA PESADOS (MÁS DE 12 TN) (DIARIOS)",15,0)))) -> 0 | AE72: =IFERROR(AD72*AC72,0) -> 0 | AF72: =AA72 -> 0 | AJ72: =IF(AI72="","",AI72) | AK72: =IF(E72="","",E72) | AQ72: =AG72 -> 0 | AR72: =AH72 -> 0 | AS72: =AJ72
A73: 67 | B73: SANTO DOMINGO | C73: CONTROL 120 | Y73: =P73 -> 0 | AC73: =(V73-D73)+1 -> 1 | AD73: =IF(AB73="SERVICIO DE GARAJE LIVIANOS (HASTA 3,5 TN A EXCEPCIÓN DE MOTOCICLETAS) (DIARIOS)",3,IF(AB73="SERVICIO DE GARAJE PESADOS (DE 3,51 TN HASTA 12 TN) (DIARIOS)",9,IF(AB73="SERVICIO DE GARAJE (CENTROS DE RETENCIÓN) MOTOCICLETA",1,IF(AB73="SERVICIO DE GARAJE EXTRA PESADOS (MÁS DE 12 TN) (DIARIOS)",15,0)))) -> 0 | AE73: =IFERROR(AD73*AC73,0) -> 0 | AF73: =AA73 -> 0 | AJ73: =IF(AI73="","",AI73) | AK73: =IF(E73="","",E73) | AQ73: =AG73 -> 0 | AR73: =AH73 -> 0 | AS73: =AJ73
A74: 68 | B74: SANTO DOMINGO | C74: CONTROL 120 | Y74: =P74 -> 0 | AC74: =(V74-D74)+1 -> 1 | AD74: =IF(AB74="SERVICIO DE GARAJE LIVIANOS (HASTA 3,5 TN A EXCEPCIÓN DE MOTOCICLETAS) (DIARIOS)",3,IF(AB74="SERVICIO DE GARAJE PESADOS (DE 3,51 TN HASTA 12 TN) (DIARIOS)",9,IF(AB74="SERVICIO DE GARAJE (CENTROS DE RETENCIÓN) MOTOCICLETA",1,IF(AB74="SERVICIO DE GARAJE EXTRA PESADOS (MÁS DE 12 TN) (DIARIOS)",15,0)))) -> 0 | AE74: =IFERROR(AD74*AC74,0) -> 0 | AF74: =AA74 -> 0 | AJ74: =IF(AI74="","",AI74) | AK74: =IF(E74="","",E74) | AQ74: =AG74 -> 0 | AR74: =AH74 -> 0 | AS74: =AJ74
A75: 69 | B75: SANTO DOMINGO | C75: CONTROL 120 | Y75: =P75 -> 0 | AC75: =(V75-D75)+1 -> 1 | AD75: =IF(AB75="SERVICIO DE GARAJE LIVIANOS (HASTA 3,5 TN A EXCEPCIÓN DE MOTOCICLETAS) (DIARIOS)",3,IF(AB75="SERVICIO DE GARAJE PESADOS (DE 3,51 TN HASTA 12 TN) (DIARIOS)",9,IF(AB75="SERVICIO DE GARAJE (CENTROS DE RETENCIÓN) MOTOCICLETA",1,IF(AB75="SERVICIO DE GARAJE EXTRA PESADOS (MÁS DE 12 TN) (DIARIOS)",15,0)))) -> 0 | AE75: =IFERROR(AD75*AC75,0) -> 0 | AF75: =AA75 -> 0 | AJ75: =IF(AI75="","",AI75) | AK75: =IF(E75="","",E75) | AQ75: =AG75 -> 0 | AR75: =AH75 -> 0 | AS75: =AJ75
A76: 70 | B76: SANTO DOMINGO | C76: CONTROL 120 | Y76: =P76 -> 0 | AC76: =(V76-D76)+1 -> 1 | AD76: =IF(AB76="SERVICIO DE GARAJE LIVIANOS (HASTA 3,5 TN A EXCEPCIÓN DE MOTOCICLETAS) (DIARIOS)",3,IF(AB76="SERVICIO DE GARAJE PESADOS (DE 3,51 TN HASTA 12 TN) (DIARIOS)",9,IF(AB76="SERVICIO DE GARAJE (CENTROS DE RETENCIÓN) MOTOCICLETA",1,IF(AB76="SERVICIO DE GARAJE EXTRA PESADOS (MÁS DE 12 TN) (DIARIOS)",15,0)))) -> 0 | AE76: =IFERROR(AD76*AC76,0) -> 0 | AF76: =AA76 -> 0 | AJ76: =IF(AI76="","",AI76) | AK76: =IF(E76="","",E76) | AQ76: =AG76 -> 0 | AR76: =AH76 -> 0 | AS76: =AJ76
A77: 71 | B77: SANTO DOMINGO | C77: CONTROL 120 | Y77: =P77 -> 0 | AC77: =(V77-D77)+1 -> 1 | AD77: =IF(AB77="SERVICIO DE GARAJE LIVIANOS (HASTA 3,5 TN A EXCEPCIÓN DE MOTOCICLETAS) (DIARIOS)",3,IF(AB77="SERVICIO DE GARAJE PESADOS (DE 3,51 TN HASTA 12 TN) (DIARIOS)",9,IF(AB77="SERVICIO DE GARAJE (CENTROS DE RETENCIÓN) MOTOCICLETA",1,IF(AB77="SERVICIO DE GARAJE EXTRA PESADOS (MÁS DE 12 TN) (DIARIOS)",15,0)))) -> 0 | AE77: =IFERROR(AD77*AC77,0) -> 0 | AF77: =AA77 -> 0 | AJ77: =IF(AI77="","",AI77) | AK77: =IF(E77="","",E77) | AQ77: =AG77 -> 0 | AR77: =AH77 -> 0 | AS77: =AJ77
A78: 72 | B78: SANTO DOMINGO | C78: CONTROL 120 | Y78: =P78 -> 0 | AC78: =(V78-D78)+1 -> 1 | AD78: =IF(AB78="SERVICIO DE GARAJE LIVIANOS (HASTA 3,5 TN A EXCEPCIÓN DE MOTOCICLETAS) (DIARIOS)",3,IF(AB78="SERVICIO DE GARAJE PESADOS (DE 3,51 TN HASTA 12 TN) (DIARIOS)",9,IF(AB78="SERVICIO DE GARAJE (CENTROS DE RETENCIÓN) MOTOCICLETA",1,IF(AB78="SERVICIO DE GARAJE EXTRA PESADOS (MÁS DE 12 TN) (DIARIOS)",15,0)))) -> 0 | AE78: =IFERROR(AD78*AC78,0) -> 0 | AF78: =AA78 -> 0 | AJ78: =IF(AI78="","",AI78) | AK78: =IF(E78="","",E78) | AQ78: =AG78 -> 0 | AR78: =AH78 -> 0 | AS78: =AJ78
A79: 73 | B79: SANTO DOMINGO | C79: CONTROL 120 | Y79: =P79 -> 0 | AC79: =(V79-D79)+1 -> 1 | AD79: =IF(AB79="SERVICIO DE GARAJE LIVIANOS (HASTA 3,5 TN A EXCEPCIÓN DE MOTOCICLETAS) (DIARIOS)",3,IF(AB79="SERVICIO DE GARAJE PESADOS (DE 3,51 TN HASTA 12 TN) (DIARIOS)",9,IF(AB79="SERVICIO DE GARAJE (CENTROS DE RETENCIÓN) MOTOCICLETA",1,IF(AB79="SERVICIO DE GARAJE EXTRA PESADOS (MÁS DE 12 TN) (DIARIOS)",15,0)))) -> 0 | AE79: =IFERROR(AD79*AC79,0) -> 0 | AF79: =AA79 -> 0 | AJ79: =IF(AI79="","",AI79) | AK79: =IF(E79="","",E79) | AQ79: =AG79 -> 0 | AR79: =AH79 -> 0 | AS79: =AJ79
A80: 74 | B80: SANTO DOMINGO | C80: CONTROL 120 | Y80: =P80 -> 0 | AC80: =(V80-D80)+1 -> 1 | AD80: =IF(AB80="SERVICIO DE GARAJE LIVIANOS (HASTA 3,5 TN A EXCEPCIÓN DE MOTOCICLETAS) (DIARIOS)",3,IF(AB80="SERVICIO DE GARAJE PESADOS (DE 3,51 TN HASTA 12 TN) (DIARIOS)",9,IF(AB80="SERVICIO DE GARAJE (CENTROS DE RETENCIÓN) MOTOCICLETA",1,IF(AB80="SERVICIO DE GARAJE EXTRA PESADOS (MÁS DE 12 TN) (DIARIOS)",15,0)))) -> 0 | AE80: =IFERROR(AD80*AC80,0) -> 0 | AF80: =AA80 -> 0 | AJ80: =IF(AI80="","",AI80) | AK80: =IF(E80="","",E80) | AQ80: =AG80 -> 0 | AR80: =AH80 -> 0 | AS80: =AJ80
A81: 75 | B81: SANTO DOMINGO | C81: CONTROL 120 | Y81: =P81 -> 0 | AC81: =(V81-D81)+1 -> 1 | AD81: =IF(AB81="SERVICIO DE GARAJE LIVIANOS (HASTA 3,5 TN A EXCEPCIÓN DE MOTOCICLETAS) (DIARIOS)",3,IF(AB81="SERVICIO DE GARAJE PESADOS (DE 3,51 TN HASTA 12 TN) (DIARIOS)",9,IF(AB81="SERVICIO DE GARAJE (CENTROS DE RETENCIÓN) MOTOCICLETA",1,IF(AB81="SERVICIO DE GARAJE EXTRA PESADOS (MÁS DE 12 TN) (DIARIOS)",15,0)))) -> 0 | AE81: =IFERROR(AD81*AC81,0) -> 0 | AF81: =AA81 -> 0 | AJ81: =IF(AI81="","",AI81) | AK81: =IF(E81="","",E81) | AQ81: =AG81 -> 0 | AR81: =AH81 -> 0 | AS81: =AJ81
A82: 76 | B82: SANTO DOMINGO | C82: CONTROL 120 | Y82: =P82 -> 0 | AC82: =(V82-D82)+1 -> 1 | AD82: =IF(AB82="SERVICIO DE GARAJE LIVIANOS (HASTA 3,5 TN A EXCEPCIÓN DE MOTOCICLETAS) (DIARIOS)",3,IF(AB82="SERVICIO DE GARAJE PESADOS (DE 3,51 TN HASTA 12 TN) (DIARIOS)",9,IF(AB82="SERVICIO DE GARAJE (CENTROS DE RETENCIÓN) MOTOCICLETA",1,IF(AB82="SERVICIO DE GARAJE EXTRA PESADOS (MÁS DE 12 TN) (DIARIOS)",15,0)))) -> 0 | AE82: =IFERROR(AD82*AC82,0) -> 0 | AF82: =AA82 -> 0 | AJ82: =IF(AI82="","",AI82) | AK82: =IF(E82="","",E82) | AQ82: =AG82 -> 0 | AR82: =AH82 -> 0 | AS82: =AJ82
A83: 77 | B83: SANTO DOMINGO | C83: CONTROL 120 | Y83: =P83 -> 0 | AC83: =(V83-D83)+1 -> 1 | AD83: =IF(AB83="SERVICIO DE GARAJE LIVIANOS (HASTA 3,5 TN A EXCEPCIÓN DE MOTOCICLETAS) (DIARIOS)",3,IF(AB83="SERVICIO DE GARAJE PESADOS (DE 3,51 TN HASTA 12 TN) (DIARIOS)",9,IF(AB83="SERVICIO DE GARAJE (CENTROS DE RETENCIÓN) MOTOCICLETA",1,IF(AB83="SERVICIO DE GARAJE EXTRA PESADOS (MÁS DE 12 TN) (DIARIOS)",15,0)))) -> 0 | AE83: =IFERROR(AD83*AC83,0) -> 0 | AF83: =AA83 -> 0 | AJ83: =IF(AI83="","",AI83) | AK83: =IF(E83="","",E83) | AQ83: =AG83 -> 0 | AR83: =AH83 -> 0 | AS83: =AJ83
... A109: 103 | B109: SANTO DOMINGO | C109: CONTROL 120 | Y109: =P109 -> 0 | AC109: =(V109-D109)+1 -> 1 | AD109: =IF(AB109="SERVICIO DE GARAJE LIVIANOS (HASTA 3,5 TN A EXCEPCIÓN DE MOTOCICLETAS) (DIARIOS)",3,IF(AB109="SERVICIO DE GARAJE PESADOS (DE 3,51 TN HASTA 12 TN) (DIARIOS)",9,IF(AB109="SERVICIO DE GARAJE (CENTROS DE RETENCIÓN) MOTOCICLETA",1,IF(AB109="SERVICIO DE GARAJE EXTRA PESADOS (MÁS DE 12 TN) (DIARIOS)",15,0)))) -> 0 | AE109: =IFERROR(AD109*AC109,0) -> 0 | AF109: =AA109 -> 0 | AJ109: =IF(AI109="","",AI109) | AK109: =IF(E109="","",E109) | AQ109: =AG109 -> 0 | AR109: =AH109 -> 0 | AS109: =AJ109
A110: 104 | B110: SANTO DOMINGO | C110: CONTROL 120 | Y110: =P110 -> 0 | AC110: =(V110-D110)+1 -> 1 | AD110: =IF(AB110="SERVICIO DE GARAJE LIVIANOS (HASTA 3,5 TN A EXCEPCIÓN DE MOTOCICLETAS) (DIARIOS)",3,IF(AB110="SERVICIO DE GARAJE PESADOS (DE 3,51 TN HASTA 12 TN) (DIARIOS)",9,IF(AB110="SERVICIO DE GARAJE (CENTROS DE RETENCIÓN) MOTOCICLETA",1,IF(AB110="SERVICIO DE GARAJE EXTRA PESADOS (MÁS DE 12 TN) (DIARIOS)",15,0)))) -> 0 | AE110: =IFERROR(AD110*AC110,0) -> 0 | AF110: =AA110 -> 0 | AJ110: =IF(AI110="","",AI110) | AK110: =IF(E110="","",E110) | AR110: =AH110 -> 0 | AS110: =AJ110
AC196: =(V196-D196)+1 -> 1 | AE196: =IFERROR(AD196*AC196,0) -> 0 | AF196: =AA196 -> 0 | AK196: =IF(E196="","",E196) | AO196: N/A | AP196: N/A | AS196: =AJ196 -> 0
AC197: =(V197-D197)+1 -> 1 | AE197: =IFERROR(AD197*AC197,0) -> 0 | AF197: =AA197 -> 0 | AK197: =IF(E197="","",E197) | AO197: INORME TECNICO PERICIAL DE EVALUO TECNICO MECANICO Y RECONOCIMIENTO DE DAÑOS MATERIALES (TIPO B) | AP197: POLI. ANDI GREFA LEANDRO | AS197: =AJ197 -> 0
AC198: =(V198-D198)+1 -> 1 | AE198: =IFERROR(AD198*AC198,0) -> 0 | AF198: =AA198 -> 0 | AK198: =IF(E198="","",E198) | AO198: INORME TECNICO PERICIAL DE EVALUO TECNICO MECANICO Y RECONOCIMIENTO DE DAÑOS MATERIALES (TIPO B) | AP198: CBOP. GAVILANEZ AZOGUE LENIN | AS198: =AJ198 -> 0
AC199: =(V199-D199)+1 -> 1 | AE199: =IFERROR(AD199*AC199,0) -> 0 | AF199: =AA199 -> 0 | AK199: =IF(E199="","",E199) | AO199: N/A | AP199: N/A | AS199: =AJ199 -> 0
AC200: =(V200-D200)+1 -> 1 | AE200: =IFERROR(AD200*AC200,0) -> 0 | AF200: =AA200 -> 0 | AK200: =IF(E200="","",E200) | AO200: N/A | AP200: N/A | AS200: =AJ200 -> 0
AC201: =(V201-D201)+1 -> 1 | AE201: =IFERROR(AD201*AC201,0) -> 0 | AF201: =AA201 -> 0 | AK201: =IF(E201="","",E201) | AO201: INORME TECNICO PERICIAL DE EVALUO TECNICO MECANICO Y RECONOCIMIENTO DE DAÑOS MATERIALES | AP201: CBOP. GAVILANEZ AZOGUE LENIN | AS201: =AJ201 -> 0
AC202: =(V202-D202)+1 -> 1 | AE202: =IFERROR(AD202*AC202,0) -> 0 | AF202: =AA202 -> 0 | AK202: =IF(E202="","",E202) | AO202: INORME TECNICO PERICIAL DE EVALUO TECNICO MECANICO Y RECONOCIMIENTO DE DAÑOS MATERIALES (TIPO B) | AP202: SGOS. BARCENES FREDY | AS202: =AJ202 -> 0
AC203: =(V203-D203)+1 -> 1 | AE203: =IFERROR(AD203*AC203,0) -> 0 | AF203: =AA203 -> 0 | AK203: =IF(E203="","",E203) | AO203: N/A | AP203: N/A | AS203: =AJ203 -> 0
AC204: =(V204-D204)+1 -> 1 | AE204: =IFERROR(AD204*AC204,0) -> 0 | AF204: =AA204 -> 0 | AK204: =IF(E204="","",E204) | AO204: N/A | AP204: N/A | AS204: =AJ204 -> 0
AC205: =(V205-D205)+1 -> 1 | AE205: =IFERROR(AD205*AC205,0) -> 0 | AF205: =AA205 -> 0 | AK205: =IF(E205="","",E205) | AO205: 1 | AP205: SGOS. BARCENES FREDY | AS205: =AJ205 -> 0
AC206: =(V206-D206)+1 -> 1 | AF206: =AA206 -> 0 | AK206: =IF(E206="","",E206) | AS206: =AJ206 -> 0
AC207: =(V207-D207)+1 -> 1 | AF207: =AA207 -> 0 | AK207: =IF(E207="","",E207) | AS207: =AJ207 -> 0
AC208: =(V208-D208)+1 -> 1 | AF208: =AA208 -> 0 | AK208: =IF(E208="","",E208) | AS208: =AJ208 -> 0
AC209: =(V209-D209)+1 -> 1 | AF209: =AA209 -> 0 | AK209: =IF(E209="","",E209) | AS209: =AJ209 -> 0
AC210: =(V210-D210)+1 -> 1 | AF210: =AA210 -> 0 | AK210: =IF(E210="","",E210) | AS210: =AJ210 -> 0
AC211: =(V211-D211)+1 -> 1 | AF211: =AA211 -> 0 | AK211: =IF(E211="","",E211) | AS211: =AJ211 -> 0
...

Sheet INVENTARIO CAJA 1
A1: COMANDO GENERAL
A2: INVENTARIO DOCUMENTAL DE TRANSFERENCIA PRIMARIA
A3: SECCIÓN: | C3: Jefatura Operativa de Control del Tránsito y Seguridad Vial
A4: SUB SECCIÓN: | C4: Patio de retención vehicular
F5: FECHAS EXTREMAS | K5: UBICACIÓN TOPOGRÁFICA
A6: SERIE /SUBSERIE DOCUMENTAL | B6: N° CAJA | C6: N° DE EXPEDIENTE | D6: N° DE TOMO | E6: DESCRIPCIÓN | F6: APERTURA | G6: CIERRE | H6: N° FOJAS | I6: DESTINO FINAL | J6: SOPORTE | K6: ZONA | L6: ESTANTERÍA | M6: BANDEJA | N6: OBSERVACIONES | O6: PLACA (CLAVE DE VÍNCULO)
A7: Retenciones Vehiculares | B7: 1 | C7: 0002_2026 | D7: 1/1 | E7: =IF($O7="","",IFERROR("Parte policial Nro. "&SUBSTITUTE(INDEX(VEHICULOS!$N:$N,MATCH($O7,VEHICULOS!$F:$F,0)),"´","")&", Hoja de Ingreso y Salida Nro. "&TEXT(INDEX(VEHICULOS!$E:$E,MATCH($O7,VEHICULOS!$F:$F,0)),"0000000")&", entregado al señor "&INDEX(VEHICULOS!$P:$P,MATCH($O7,VEHICULOS!$F:$F,0))&", con cédula "&INDEX(VEHICULOS!$Z:$Z,MATCH($O7,VEHICULOS!$F:$F,0))&" del Vehiculo Tipo "&INDEX(VEHICULOS!$H:$H,MATCH($O7,VEHICULOS!$F:$F,0))&" marca "&INDEX(VEHICULOS!$G:$G,MATCH($O7,VEHICULOS!$F:$F,0))&", color "&INDEX(VEHICULOS!$J:$J,MATCH($O7,VEHICULOS!$F:$F,0))&" con placas "&$O7&", por "&INDEX(VEHICULOS!$Q:$Q,MATCH($O7,VEHICULOS!$F:$F,0))&".","REVISAR: placa no encontrada en VEHICULOS")) -> Parte policial Nro. 202512071018484501, Hoja de Ingreso y Salida Nro. 0002031, entregado al señor ONTANEDA YEPEZ JORGE ANIBAL, con cédula 1711325496 del Vehiculo Tipo CISTERNA marca FORD, color BLANCO con placas PQF0838, por ACCIDENTE DE TRANSITO. | F7: =IF($O7="","",IFERROR(INDEX(VEHICULOS!$D:$D,MATCH($O7,VEHICULOS!$F:$F,0)),"")) -> 45998 | G7: =IF($O7="","",IFERROR(INDEX(VEHICULOS!$V:$V,MATCH($O7,VEHICULOS!$F:$F,0)),"")) -> 46030 | H7: 18 | I7: Eliminación | J7: Fisico | O7: PQF0838
A8: Retenciones Vehiculares | B8: 1 | C8: 0003_2026 | D8: 1/1 | E8: =IF($O8="","",IFERROR("Parte policial Nro. "&SUBSTITUTE(INDEX(VEHICULOS!$N:$N,MATCH($O8,VEHICULOS!$F:$F,0)),"´","")&", Hoja de Ingreso y Salida Nro. "&TEXT(INDEX(VEHICULOS!$E:$E,MATCH($O8,VEHICULOS!$F:$F,0)),"0000000")&", entregado al señor "&INDEX(VEHICULOS!$P:$P,MATCH($O8,VEHICULOS!$F:$F,0))&", con cédula "&INDEX(VEHICULOS!$Z:$Z,MATCH($O8,VEHICULOS!$F:$F,0))&" del Vehiculo Tipo "&INDEX(VEHICULOS!$H:$H,MATCH($O8,VEHICULOS!$F:$F,0))&" marca "&INDEX(VEHICULOS!$G:$G,MATCH($O8,VEHICULOS!$F:$F,0))&", color "&INDEX(VEHICULOS!$J:$J,MATCH($O8,VEHICULOS!$F:$F,0))&" con placas "&$O8&", por "&INDEX(VEHICULOS!$Q:$Q,MATCH($O8,VEHICULOS!$F:$F,0))&".","REVISAR: placa no encontrada en VEHICULOS")) -> Parte policial Nro. 2026011204060520618, Hoja de Ingreso y Salida Nro. 0002034, entregado al señor SABANDO ZAMBRANO MARIA FAVIOLA, con cédula 802191395 del Vehiculo Tipo BUS marca VOLSKWAGEN, color ANARANJADO con placas MAA3069, por ACCIDENTE DE TRANSITO. | F8: =IF($O8="","",IFERROR(INDEX(VEHICULOS!$D:$D,MATCH($O8,VEHICULOS!$F:$F,0)),"")) -> 46034 | G8: =IF($O8="","",IFERROR(INDEX(VEHICULOS!$V:$V,MATCH($O8,VEHICULOS!$F:$F,0)),"")) -> 46042 | H8: 21 | I8: Eliminación | J8: Fisico | O8: MAA3069
A9: Retenciones Vehiculares | B9: 1 | C9: 0004_2026 | D9: 1/1 | E9: =IF($O9="","",IFERROR("Parte policial Nro. "&SUBSTITUTE(INDEX(VEHICULOS!$N:$N,MATCH($O9,VEHICULOS!$F:$F,0)),"´","")&", Hoja de Ingreso y Salida Nro. "&TEXT(INDEX(VEHICULOS!$E:$E,MATCH($O9,VEHICULOS!$F:$F,0)),"0000000")&", entregado al señor "&INDEX(VEHICULOS!$P:$P,MATCH($O9,VEHICULOS!$F:$F,0))&", con cédula "&INDEX(VEHICULOS!$Z:$Z,MATCH($O9,VEHICULOS!$F:$F,0))&" del Vehiculo Tipo "&INDEX(VEHICULOS!$H:$H,MATCH($O9,VEHICULOS!$F:$F,0))&" marca "&INDEX(VEHICULOS!$G:$G,MATCH($O9,VEHICULOS!$F:$F,0))&", color "&INDEX(VEHICULOS!$J:$J,MATCH($O9,VEHICULOS!$F:$F,0))&" con placas "&$O9&", por "&INDEX(VEHICULOS!$Q:$Q,MATCH($O9,VEHICULOS!$F:$F,0))&".","REVISAR: placa no encontrada en VEHICULOS")) -> Parte policial Nro. 2026011602201191513, Hoja de Ingreso y Salida Nro. 0002035, entregado al señor CALDERON BRIONES JORGE LUIS, con cédula 1714373246 del Vehiculo Tipo VOLQUETA marca HINO, color AMARILLO con placas GBN5890, por ACCIDENTE DE TRANSITO. | F9: =IF($O9="","",IFERROR(INDEX(VEHICULOS!$D:$D,MATCH($O9,VEHICULOS!$F:$F,0)),"")) -> 46038 | G9: =IF($O9="","",IFERROR(INDEX(VEHICULOS!$V:$V,MATCH($O9,VEHICULOS!$F:$F,0)),"")) -> 46042 | H9: 21 | I9: Eliminación | J9: Fisico | O9: GBN5890
A10: Retenciones Vehiculares | B10: 1 | C10: 0005_2026 | D10: 1/1 | E10: =IF($O10="","",IFERROR("Parte policial Nro. "&SUBSTITUTE(INDEX(VEHICULOS!$N:$N,MATCH($O10,VEHICULOS!$F:$F,0)),"´","")&", Hoja de Ingreso y Salida Nro. "&TEXT(INDEX(VEHICULOS!$E:$E,MATCH($O10,VEHICULOS!$F:$F,0)),"0000000")&", entregado al señor "&INDEX(VEHICULOS!$P:$P,MATCH($O10,VEHICULOS!$F:$F,0))&", con cédula "&INDEX(VEHICULOS!$Z:$Z,MATCH($O10,VEHICULOS!$F:$F,0))&" del Vehiculo Tipo "&INDEX(VEHICULOS!$H:$H,MATCH($O10,VEHICULOS!$F:$F,0))&" marca "&INDEX(VEHICULOS!$G:$G,MATCH($O10,VEHICULOS!$F:$F,0))&", color "&INDEX(VEHICULOS!$J:$J,MATCH($O10,VEHICULOS!$F:$F,0))&" con placas "&$O10&", por "&INDEX(VEHICULOS!$Q:$Q,MATCH($O10,VEHICULOS!$F:$F,0))&".","REVISAR: placa no encontrada en VEHICULOS")) -> Parte policial Nro. 2026012408040460418, Hoja de Ingreso y Salida Nro. 0002036, entregado al señor CAIZALUIZA JURADO CARLOS, con cédula 1701212001 del Vehiculo Tipo BUS marca HINO, color AZUL con placas JAA3356, por ACCIDENTE DE TRANSITO. | F10: =IF($O10="","",IFERROR(INDEX(VEHICULOS!$D:$D,MATCH($O10,VEHICULOS!$F:$F,0)),"")) -> 46046 | G10: =IF($O10="","",IFERROR(INDEX(VEHICULOS!$V:$V,MATCH($O10,VEHICULOS!$F:$F,0)),"")) -> 46058 | H10: 17 | I10: Eliminación | J10: Fisico | O10: JAA3356
A11: Retenciones Vehiculares | B11: 1 | C11: 0006_2026 | D11: 1/1 | E11: =IF($O11="","",IFERROR("Parte policial Nro. "&SUBSTITUTE(INDEX(VEHICULOS!$N:$N,MATCH($O11,VEHICULOS!$F:$F,0)),"´","")&", Hoja de Ingreso y Salida Nro. "&TEXT(INDEX(VEHICULOS!$E:$E,MATCH($O11,VEHICULOS!$F:$F,0)),"0000000")&", entregado al señor "&INDEX(VEHICULOS!$P:$P,MATCH($O11,VEHICULOS!$F:$F,0))&", con cédula "&INDEX(VEHICULOS!$Z:$Z,MATCH($O11,VEHICULOS!$F:$F,0))&" del Vehiculo Tipo "&INDEX(VEHICULOS!$H:$H,MATCH($O11,VEHICULOS!$F:$F,0))&" marca "&INDEX(VEHICULOS!$G:$G,MATCH($O11,VEHICULOS!$F:$F,0))&", color "&INDEX(VEHICULOS!$J:$J,MATCH($O11,VEHICULOS!$F:$F,0))&" con placas "&$O11&", por "&INDEX(VEHICULOS!$Q:$Q,MATCH($O11,VEHICULOS!$F:$F,0))&".","REVISAR: placa no encontrada en VEHICULOS")) -> Parte policial Nro. 2026012700585644911, Hoja de Ingreso y Salida Nro. 0002037, entregado al señor QUIROLA VACA LUIS GONZALO, con cédula 12711739902 del Vehiculo Tipo PLATAFORMA marca SINOTRUK, color BLANCO con placas PAD2356, por ACCIDENTE DE TRANSITO. | F11: =IF($O11="","",IFERROR(INDEX(VEHICULOS!$D:$D,MATCH($O11,VEHICULOS!$F:$F,0)),"")) -> 46049 | G11: =IF($O11="","",IFERROR(INDEX(VEHICULOS!$V:$V,MATCH($O11,VEHICULOS!$F:$F,0)),"")) -> 46066 | H11: 20 | I11: Eliminación | J11: Fisico | O11: PAD2356
A12: Retenciones Vehiculares | B12: 1 | C12: 0007_2026 | D12: 1/1 | E12: =IF($O12="","",IFERROR("Parte policial Nro. "&SUBSTITUTE(INDEX(VEHICULOS!$N:$N,MATCH($O12,VEHICULOS!$F:$F,0)),"´","")&", Hoja de Ingreso y Salida Nro. "&TEXT(INDEX(VEHICULOS!$E:$E,MATCH($O12,VEHICULOS!$F:$F,0)),"0000000")&", entregado al señor "&INDEX(VEHICULOS!$P:$P,MATCH($O12,VEHICULOS!$F:$F,0))&", con cédula "&INDEX(VEHICULOS!$Z:$Z,MATCH($O12,VEHICULOS!$F:$F,0))&" del Vehiculo Tipo "&INDEX(VEHICULOS!$H:$H,MATCH($O12,VEHICULOS!$F:$F,0))&" marca "&INDEX(VEHICULOS!$G:$G,MATCH($O12,VEHICULOS!$F:$F,0))&", color "&INDEX(VEHICULOS!$J:$J,MATCH($O12,VEHICULOS!$F:$F,0))&" con placas "&$O12&", por "&INDEX(VEHICULOS!$Q:$Q,MATCH($O12,VEHICULOS!$F:$F,0))&".","REVISAR: placa no encontrada en VEHICULOS")) -> Parte policial Nro. 2026012700585644911, Hoja de Ingreso y Salida Nro. 0002038, entregado al señor COLCHA GUNSHA ERIK ALEXANDER, con cédula 0605787365 del Vehiculo Tipo CAMIÓN marca HINO, color BLANCO con placas IAK0630, por ACCIDENTE DE TRANSITO. | F12: =IF($O12="","",IFERROR(INDEX(VEHICULOS!$D:$D,MATCH($O12,VEHICULOS!$F:$F,0)),"")) -> 46049 | G12: =IF($O12="","",IFERROR(INDEX(VEHICULOS!$V:$V,MATCH($O12,VEHICULOS!$F:$F,0)),"")) -> 46077 | H12: 17 | I12: Eliminación | J12: Fisico | O12: IAK0630
A13: Retenciones Vehiculares | B13: 1 | C13: 0008_2026 | D13: 1/1 | E13: =IF($O13="","",IFERROR("Parte policial Nro. "&SUBSTITUTE(INDEX(VEHICULOS!$N:$N,MATCH($O13,VEHICULOS!$F:$F,0)),"´","")&", Hoja de Ingreso y Salida Nro. "&TEXT(INDEX(VEHICULOS!$E:$E,MATCH($O13,VEHICULOS!$F:$F,0)),"0000000")&", entregado al señor "&INDEX(VEHICULOS!$P:$P,MATCH($O13,VEHICULOS!$F:$F,0))&", con cédula "&INDEX(VEHICULOS!$Z:$Z,MATCH($O13,VEHICULOS!$F:$F,0))&" del Vehiculo Tipo "&INDEX(VEHICULOS!$H:$H,MATCH($O13,VEHICULOS!$F:$F,0))&" marca "&INDEX(VEHICULOS!$G:$G,MATCH($O13,VEHICULOS!$F:$F,0))&", color "&INDEX(VEHICULOS!$J:$J,MATCH($O13,VEHICULOS!$F:$F,0))&" con placas "&$O13&", por "&INDEX(VEHICULOS!$Q:$Q,MATCH($O13,VEHICULOS!$F:$F,0))&".","REVISAR: placa no encontrada en VEHICULOS")) -> Parte policial Nro. 2026013009255360000, Hoja de Ingreso y Salida Nro. 0002040, entregado al señor NUÑEZ MORENO JAIME PATRICIO, con cédula 1707104111 del Vehiculo Tipo FURGON marca HINO, color BLANCO con placas GBO7773, por ACCIDENTE DE TRANSITO. | F13: =IF($O13="","",IFERROR(INDEX(VEHICULOS!$D:$D,MATCH($O13,VEHICULOS!$F:$F,0)),"")) -> 46052 | G13: =IF($O13="","",IFERROR(INDEX(VEHICULOS!$V:$V,MATCH($O13,VEHICULOS!$F:$F,0)),"")) -> 46077 | H13: 15 | I13: Eliminación | J13: Fisico | O13: GBO7773
A14: Retenciones Vehiculares | B14: 1 | C14: 0009_2026 | D14: 1/1 | E14: =IF($O14="","",IFERROR("Parte policial Nro. "&SUBSTITUTE(INDEX(VEHICULOS!$N:$N,MATCH($O14,VEHICULOS!$F:$F,0)),"´","")&", Hoja de Ingreso y Salida Nro. "&TEXT(INDEX(VEHICULOS!$E:$E,MATCH($O14,VEHICULOS!$F:$F,0)),"0000000")&", entregado al señor "&INDEX(VEHICULOS!$P:$P,MATCH($O14,VEHICULOS!$F:$F,0))&", con cédula "&INDEX(VEHICULOS!$Z:$Z,MATCH($O14,VEHICULOS!$F:$F,0))&" del Vehiculo Tipo "&INDEX(VEHICULOS!$H:$H,MATCH($O14,VEHICULOS!$F:$F,0))&" marca "&INDEX(VEHICULOS!$G:$G,MATCH($O14,VEHICULOS!$F:$F,0))&", color "&INDEX(VEHICULOS!$J:$J,MATCH($O14,VEHICULOS!$F:$F,0))&" con placas "&$O14&", por "&INDEX(VEHICULOS!$Q:$Q,MATCH($O14,VEHICULOS!$F:$F,0))&".","REVISAR: placa no encontrada en VEHICULOS")) -> Parte policial Nro. 2026013009255363017, Hoja de Ingreso y Salida Nro. 0002041, entregado al señor PERALVO GARCIA MARCO VINIVIO, con cédula 1716186547 del Vehiculo Tipo TRACTO CAMIÓN marca KENWORTH, color NEGRO con placas PAB1690, por ACCIDENTE DE TRANSITO. | F14: =IF($O14="","",IFERROR(INDEX(VEHICULOS!$D:$D,MATCH($O14,VEHICULOS!$F:$F,0)),"")) -> 46052 | G14: =IF($O14="","",IFERROR(INDEX(VEHICULOS!$V:$V,MATCH($O14,VEHICULOS!$F:$F,0)),"")) -> 46058 | H14: 17 | I14: Eliminación | J14: Fisico | O14: PAB1690
A15: Retenciones Vehiculares | B15: 1 | C15: 0010_2026 | D15: 1/1 | E15: =IF($O15="","",IFERROR("Parte policial Nro. "&SUBSTITUTE(INDEX(VEHICULOS!$N:$N,MATCH($O15,VEHICULOS!$F:$F,0)),"´","")&", Hoja de Ingreso y Salida Nro. "&TEXT(INDEX(VEHICULOS!$E:$E,MATCH($O15,VEHICULOS!$F:$F,0)),"0000000")&", entregado al señor "&INDEX(VEHICULOS!$P:$P,MATCH($O15,VEHICULOS!$F:$F,0))&", con cédula "&INDEX(VEHICULOS!$Z:$Z,MATCH($O15,VEHICULOS!$F:$F,0))&" del Vehiculo Tipo "&INDEX(VEHICULOS!$H:$H,MATCH($O15,VEHICULOS!$F:$F,0))&" marca "&INDEX(VEHICULOS!$G:$G,MATCH($O15,VEHICULOS!$F:$F,0))&", color "&INDEX(VEHICULOS!$J:$J,MATCH($O15,VEHICULOS!$F:$F,0))&" con placas "&$O15&", por "&INDEX(VEHICULOS!$Q:$Q,MATCH($O15,VEHICULOS!$F:$F,0))&".","REVISAR: placa no encontrada en VEHICULOS")) -> Parte policial Nro. 2026020207283196113, Hoja de Ingreso y Salida Nro. 0002042, entregado al señor MEDINA AROCA LUIS DANIEL, con cédula 1717382491 del Vehiculo Tipo CANASTILLA marca JAC, color BLANCO con placas PAB3354, por ACCIDENTE DE TRANSITO. | F15: =IF($O15="","",IFERROR(INDEX(VEHICULOS!$D:$D,MATCH($O15,VEHICULOS!$F:$F,0)),"")) -> 46055 | G15: =IF($O15="","",IFERROR(INDEX(VEHICULOS!$V:$V,MATCH($O15,VEHICULOS!$F:$F,0)),"")) -> 46094 | H15: 13 | I15: Eliminación | J15: Fisico | O15: PAB3354
A16: Retenciones Vehiculares | B16: 1 | C16: 0011_2026 | D16: 1/1 | E16: =IF($O16="","",IFERROR("Parte policial Nro. "&SUBSTITUTE(INDEX(VEHICULOS!$N:$N,MATCH($O16,VEHICULOS!$F:$F,0)),"´","")&", Hoja de Ingreso y Salida Nro. "&TEXT(INDEX(VEHICULOS!$E:$E,MATCH($O16,VEHICULOS!$F:$F,0)),"0000000")&", entregado al señor "&INDEX(VEHICULOS!$P:$P,MATCH($O16,VEHICULOS!$F:$F,0))&", con cédula "&INDEX(VEHICULOS!$Z:$Z,MATCH($O16,VEHICULOS!$F:$F,0))&" del Vehiculo Tipo "&INDEX(VEHICULOS!$H:$H,MATCH($O16,VEHICULOS!$F:$F,0))&" marca "&INDEX(VEHICULOS!$G:$G,MATCH($O16,VEHICULOS!$F:$F,0))&", color "&INDEX(VEHICULOS!$J:$J,MATCH($O16,VEHICULOS!$F:$F,0))&" con placas "&$O16&", por "&INDEX(VEHICULOS!$Q:$Q,MATCH($O16,VEHICULOS!$F:$F,0))&".","REVISAR: placa no encontrada en VEHICULOS")) -> Parte policial Nro. 202602060046268501, Hoja de Ingreso y Salida Nro. 0002044, entregado al señor NELSON ENRIQUE REYES MENA, con cédula 0500450473 del Vehiculo Tipo FURGON marca NISSAN, color BLANCO con placas POT0362, por ACCIDENTE DE TRANSITO. | F16: =IF($O16="","",IFERROR(INDEX(VEHICULOS!$D:$D,MATCH($O16,VEHICULOS!$F:$F,0)),"")) -> 46059 | G16: =IF($O16="","",IFERROR(INDEX(VEHICULOS!$V:$V,MATCH($O16,VEHICULOS!$F:$F,0)),"")) -> 46091 | H16: 20 | I16: Eliminación | J16: Fisico | O16: POT0362
A17: Retenciones Vehiculares | B17: 1 | C17: 0012_2026 | D17: 1/1 | E17: =IF($O17="","",IFERROR("Parte policial Nro. "&SUBSTITUTE(INDEX(VEHICULOS!$N:$N,MATCH($O17,VEHICULOS!$F:$F,0)),"´","")&", Hoja de Ingreso y Salida Nro. "&TEXT(INDEX(VEHICULOS!$E:$E,MATCH($O17,VEHICULOS!$F:$F,0)),"0000000")&", entregado al señor "&INDEX(VEHICULOS!$P:$P,MATCH($O17,VEHICULOS!$F:$F,0))&", con cédula "&INDEX(VEHICULOS!$Z:$Z,MATCH($O17,VEHICULOS!$F:$F,0))&" del Vehiculo Tipo "&INDEX(VEHICULOS!$H:$H,MATCH($O17,VEHICULOS!$F:$F,0))&" marca "&INDEX(VEHICULOS!$G:$G,MATCH($O17,VEHICULOS!$F:$F,0))&", color "&INDEX(VEHICULOS!$J:$J,MATCH($O17,VEHICULOS!$F:$F,0))&" con placas "&$O17&", por "&INDEX(VEHICULOS!$Q:$Q,MATCH($O17,VEHICULOS!$F:$F,0))&".","REVISAR: placa no encontrada en VEHICULOS")) -> Parte policial Nro. 2026021110150224117, Hoja de Ingreso y Salida Nro. 0002046, entregado al señor RODRIGUEZ YUQUI CARMEN AMELIA, con cédula 913220786 del Vehiculo Tipo FURGON marca JAC, color BLANCO con placas PAE5673, por ACCIDENTE DE TRANSITO. | F17: =IF($O17="","",IFERROR(INDEX(VEHICULOS!$D:$D,MATCH($O17,VEHICULOS!$F:$F,0)),"")) -> 46064 | G17: =IF($O17="","",IFERROR(INDEX(VEHICULOS!$V:$V,MATCH($O17,VEHICULOS!$F:$F,0)),"")) -> 46086 | H17: 15 | I17: Eliminación | J17: Fisico | O17: PAE5673
A18: Retenciones Vehiculares | B18: 1 | C18: 0013_2026 | D18: 1/1 | E18: =IF($O18="","",IFERROR("Parte policial Nro. "&SUBSTITUTE(INDEX(VEHICULOS!$N:$N,MATCH($O18,VEHICULOS!$F:$F,0)),"´","")&", Hoja de Ingreso y Salida Nro. "&TEXT(INDEX(VEHICULOS!$E:$E,MATCH($O18,VEHICULOS!$F:$F,0)),"0000000")&", entregado al señor "&INDEX(VEHICULOS!$P:$P,MATCH($O18,VEHICULOS!$F:$F,0))&", con cédula "&INDEX(VEHICULOS!$Z:$Z,MATCH($O18,VEHICULOS!$F:$F,0))&" del Vehiculo Tipo "&INDEX(VEHICULOS!$H:$H,MATCH($O18,VEHICULOS!$F:$F,0))&" marca "&INDEX(VEHICULOS!$G:$G,MATCH($O18,VEHICULOS!$F:$F,0))&", color "&INDEX(VEHICULOS!$J:$J,MATCH($O18,VEHICULOS!$F:$F,0))&" con placas "&$O18&", por "&INDEX(VEHICULOS!$Q:$Q,MATCH($O18,VEHICULOS!$F:$F,0))&".","REVISAR: placa no encontrada en VEHICULOS")) -> Parte policial Nro. 2026021110150224117, Hoja de Ingreso y Salida Nro. 0002047, entregado al señor RAMOS ARGUELLO HOLGER ROLANDO, con cédula 201455029 del Vehiculo Tipo TRACTO CAMIÓN marca FOTON, color AMARILLO con placas RAA6300, por ACCIDENTE DE TRANSITO. | F18: =IF($O18="","",IFERROR(INDEX(VEHICULOS!$D:$D,MATCH($O18,VEHICULOS!$F:$F,0)),"")) -> 46064 | G18: =IF($O18="","",IFERROR(INDEX(VEHICULOS!$V:$V,MATCH($O18,VEHICULOS!$F:$F,0)),"")) -> 46085 | H18: 17 | I18: Eliminación | J18: Fisico | O18: RAA6300
A19: Retenciones Vehiculares | B19: 1 | C19: 0014_2026 | D19: 1/1 | E19: =IF($O19="","",IFERROR("Parte policial Nro. "&SUBSTITUTE(INDEX(VEHICULOS!$N:$N,MATCH($O19,VEHICULOS!$F:$F,0)),"´","")&", Hoja de Ingreso y Salida Nro. "&TEXT(INDEX(VEHICULOS!$E:$E,MATCH($O19,VEHICULOS!$F:$F,0)),"0000000")&", entregado al señor "&INDEX(VEHICULOS!$P:$P,MATCH($O19,VEHICULOS!$F:$F,0))&", con cédula "&INDEX(VEHICULOS!$Z:$Z,MATCH($O19,VEHICULOS!$F:$F,0))&" del Vehiculo Tipo "&INDEX(VEHICULOS!$H:$H,MATCH($O19,VEHICULOS!$F:$F,0))&" marca "&INDEX(VEHICULOS!$G:$G,MATCH($O19,VEHICULOS!$F:$F,0))&", color "&INDEX(VEHICULOS!$J:$J,MATCH($O19,VEHICULOS!$F:$F,0))&" con placas "&$O19&", por "&INDEX(VEHICULOS!$Q:$Q,MATCH($O19,VEHICULOS!$F:$F,0))&".","REVISAR: placa no encontrada en VEHICULOS")) -> Parte policial Nro. 2026022101231431508, Hoja de Ingreso y Salida Nro. 0002048, entregado al señor JIMENEZ VACA LEONEL ISRAEL, con cédula 503404246 del Vehiculo Tipo TRACTO CAMIÓN marca HINO, color BLANCO con placas PCD3784, por ACCIDENTE DE TRANSITO. | F19: =IF($O19="","",IFERROR(INDEX(VEHICULOS!$D:$D,MATCH($O19,VEHICULOS!$F:$F,0)),"")) -> 46074 | G19: =IF($O19="","",IFERROR(INDEX(VEHICULOS!$V:$V,MATCH($O19,VEHICULOS!$F:$F,0)),"")) -> 46080 | H19: 21 | I19: Eliminación | J19: Fisico | O19: PCD3784
A20: Retenciones Vehiculares | B20: 1 | C20: 0015_2026 | D20: 1/1 | E20: =IF($O20="","",IFERROR("Parte policial Nro. "&SUBSTITUTE(INDEX(VEHICULOS!$N:$N,MATCH($O20,VEHICULOS!$F:$F,0)),"´","")&", Hoja de Ingreso y Salida Nro. "&TEXT(INDEX(VEHICULOS!$E:$E,MATCH($O20,VEHICULOS!$F:$F,0)),"0000000")&", entregado al señor "&INDEX(VEHICULOS!$P:$P,MATCH($O20,VEHICULOS!$F:$F,0))&", con cédula "&INDEX(VEHICULOS!$Z:$Z,MATCH($O20,VEHICULOS!$F:$F,0))&" del Vehiculo Tipo "&INDEX(VEHICULOS!$H:$H,MATCH($O20,VEHICULOS!$F:$F,0))&" marca "&INDEX(VEHICULOS!$G:$G,MATCH($O20,VEHICULOS!$F:$F,0))&", color "&INDEX(VEHICULOS!$J:$J,MATCH($O20,VEHICULOS!$F:$F,0))&" con placas "&$O20&", por "&INDEX(VEHICULOS!$Q:$Q,MATCH($O20,VEHICULOS!$F:$F,0))&".","REVISAR: placa no encontrada en VEHICULOS")) -> Parte policial Nro. 2026022607544979807, Hoja de Ingreso y Salida Nro. 0002049, entregado al señor ALCOCER ZAPATA LUIS GUSTAVO, con cédula 1710361179 del Vehiculo Tipo FURGON marca HINO, color BLANCO con placas PAB7793, por ACCIDENTE DE TRANSITO. | F20: =IF($O20="","",IFERROR(INDEX(VEHICULOS!$D:$D,MATCH($O20,VEHICULOS!$F:$F,0)),"")) -> 46078 | G20: =IF($O20="","",IFERROR(INDEX(VEHICULOS!$V:$V,MATCH($O20,VEHICULOS!$F:$F,0)),"")) -> 46093 | H20: 19 | I20: Eliminación | J20: Fisico | N20: la fecha de elaboracion del parte es 26/02/2026 | O20: PAB7793
A21: Retenciones Vehiculares | B21: 1 | C21: 0016_2026 | D21: 1/1 | E21: =IF($O21="","",IFERROR("Parte policial Nro. "&SUBSTITUTE(INDEX(VEHICULOS!$N:$N,MATCH($O21,VEHICULOS!$F:$F,0)),"´","")&", Hoja de Ingreso y Salida Nro. "&TEXT(INDEX(VEHICULOS!$E:$E,MATCH($O21,VEHICULOS!$F:$F,0)),"0000000")&", entregado al señor "&INDEX(VEHICULOS!$P:$P,MATCH($O21,VEHICULOS!$F:$F,0))&", con cédula "&INDEX(VEHICULOS!$Z:$Z,MATCH($O21,VEHICULOS!$F:$F,0))&" del Vehiculo Tipo "&INDEX(VEHICULOS!$H:$H,MATCH($O21,VEHICULOS!$F:$F,0))&" marca "&INDEX(VEHICULOS!$G:$G,MATCH($O21,VEHICULOS!$F:$F,0))&", color "&INDEX(VEHICULOS!$J:$J,MATCH($O21,VEHICULOS!$F:$F,0))&" con placas "&$O21&", por "&INDEX(VEHICULOS!$Q:$Q,MATCH($O21,VEHICULOS!$F:$F,0))&".","REVISAR: placa no encontrada en VEHICULOS")) -> Parte policial Nro. 2026022802031976305, Hoja de Ingreso y Salida Nro. 0002051, entregado al señor VILATUÑA PINTO LIVIA MARUJA, con cédula 1704123031 del Vehiculo Tipo AUTOBUS marca VOLKSWAGEN, color AZUL con placas EAA1221, por ACCIDENTE DE TRANSITO. | F21: =IF($O21="","",IFERROR(INDEX(VEHICULOS!$D:$D,MATCH($O21,VEHICULOS!$F:$F,0)),"")) -> 46081 | G21: =IF($O21="","",IFERROR(INDEX(VEHICULOS!$V:$V,MATCH($O21,VEHICULOS!$F:$F,0)),"")) -> 46101 | H21: 17 | I21: Eliminación | J21: Fisico | O21: EAA1221
A22: Retenciones Vehiculares | B22: 1 | C22: 0017_2026 | D22: 1/1 | E22: =IF($O22="","",IFERROR("Parte policial Nro. "&SUBSTITUTE(INDEX(VEHICULOS!$N:$N,MATCH($O22,VEHICULOS!$F:$F,0)),"´","")&", Hoja de Ingreso y Salida Nro. "&TEXT(INDEX(VEHICULOS!$E:$E,MATCH($O22,VEHICULOS!$F:$F,0)),"0000000")&", entregado al señor "&INDEX(VEHICULOS!$P:$P,MATCH($O22,VEHICULOS!$F:$F,0))&", con cédula "&INDEX(VEHICULOS!$Z:$Z,MATCH($O22,VEHICULOS!$F:$F,0))&" del Vehiculo Tipo "&INDEX(VEHICULOS!$H:$H,MATCH($O22,VEHICULOS!$F:$F,0))&" marca "&INDEX(VEHICULOS!$G:$G,MATCH($O22,VEHICULOS!$F:$F,0))&", color "&INDEX(VEHICULOS!$J:$J,MATCH($O22,VEHICULOS!$F:$F,0))&" con placas "&$O22&", por "&INDEX(VEHICULOS!$Q:$Q,MATCH($O22,VEHICULOS!$F:$F,0))&".","REVISAR: placa no encontrada en VEHICULOS")) -> Parte policial Nro. 2026030607392661603, Hoja de Ingreso y Salida Nro. 0002052, entregado al señor CHACON MOLINA PABLO ALFREDO, con cédula ´0502119522 del Vehiculo Tipo TRACTO CAMIÓN marca KENWORTH, color ANARANJADO con placas XAA1180, por ACCIDENTE DE TRANSITO. | F22: =IF($O22="","",IFERROR(INDEX(VEHICULOS!$D:$D,MATCH($O22,VEHICULOS!$F:$F,0)),"")) -> 46087 | G22: =IF($O22="","",IFERROR(INDEX(VEHICULOS!$V:$V,MATCH($O22,VEHICULOS!$F:$F,0)),"")) -> 46093 | H22: 22 | I22: Eliminación | J22: Fisico | O22: XAA1180
A23: Retenciones Vehiculares | B23: 1 | C23: 0018_2026 | D23: 1/1 | E23: =IF($O23="","",IFERROR("Parte policial Nro. "&SUBSTITUTE(INDEX(VEHICULOS!$N:$N,MATCH($O23,VEHICULOS!$F:$F,0)),"´","")&", Hoja de Ingreso y Salida Nro. "&TEXT(INDEX(VEHICULOS!$E:$E,MATCH($O23,VEHICULOS!$F:$F,0)),"0000000")&", entregado al señor "&INDEX(VEHICULOS!$P:$P,MATCH($O23,VEHICULOS!$F:$F,0))&", con cédula "&INDEX(VEHICULOS!$Z:$Z,MATCH($O23,VEHICULOS!$F:$F,0))&" del Vehiculo Tipo "&INDEX(VEHICULOS!$H:$H,MATCH($O23,VEHICULOS!$F:$F,0))&" marca "&INDEX(VEHICULOS!$G:$G,MATCH($O23,VEHICULOS!$F:$F,0))&", color "&INDEX(VEHICULOS!$J:$J,MATCH($O23,VEHICULOS!$F:$F,0))&" con placas "&$O23&", por "&INDEX(VEHICULOS!$Q:$Q,MATCH($O23,VEHICULOS!$F:$F,0))&".","REVISAR: placa no encontrada en VEHICULOS")) -> Parte policial Nro. 2026031001195636511, Hoja de Ingreso y Salida Nro. 0002053, entregado al señor MONTERO PINOS EDUARDO ANGEL, con cédula 1500421878 del Vehiculo Tipo BUS marca HINO, color AZUL con placas JAA1725, por ACCIDENTE DE TRANSITO. | F23: =IF($O23="","",IFERROR(INDEX(VEHICULOS!$D:$D,MATCH($O23,VEHICULOS!$F:$F,0)),"")) -> 46091 | G23: =IF($O23="","",IFERROR(INDEX(VEHICULOS!$V:$V,MATCH($O23,VEHICULOS!$F:$F,0)),"")) -> 46093 | H23: 21 | I23: Eliminación | J23: Fisico | O23: JAA1725
A24: Retenciones Vehiculares | B24: 1 | C24: 0019_2026 | D24: 1/1 | E24: =IF($O24="","",IFERROR("Parte policial Nro. "&SUBSTITUTE(INDEX(VEHICULOS!$N:$N,MATCH($O24,VEHICULOS!$F:$F,0)),"´","")&", Hoja de Ingreso y Salida Nro. "&TEXT(INDEX(VEHICULOS!$E:$E,MATCH($O24,VEHICULOS!$F:$F,0)),"0000000")&", entregado al señor "&INDEX(VEHICULOS!$P:$P,MATCH($O24,VEHICULOS!$F:$F,0))&", con cédula "&INDEX(VEHICULOS!$Z:$Z,MATCH($O24,VEHICULOS!$F:$F,0))&" del Vehiculo Tipo "&INDEX(VEHICULOS!$H:$H,MATCH($O24,VEHICULOS!$F:$F,0))&" marca "&INDEX(VEHICULOS!$G:$G,MATCH($O24,VEHICULOS!$F:$F,0))&", color "&INDEX(VEHICULOS!$J:$J,MATCH($O24,VEHICULOS!$F:$F,0))&" con placas "&$O24&", por "&INDEX(VEHICULOS!$Q:$Q,MATCH($O24,VEHICULOS!$F:$F,0))&".","REVISAR: placa no encontrada en VEHICULOS")) -> Parte policial Nro. 202603130919564104, Hoja de Ingreso y Salida Nro. 0002054, entregado al señor CHINGAL ZUÑIGA DALY VANESSA, con cédula 1758756249 del Vehiculo Tipo CAMIÓN marca CHEVROLET, color BLANCO con placas IBA1861, por ACCIDENTE DE TRANSITO. | F24: =IF($O24="","",IFERROR(INDEX(VEHICULOS!$D:$D,MATCH($O24,VEHICULOS!$F:$F,0)),"")) -> 46094 | G24: =IF($O24="","",IFERROR(INDEX(VEHICULOS!$V:$V,MATCH($O24,VEHICULOS!$F:$F,0)),"")) -> 46100 | H24: 15 | I24: Eliminación | J24: Fisico | O24: IBA1861
A25: Retenciones Vehiculares | B25: 1 | C25: 0020_2026 | D25: 1/1 | E25: =IF($O25="","",IFERROR("Parte policial Nro. "&SUBSTITUTE(INDEX(VEHICULOS!$N:$N,MATCH($O25,VEHICULOS!$F:$F,0)),"´","")&", Hoja de Ingreso y Salida Nro. "&TEXT(INDEX(VEHICULOS!$E:$E,MATCH($O25,VEHICULOS!$F:$F,0)),"0000000")&", entregado al señor "&INDEX(VEHICULOS!$P:$P,MATCH($O25,VEHICULOS!$F:$F,0))&", con cédula "&INDEX(VEHICULOS!$Z:$Z,MATCH($O25,VEHICULOS!$F:$F,0))&" del Vehiculo Tipo "&INDEX(VEHICULOS!$H:$H,MATCH($O25,VEHICULOS!$F:$F,0))&" marca "&INDEX(VEHICULOS!$G:$G,MATCH($O25,VEHICULOS!$F:$F,0))&", color "&INDEX(VEHICULOS!$J:$J,MATCH($O25,VEHICULOS!$F:$F,0))&" con placas "&$O25&", por "&INDEX(VEHICULOS!$Q:$Q,MATCH($O25,VEHICULOS!$F:$F,0))&".","REVISAR: placa no encontrada en VEHICULOS")) -> Parte policial Nro. 202603130919564104, Hoja de Ingreso y Salida Nro. 0002055, entregado al señor PERALVO GARCIA MARCO VINIVIO, con cédula 1716186547 del Vehiculo Tipo TRACTO CAMIÓN marca KENWORTH, color AZUL con placas PAE1001, por ACCIDENTE DE TRANSITO. | F25: =IF($O25="","",IFERROR(INDEX(VEHICULOS!$D:$D,MATCH($O25,VEHICULOS!$F:$F,0)),"")) -> 46094 | G25: =IF($O25="","",IFERROR(INDEX(VEHICULOS!$V:$V,MATCH($O25,VEHICULOS!$F:$F,0)),"")) -> 46100 | H25: 15 | I25: Eliminación | J25: Fisico | O25: PAE1001
A26: Retenciones Vehiculares | B26: 1 | C26: 0021_2026 | D26: 1/1 | E26: =IF($O26="","",IFERROR("Parte policial Nro. "&SUBSTITUTE(INDEX(VEHICULOS!$N:$N,MATCH($O26,VEHICULOS!$F:$F,0)),"´","")&", Hoja de Ingreso y Salida Nro. "&TEXT(INDEX(VEHICULOS!$E:$E,MATCH($O26,VEHICULOS!$F:$F,0)),"0000000")&", entregado al señor "&INDEX(VEHICULOS!$P:$P,MATCH($O26,VEHICULOS!$F:$F,0))&", con cédula "&INDEX(VEHICULOS!$Z:$Z,MATCH($O26,VEHICULOS!$F:$F,0))&" del Vehiculo Tipo "&INDEX(VEHICULOS!$H:$H,MATCH($O26,VEHICULOS!$F:$F,0))&" marca "&INDEX(VEHICULOS!$G:$G,MATCH($O26,VEHICULOS!$F:$F,0))&", color "&INDEX(VEHICULOS!$J:$J,MATCH($O26,VEHICULOS!$F:$F,0))&" con placas "&$O26&", por "&INDEX(VEHICULOS!$Q:$Q,MATCH($O26,VEHICULOS!$F:$F,0))&".","REVISAR: placa no encontrada en VEHICULOS")) -> Parte policial Nro. 202603140924020503, Hoja de Ingreso y Salida Nro. 0002056, entregado al señor HARO OÑATE MARTHA CECILIA, con cédula ´0601972102 del Vehiculo Tipo BUS marca HINO, color PLATEADO con placas JAA3530, por ACCIDENTE DE TRANSITO. | F26: =IF($O26="","",IFERROR(INDEX(VEHICULOS!$D:$D,MATCH($O26,VEHICULOS!$F:$F,0)),"")) -> 46095 | G26: =IF($O26="","",IFERROR(INDEX(VEHICULOS!$V:$V,MATCH($O26,VEHICULOS!$F:$F,0)),"")) -> 46101 | H26: 19 | I26: Eliminación | J26: Fisico | O26: JAA3530
A27: Retenciones Vehiculares | B27: 1 | C27: 0022_2026 | D27: 1/1 | E27: =IF($O27="","",IFERROR("Parte policial Nro. "&SUBSTITUTE(INDEX(VEHICULOS!$N:$N,MATCH($O27,VEHICULOS!$F:$F,0)),"´","")&", Hoja de Ingreso y Salida Nro. "&TEXT(INDEX(VEHICULOS!$E:$E,MATCH($O27,VEHICULOS!$F:$F,0)),"0000000")&", entregado al señor "&INDEX(VEHICULOS!$P:$P,MATCH($O27,VEHICULOS!$F:$F,0))&", con cédula "&INDEX(VEHICULOS!$Z:$Z,MATCH($O27,VEHICULOS!$F:$F,0))&" del Vehiculo Tipo "&INDEX(VEHICULOS!$H:$H,MATCH($O27,VEHICULOS!$F:$F,0))&" marca "&INDEX(VEHICULOS!$G:$G,MATCH($O27,VEHICULOS!$F:$F,0))&", color "&INDEX(VEHICULOS!$J:$J,MATCH($O27,VEHICULOS!$F:$F,0))&" con placas "&$O27&", por "&INDEX(VEHICULOS!$Q:$Q,MATCH($O27,VEHICULOS!$F:$F,0))&".","REVISAR: placa no encontrada en VEHICULOS")) -> Parte policial Nro. 2026013009255363017, Hoja de Ingreso y Salida Nro. 0002039, entregado al señor CAIZAGUANO CHICAIZA ANGEL DIEGO, con cédula 0604415398 del Vehiculo Tipo CAMIÓN marca HINO, color AZUL con placas GPX0484, por ACCIDENTE DE TRANSITO. | F27: =IF($O27="","",IFERROR(INDEX(VEHICULOS!$D:$D,MATCH($O27,VEHICULOS!$F:$F,0)),"")) -> 46052 | G27: =IF($O27="","",IFERROR(INDEX(VEHICULOS!$V:$V,MATCH($O27,VEHICULOS!$F:$F,0)),"")) -> 46101 | H27: 28 | I27: Eliminación | J27: Fisico | O27: GPX0484
A28: Retenciones Vehiculares | B28: 1 | C28: 0023_2026 | D28: 1/1 | E28: =IF($O28="","",IFERROR("Parte policial Nro. "&SUBSTITUTE(INDEX(VEHICULOS!$N:$N,MATCH($O28,VEHICULOS!$F:$F,0)),"´","")&", Hoja de Ingreso y Salida Nro. "&TEXT(INDEX(VEHICULOS!$E:$E,MATCH($O28,VEHICULOS!$F:$F,0)),"0000000")&", entregado al señor "&INDEX(VEHICULOS!$P:$P,MATCH($O28,VEHICULOS!$F:$F,0))&", con cédula "&INDEX(VEHICULOS!$Z:$Z,MATCH($O28,VEHICULOS!$F:$F,0))&" del Vehiculo Tipo "&INDEX(VEHICULOS!$H:$H,MATCH($O28,VEHICULOS!$F:$F,0))&" marca "&INDEX(VEHICULOS!$G:$G,MATCH($O28,VEHICULOS!$F:$F,0))&", color "&INDEX(VEHICULOS!$J:$J,MATCH($O28,VEHICULOS!$F:$F,0))&" con placas "&$O28&", por "&INDEX(VEHICULOS!$Q:$Q,MATCH($O28,VEHICULOS!$F:$F,0))&".","REVISAR: placa no encontrada en VEHICULOS")) -> Parte policial Nro. 202602060046268510, Hoja de Ingreso y Salida Nro. 0002045, entregado al señor ORIENTAL ALIMENTICIA S.A., con cédula 1206209627 del Vehiculo Tipo CABEZAL marca SINOTRUK, color BLANCO con placas GTT9096, por ACCIDENTE DE TRANSITO. | F28: =IF($O28="","",IFERROR(INDEX(VEHICULOS!$D:$D,MATCH($O28,VEHICULOS!$F:$F,0)),"")) -> 46059 | G28: =IF($O28="","",IFERROR(INDEX(VEHICULOS!$V:$V,MATCH($O28,VEHICULOS!$F:$F,0)),"")) -> 46106 | H28: 20 | I28: Eliminación | J28: Fisico | O28: GTT9096
A29: Retenciones Vehiculares | B29: 1 | C29: 0024_2026 | D29: 1/1 | E29: =IF($O29="","",IFERROR("Parte policial Nro. "&SUBSTITUTE(INDEX(VEHICULOS!$N:$N,MATCH($O29,VEHICULOS!$F:$F,0)),"´","")&", Hoja de Ingreso y Salida Nro. "&TEXT(INDEX(VEHICULOS!$E:$E,MATCH($O29,VEHICULOS!$F:$F,0)),"0000000")&", entregado al señor "&INDEX(VEHICULOS!$P:$P,MATCH($O29,VEHICULOS!$F:$F,0))&", con cédula "&INDEX(VEHICULOS!$Z:$Z,MATCH($O29,VEHICULOS!$F:$F,0))&" del Vehiculo Tipo "&INDEX(VEHICULOS!$H:$H,MATCH($O29,VEHICULOS!$F:$F,0))&" marca "&INDEX(VEHICULOS!$G:$G,MATCH($O29,VEHICULOS!$F:$F,0))&", color "&INDEX(VEHICULOS!$J:$J,MATCH($O29,VEHICULOS!$F:$F,0))&" con placas "&$O29&", por "&INDEX(VEHICULOS!$Q:$Q,MATCH($O29,VEHICULOS!$F:$F,0))&".","REVISAR: placa no encontrada en VEHICULOS")) -> Parte policial Nro. 2026022511524258300, Hoja de Ingreso y Salida Nro. 0002050, entregado al señor DISTRIBUIDORA IMPORTADORA DIPORT, con cédula 1706508155 del Vehiculo Tipo FURGON marca HINO, color BLANCO con placas RCF0072, por ACCIDENTE DE TRANSITO. | F29: =IF($O29="","",IFERROR(INDEX(VEHICULOS!$D:$D,MATCH($O29,VEHICULOS!$F:$F,0)),"")) -> 46078 | G29: =IF($O29="","",IFERROR(INDEX(VEHICULOS!$V:$V,MATCH($O29,VEHICULOS!$F:$F,0)),"")) -> 46122 | H29: 30 | I29: Eliminación | J29: Fisico | O29: RCF0072
A30: Retenciones Vehiculares | B30: 1 | C30: 0025_2026 | D30: 1/1 | E30: =IF($O30="","",IFERROR("Parte policial Nro. "&SUBSTITUTE(INDEX(VEHICULOS!$N:$N,MATCH($O30,VEHICULOS!$F:$F,0)),"´","")&", Hoja de Ingreso y Salida Nro. "&TEXT(INDEX(VEHICULOS!$E:$E,MATCH($O30,VEHICULOS!$F:$F,0)),"0000000")&", entregado al señor "&INDEX(VEHICULOS!$P:$P,MATCH($O30,VEHICULOS!$F:$F,0))&", con cédula "&INDEX(VEHICULOS!$Z:$Z,MATCH($O30,VEHICULOS!$F:$F,0))&" del Vehiculo Tipo "&INDEX(VEHICULOS!$H:$H,MATCH($O30,VEHICULOS!$F:$F,0))&" marca "&INDEX(VEHICULOS!$G:$G,MATCH($O30,VEHICULOS!$F:$F,0))&", color "&INDEX(VEHICULOS!$J:$J,MATCH($O30,VEHICULOS!$F:$F,0))&" con placas "&$O30&", por "&INDEX(VEHICULOS!$Q:$Q,MATCH($O30,VEHICULOS!$F:$F,0))&".","REVISAR: placa no encontrada en VEHICULOS")) -> Parte policial Nro. 2026032310204179007, Hoja de Ingreso y Salida Nro. 0002058, entregado al señor TAPIA LOPEZ EDGAR FERNANDO, con cédula 0502060635 del Vehiculo Tipo TRACTO CAMIÓN marca INTERNATIONAL, color ROJO con placas CAA1101, por ACCIDENTE DE TRANSITO. | F30: =IF($O30="","",IFERROR(INDEX(VEHICULOS!$D:$D,MATCH($O30,VEHICULOS!$F:$F,0)),"")) -> 46103 | G30: =IF($O30="","",IFERROR(INDEX(VEHICULOS!$V:$V,MATCH($O30,VEHICULOS!$F:$F,0)),"")) -> 46113 | H30: 18 | I30: Eliminación | J30: Fisico | N30: la fecha de elaboracion del parte es 23/08/2026 | O30: CAA1101
A31: Retenciones Vehiculares | B31: 1 | C31: 0026_2026 | D31: 1/1 | E31: =IF($O31="","",IFERROR("Parte policial Nro. "&SUBSTITUTE(INDEX(VEHICULOS!$N:$N,MATCH($O31,VEHICULOS!$F:$F,0)),"´","")&", Hoja de Ingreso y Salida Nro. "&TEXT(INDEX(VEHICULOS!$E:$E,MATCH($O31,VEHICULOS!$F:$F,0)),"0000000")&", entregado al señor "&INDEX(VEHICULOS!$P:$P,MATCH($O31,VEHICULOS!$F:$F,0))&", con cédula "&INDEX(VEHICULOS!$Z:$Z,MATCH($O31,VEHICULOS!$F:$F,0))&" del Vehiculo Tipo "&INDEX(VEHICULOS!$H:$H,MATCH($O31,VEHICULOS!$F:$F,0))&" marca "&INDEX(VEHICULOS!$G:$G,MATCH($O31,VEHICULOS!$F:$F,0))&", color "&INDEX(VEHICULOS!$J:$J,MATCH($O31,VEHICULOS!$F:$F,0))&" con placas "&$O31&", por "&INDEX(VEHICULOS!$Q:$Q,MATCH($O31,VEHICULOS!$F:$F,0))&".","REVISAR: placa no encontrada en VEHICULOS")) -> Parte policial Nro. 20260311709433770701, Hoja de Ingreso y Salida Nro. 0002057, entregado al señor AGILA LALANGUI OLGA ISABEL, con cédula 1718853326 del Vehiculo Tipo CABEZAL marca MERCEDEZ BENZ, color PLOMO con placas QAA3010, por ACCIDENTE DE TRANSITO. | F31: =IF($O31="","",IFERROR(INDEX(VEHICULOS!$D:$D,MATCH($O31,VEHICULOS!$F:$F,0)),"")) -> 46098 | G31: =IF($O31="","",IFERROR(INDEX(VEHICULOS!$V:$V,MATCH($O31,VEHICULOS!$F:$F,0)),"")) -> 46108 | H31: 19 | I31: Eliminación | J31: Fisico | O31: QAA3010
A32: Retenciones Vehiculares | B32: 1 | C32: 0027_2026 | D32: 1/1 | E32: =IF($O32="","",IFERROR("Parte policial Nro. "&SUBSTITUTE(INDEX(VEHICULOS!$N:$N,MATCH($O32,VEHICULOS!$F:$F,0)),"´","")&", Hoja de Ingreso y Salida Nro. "&TEXT(INDEX(VEHICULOS!$E:$E,MATCH($O32,VEHICULOS!$F:$F,0)),"0000000")&", entregado al señor "&INDEX(VEHICULOS!$P:$P,MATCH($O32,VEHICULOS!$F:$F,0))&", con cédula "&INDEX(VEHICULOS!$Z:$Z,MATCH($O32,VEHICULOS!$F:$F,0))&" del Vehiculo Tipo "&INDEX(VEHICULOS!$H:$H,MATCH($O32,VEHICULOS!$F:$F,0))&" marca "&INDEX(VEHICULOS!$G:$G,MATCH($O32,VEHICULOS!$F:$F,0))&", color "&INDEX(VEHICULOS!$J:$J,MATCH($O32,VEHICULOS!$F:$F,0))&" con placas "&$O32&", por "&INDEX(VEHICULOS!$Q:$Q,MATCH($O32,VEHICULOS!$F:$F,0))&".","REVISAR: placa no encontrada en VEHICULOS")) -> Parte policial Nro. 202603237112163205, Hoja de Ingreso y Salida Nro. 0002059, entregado al señor CHANGOLUISA VENEGAS OSCAR ROLANDO, con cédula 1713838694 del Vehiculo Tipo FURGON marca CHEVROLET, color ROJO con placas CBL0337, por ART. 160. | F32: =IF($O32="","",IFERROR(INDEX(VEHICULOS!$D:$D,MATCH($O32,VEHICULOS!$F:$F,0)),"")) -> 46103 | G32: =IF($O32="","",IFERROR(INDEX(VEHICULOS!$V:$V,MATCH($O32,VEHICULOS!$F:$F,0)),"")) -> 46104 | H32: 12 | I32: Eliminación | J32: Fisico | O32: CBL0337
A33: Retenciones Vehiculares | B33: 1 | C33: 0028_2026 | D33: 1/1 | E33: =IF($O33="","",IFERROR("Parte policial Nro. "&SUBSTITUTE(INDEX(VEHICULOS!$N:$N,MATCH($O33,VEHICULOS!$F:$F,0)),"´","")&", Hoja de Ingreso y Salida Nro. "&TEXT(INDEX(VEHICULOS!$E:$E,MATCH($O33,VEHICULOS!$F:$F,0)),"0000000")&", entregado al señor "&INDEX(VEHICULOS!$P:$P,MATCH($O33,VEHICULOS!$F:$F,0))&", con cédula "&INDEX(VEHICULOS!$Z:$Z,MATCH($O33,VEHICULOS!$F:$F,0))&" del Vehiculo Tipo "&INDEX(VEHICULOS!$H:$H,MATCH($O33,VEHICULOS!$F:$F,0))&" marca "&INDEX(VEHICULOS!$G:$G,MATCH($O33,VEHICULOS!$F:$F,0))&", color "&INDEX(VEHICULOS!$J:$J,MATCH($O33,VEHICULOS!$F:$F,0))&" con placas "&$O33&", por "&INDEX(VEHICULOS!$Q:$Q,MATCH($O33,VEHICULOS!$F:$F,0))&".","REVISAR: placa no encontrada en VEHICULOS")) -> Parte policial Nro. 2026031810551959409, Hoja de Ingreso y Salida Nro. 0002060, entregado al señor MURILLO VELAZQUEZ STALIN LEONEL, con cédula 2350595589 del Vehiculo Tipo CAMIÓN marca HINO, color BLANCO con placas XCB0016, por ACCIDENTE DE TRANSITO. | F33: =IF($O33="","",IFERROR(INDEX(VEHICULOS!$D:$D,MATCH($O33,VEHICULOS!$F:$F,0)),"")) -> 46098 | G33: =IF($O33="","",IFERROR(INDEX(VEHICULOS!$V:$V,MATCH($O33,VEHICULOS!$F:$F,0)),"")) -> 46113 | H33: 27 | I33: Eliminación | J33: Fisico | O33: XCB0016
A34: Retenciones Vehiculares | B34: 1 | C34: 0029_2026 | D34: 1/1 | E34: =IF($O34="","",IFERROR("Parte policial Nro. "&SUBSTITUTE(INDEX(VEHICULOS!$N:$N,MATCH($O34,VEHICULOS!$F:$F,0)),"´","")&", Hoja de Ingreso y Salida Nro. "&TEXT(INDEX(VEHICULOS!$E:$E,MATCH($O34,VEHICULOS!$F:$F,0)),"0000000")&", entregado al señor "&INDEX(VEHICULOS!$P:$P,MATCH($O34,VEHICULOS!$F:$F,0))&", con cédula "&INDEX(VEHICULOS!$Z:$Z,MATCH($O34,VEHICULOS!$F:$F,0))&" del Vehiculo Tipo "&INDEX(VEHICULOS!$H:$H,MATCH($O34,VEHICULOS!$F:$F,0))&" marca "&INDEX(VEHICULOS!$G:$G,MATCH($O34,VEHICULOS!$F:$F,0))&", color "&INDEX(VEHICULOS!$J:$J,MATCH($O34,VEHICULOS!$F:$F,0))&" con placas "&$O34&", por "&INDEX(VEHICULOS!$Q:$Q,MATCH($O34,VEHICULOS!$F:$F,0))&".","REVISAR: placa no encontrada en VEHICULOS")) -> Parte policial Nro. 2026032809402780510, Hoja de Ingreso y Salida Nro. 0002063, entregado al señor GAD STO. DOMINGO, con cédula 1719428508 del Vehiculo Tipo VOLQUETA marca HINO, color AMARILLO con placas JEI1029, por ACCIDENTE TRANSITO. | F34: =IF($O34="","",IFERROR(INDEX(VEHICULOS!$D:$D,MATCH($O34,VEHICULOS!$F:$F,0)),"")) -> 46109 | G34: =IF($O34="","",IFERROR(INDEX(VEHICULOS!$V:$V,MATCH($O34,VEHICULOS!$F:$F,0)),"")) -> 46121 | H34: 21 | I34: Eliminación | J34: Fisico | O34: JEI1029
A35: Retenciones Vehiculares | B35: 1 | C35: 0030_2026 | D35: 1/1 | E35: =IF($O35="","",IFERROR("Parte policial Nro. "&SUBSTITUTE(INDEX(VEHICULOS!$N:$N,MATCH($O35,VEHICULOS!$F:$F,0)),"´","")&", Hoja de Ingreso y Salida Nro. "&TEXT(INDEX(VEHICULOS!$E:$E,MATCH($O35,VEHICULOS!$F:$F,0)),"0000000")&", entregado al señor "&INDEX(VEHICULOS!$P:$P,MATCH($O35,VEHICULOS!$F:$F,0))&", con cédula "&INDEX(VEHICULOS!$Z:$Z,MATCH($O35,VEHICULOS!$F:$F,0))&" del Vehiculo Tipo "&INDEX(VEHICULOS!$H:$H,MATCH($O35,VEHICULOS!$F:$F,0))&" marca "&INDEX(VEHICULOS!$G:$G,MATCH($O35,VEHICULOS!$F:$F,0))&", color "&INDEX(VEHICULOS!$J:$J,MATCH($O35,VEHICULOS!$F:$F,0))&" con placas "&$O35&", por "&INDEX(VEHICULOS!$Q:$Q,MATCH($O35,VEHICULOS!$F:$F,0))&".","REVISAR: placa no encontrada en VEHICULOS")) -> Parte policial Nro. 2026020503164428108, Hoja de Ingreso y Salida Nro. 0002043, entregado al señor CAZA MENDEZ JOSE LUIS, con cédula 1721866018 del Vehiculo Tipo PLATAFORMA marca CHEVROLET, color BLANCO con placas CAE0442, por ACCIDENTE DE TRANSITO. | F35: =IF($O35="","",IFERROR(INDEX(VEHICULOS!$D:$D,MATCH($O35,VEHICULOS!$F:$F,0)),"")) -> 46058 | G35: =IF($O35="","",IFERROR(INDEX(VEHICULOS!$V:$V,MATCH($O35,VEHICULOS!$F:$F,0)),"")) -> 46128 | H35: 20 | I35: Eliminación | J35: Fisico | O35: CAE0442
A36: Retenciones Vehiculares | B36: 1 | C36: =TEXT(VALUE(LEFT(C35,4))+1,"0000")&"_2026" -> 0031_2026 | D36: 1/1 | E36: =IF($O36="","",IFERROR("Parte policial Nro. "&SUBSTITUTE(INDEX(VEHICULOS!$N:$N,MATCH($O36,VEHICULOS!$F:$F,0)),"´","")&", Hoja de Ingreso y Salida Nro. "&TEXT(INDEX(VEHICULOS!$E:$E,MATCH($O36,VEHICULOS!$F:$F,0)),"0000000")&", entregado al señor "&INDEX(VEHICULOS!$P:$P,MATCH($O36,VEHICULOS!$F:$F,0))&", con cédula "&INDEX(VEHICULOS!$Z:$Z,MATCH($O36,VEHICULOS!$F:$F,0))&" del Vehiculo Tipo "&INDEX(VEHICULOS!$H:$H,MATCH($O36,VEHICULOS!$F:$F,0))&" marca "&INDEX(VEHICULOS!$G:$G,MATCH($O36,VEHICULOS!$F:$F,0))&", color "&INDEX(VEHICULOS!$J:$J,MATCH($O36,VEHICULOS!$F:$F,0))&" con placas "&$O36&", por "&INDEX(VEHICULOS!$Q:$Q,MATCH($O36,VEHICULOS!$F:$F,0))&".","REVISAR: placa no encontrada en VEHICULOS")) -> Parte policial Nro. 2026032809402780510, Hoja de Ingreso y Salida Nro. 0002062, entregado al señor VALERA VILLAVICENCIO CHISTIAN, con cédula 1726674011 del Vehiculo Tipo CAMIÓN marca JAC, color BLANCO con placas TBB2616, por ACCIDENTE DE TRANSITO. | F36: =IF($O36="","",IFERROR(INDEX(VEHICULOS!$D:$D,MATCH($O36,VEHICULOS!$F:$F,0)),"")) -> 46109 | G36: =IF($O36="","",IFERROR(INDEX(VEHICULOS!$V:$V,MATCH($O36,VEHICULOS!$F:$F,0)),"")) -> 46156 | H36: 13 | I36: Eliminación | J36: Fisico | O36: TBB2616
A37: Retenciones Vehiculares | B37: 1 | C37: =TEXT(VALUE(LEFT(C36,4))+1,"0000")&"_2026" -> 0032_2026 | D37: 1/1 | E37: =IF($O37="","",IFERROR("Parte policial Nro. "&SUBSTITUTE(INDEX(VEHICULOS!$N:$N,MATCH($O37,VEHICULOS!$F:$F,0)),"´","")&", Hoja de Ingreso y Salida Nro. "&TEXT(INDEX(VEHICULOS!$E:$E,MATCH($O37,VEHICULOS!$F:$F,0)),"0000000")&", entregado al señor "&INDEX(VEHICULOS!$P:$P,MATCH($O37,VEHICULOS!$F:$F,0))&", con cédula "&INDEX(VEHICULOS!$Z:$Z,MATCH($O37,VEHICULOS!$F:$F,0))&" del Vehiculo Tipo "&INDEX(VEHICULOS!$H:$H,MATCH($O37,VEHICULOS!$F:$F,0))&" marca "&INDEX(VEHICULOS!$G:$G,MATCH($O37,VEHICULOS!$F:$F,0))&", color "&INDEX(VEHICULOS!$J:$J,MATCH($O37,VEHICULOS!$F:$F,0))&" con placas "&$O37&", por "&INDEX(VEHICULOS!$Q:$Q,MATCH($O37,VEHICULOS!$F:$F,0))&".","REVISAR: placa no encontrada en VEHICULOS")) -> Parte policial Nro. 2026040610455152911, Hoja de Ingreso y Salida Nro. 0002065, entregado al señor GUANOQUIZA VALIENTE MILTON PATRICIO, con cédula 0502919780 del Vehiculo Tipo AUTOBUS marca HINO, color AZUL con placas TAT0311, por ART. 386 INCISO 3 #1. | F37: =IF($O37="","",IFERROR(INDEX(VEHICULOS!$D:$D,MATCH($O37,VEHICULOS!$F:$F,0)),"")) -> 46117 | G37: =IF($O37="","",IFERROR(INDEX(VEHICULOS!$V:$V,MATCH($O37,VEHICULOS!$F:$F,0)),"")) -> 46137 | H37: 25 | I37: Eliminación | J37: Fisico | O37: TAT0311
A38: Retenciones Vehiculares | B38: 1 | C38: =TEXT(VALUE(LEFT(C37,4))+1,"0000")&"_2026" -> 0033_2026 | D38: 1/1 | E38: =IF($O38="","",IFERROR("Parte policial Nro. "&SUBSTITUTE(INDEX(VEHICULOS!$N:$N,MATCH($O38,VEHICULOS!$F:$F,0)),"´","")&", Hoja de Ingreso y Salida Nro. "&TEXT(INDEX(VEHICULOS!$E:$E,MATCH($O38,VEHICULOS!$F:$F,0)),"0000000")&", entregado al señor "&INDEX(VEHICULOS!$P:$P,MATCH($O38,VEHICULOS!$F:$F,0))&", con cédula "&INDEX(VEHICULOS!$Z:$Z,MATCH($O38,VEHICULOS!$F:$F,0))&" del Vehiculo Tipo "&INDEX(VEHICULOS!$H:$H,MATCH($O38,VEHICULOS!$F:$F,0))&" marca "&INDEX(VEHICULOS!$G:$G,MATCH($O38,VEHICULOS!$F:$F,0))&", color "&INDEX(VEHICULOS!$J:$J,MATCH($O38,VEHICULOS!$F:$F,0))&" con placas "&$O38&", por "&INDEX(VEHICULOS!$Q:$Q,MATCH($O38,VEHICULOS!$F:$F,0))&".","REVISAR: placa no encontrada en VEHICULOS")) -> Parte policial Nro. 202604100449574102, Hoja de Ingreso y Salida Nro. 0002066, entregado al señor PAEZ MIÑIZ JORGE REINALDO, con cédula 1723853600 del Vehiculo Tipo CAMIÓN marca CHEVROLET, color BLANCO con placas PAA8922, por ACCIDENTE DE TRANSITO. | F38: =IF($O38="","",IFERROR(INDEX(VEHICULOS!$D:$D,MATCH($O38,VEHICULOS!$F:$F,0)),"")) -> 46122 | G38: =IF($O38="","",IFERROR(INDEX(VEHICULOS!$V:$V,MATCH($O38,VEHICULOS!$F:$F,0)),"")) -> 46134 | H38: 20 | I38: Eliminación | J38: Fisico | O38: PAA8922
A39: Retenciones Vehiculares | B39: 1 | C39: =TEXT(VALUE(LEFT(C38,4))+1,"0000")&"_2026" -> 0034_2026 | D39: 1/1 | E39: =IF($O39="","",IFERROR("Parte policial Nro. "&SUBSTITUTE(INDEX(VEHICULOS!$N:$N,MATCH($O39,VEHICULOS!$F:$F,0)),"´","")&", Hoja de Ingreso y Salida Nro. "&TEXT(INDEX(VEHICULOS!$E:$E,MATCH($O39,VEHICULOS!$F:$F,0)),"0000000")&", entregado al señor "&INDEX(VEHICULOS!$P:$P,MATCH($O39,VEHICULOS!$F:$F,0))&", con cédula "&INDEX(VEHICULOS!$Z:$Z,MATCH($O39,VEHICULOS!$F:$F,0))&" del Vehiculo Tipo "&INDEX(VEHICULOS!$H:$H,MATCH($O39,VEHICULOS!$F:$F,0))&" marca "&INDEX(VEHICULOS!$G:$G,MATCH($O39,VEHICULOS!$F:$F,0))&", color "&INDEX(VEHICULOS!$J:$J,MATCH($O39,VEHICULOS!$F:$F,0))&" con placas "&$O39&", por "&INDEX(VEHICULOS!$Q:$Q,MATCH($O39,VEHICULOS!$F:$F,0))&".","REVISAR: placa no encontrada en VEHICULOS")) -> Parte policial Nro. 2026041603160431611, Hoja de Ingreso y Salida Nro. 0002068, entregado al señor CORTEZ ROGEL ELIZABETH, con cédula 0802740647 del Vehiculo Tipo PLATAFORMA marca HINO, color BLANCO con placas LBX0099, por ACCIDENTE DE TRANSITO. | F39: =IF($O39="","",IFERROR(INDEX(VEHICULOS!$D:$D,MATCH($O39,VEHICULOS!$F:$F,0)),"")) -> 46128 | G39: =IF($O39="","",IFERROR(INDEX(VEHICULOS!$V:$V,MATCH($O39,VEHICULOS!$F:$F,0)),"")) -> 46162 | H39: 26 | I39: Eliminación | J39: Fisico | O39: LBX0099
A40: Retenciones Vehiculares | B40: 1 | C40: =TEXT(VALUE(LEFT(C39,4))+1,"0000")&"_2026" -> 0035_2026 | D40: 1/1 | E40: =IF($O40="","",IFERROR("Parte policial Nro. "&SUBSTITUTE(INDEX(VEHICULOS!$N:$N,MATCH($O40,VEHICULOS!$F:$F,0)),"´","")&", Hoja de Ingreso y Salida Nro. "&TEXT(INDEX(VEHICULOS!$E:$E,MATCH($O40,VEHICULOS!$F:$F,0)),"0000000")&", entregado al señor "&INDEX(VEHICULOS!$P:$P,MATCH($O40,VEHICULOS!$F:$F,0))&", con cédula "&INDEX(VEHICULOS!$Z:$Z,MATCH($O40,VEHICULOS!$F:$F,0))&" del Vehiculo Tipo "&INDEX(VEHICULOS!$H:$H,MATCH($O40,VEHICULOS!$F:$F,0))&" marca "&INDEX(VEHICULOS!$G:$G,MATCH($O40,VEHICULOS!$F:$F,0))&", color "&INDEX(VEHICULOS!$J:$J,MATCH($O40,VEHICULOS!$F:$F,0))&" con placas "&$O40&", por "&INDEX(VEHICULOS!$Q:$Q,MATCH($O40,VEHICULOS!$F:$F,0))&".","REVISAR: placa no encontrada en VEHICULOS")) -> Parte policial Nro. 2026042208143572112, Hoja de Ingreso y Salida Nro. 0002069, entregado al señor PINANGO JUAN FRANCISCO, con cédula 1709076234 del Vehiculo Tipo TRACTO CAMIÓN marca FOTON, color DORADO con placas XAA1507, por ACCIDENTE DE TRANSITO. | F40: =IF($O40="","",IFERROR(INDEX(VEHICULOS!$D:$D,MATCH($O40,VEHICULOS!$F:$F,0)),"")) -> 46134 | G40: =IF($O40="","",IFERROR(INDEX(VEHICULOS!$V:$V,MATCH($O40,VEHICULOS!$F:$F,0)),"")) -> 46139 | H40: 15 | I40: Eliminación | J40: Fisico | O40: XAA1507
A41: Retenciones Vehiculares | B41: 1 | C41: =TEXT(VALUE(LEFT(C40,4))+1,"0000")&"_2026" -> 0036_2026 | D41: 1/1 | E41: =IF($O41="","",IFERROR("Parte policial Nro. "&SUBSTITUTE(INDEX(VEHICULOS!$N:$N,MATCH($O41,VEHICULOS!$F:$F,0)),"´","")&", Hoja de Ingreso y Salida Nro. "&TEXT(INDEX(VEHICULOS!$E:$E,MATCH($O41,VEHICULOS!$F:$F,0)),"0000000")&", entregado al señor "&INDEX(VEHICULOS!$P:$P,MATCH($O41,VEHICULOS!$F:$F,0))&", con cédula "&INDEX(VEHICULOS!$Z:$Z,MATCH($O41,VEHICULOS!$F:$F,0))&" del Vehiculo Tipo "&INDEX(VEHICULOS!$H:$H,MATCH($O41,VEHICULOS!$F:$F,0))&" marca "&INDEX(VEHICULOS!$G:$G,MATCH($O41,VEHICULOS!$F:$F,0))&", color "&INDEX(VEHICULOS!$J:$J,MATCH($O41,VEHICULOS!$F:$F,0))&" con placas "&$O41&", por "&INDEX(VEHICULOS!$Q:$Q,MATCH($O41,VEHICULOS!$F:$F,0))&".","REVISAR: placa no encontrada en VEHICULOS")) -> Parte policial Nro. 2026042310012581806, Hoja de Ingreso y Salida Nro. 0002070, entregado al señor LEVERONE ARBOLEDA GARY CRISTHOPER, con cédula 0802813675 del Vehiculo Tipo CAMIÓN marca HINO, color BLANCO con placas TDV0954, por ACCIDENTE DE TRANSITO. | F41: =IF($O41="","",IFERROR(INDEX(VEHICULOS!$D:$D,MATCH($O41,VEHICULOS!$F:$F,0)),"")) -> 46135 | G41: =IF($O41="","",IFERROR(INDEX(VEHICULOS!$V:$V,MATCH($O41,VEHICULOS!$F:$F,0)),"")) -> 46148 | H41: 35 | I41: Eliminación | J41: Fisico | O41: TDV0954
A42: Retenciones Vehiculares | B42: 1 | C42: =TEXT(VALUE(LEFT(C41,4))+1,"0000")&"_2026" -> 0037_2026 | D42: 1/1 | E42: =IF($O42="","",IFERROR("Parte policial Nro. "&SUBSTITUTE(INDEX(VEHICULOS!$N:$N,MATCH($O42,VEHICULOS!$F:$F,0)),"´","")&", Hoja de Ingreso y Salida Nro. "&TEXT(INDEX(VEHICULOS!$E:$E,MATCH($O42,VEHICULOS!$F:$F,0)),"0000000")&", entregado al señor "&INDEX(VEHICULOS!$P:$P,MATCH($O42,VEHICULOS!$F:$F,0))&", con cédula "&INDEX(VEHICULOS!$Z:$Z,MATCH($O42,VEHICULOS!$F:$F,0))&" del Vehiculo Tipo "&INDEX(VEHICULOS!$H:$H,MATCH($O42,VEHICULOS!$F:$F,0))&" marca "&INDEX(VEHICULOS!$G:$G,MATCH($O42,VEHICULOS!$F:$F,0))&", color "&INDEX(VEHICULOS!$J:$J,MATCH($O42,VEHICULOS!$F:$F,0))&" con placas "&$O42&", por "&INDEX(VEHICULOS!$Q:$Q,MATCH($O42,VEHICULOS!$F:$F,0))&".","REVISAR: placa no encontrada en VEHICULOS")) -> Parte policial Nro. 2026050302104185307, Hoja de Ingreso y Salida Nro. 0002071, entregado al señor BARONA FIALLOS ANGEL GUSTAVO, con cédula 1711484004 del Vehiculo Tipo BUS marca CHEVROLET, color ANARANJADO con placas IAI0267, por ACCIDENTE DE TRANSITO. | F42: =IF($O42="","",IFERROR(INDEX(VEHICULOS!$D:$D,MATCH($O42,VEHICULOS!$F:$F,0)),"")) -> 46145 | G42: =IF($O42="","",IFERROR(INDEX(VEHICULOS!$V:$V,MATCH($O42,VEHICULOS!$F:$F,0)),"")) -> 46148 | H42: 24 | I42: Eliminación | J42: Fisico | O42: IAI0267
A43: Retenciones Vehiculares | B43: 1 | C43: =TEXT(VALUE(LEFT(C42,4))+1,"0000")&"_2026" -> 0038_2026 | D43: 1/1 | E43: =IF($O43="","",IFERROR("Parte policial Nro. "&SUBSTITUTE(INDEX(VEHICULOS!$N:$N,MATCH($O43,VEHICULOS!$F:$F,0)),"´","")&", Hoja de Ingreso y Salida Nro. "&TEXT(INDEX(VEHICULOS!$E:$E,MATCH($O43,VEHICULOS!$F:$F,0)),"0000000")&", entregado al señor "&INDEX(VEHICULOS!$P:$P,MATCH($O43,VEHICULOS!$F:$F,0))&", con cédula "&INDEX(VEHICULOS!$Z:$Z,MATCH($O43,VEHICULOS!$F:$F,0))&" del Vehiculo Tipo "&INDEX(VEHICULOS!$H:$H,MATCH($O43,VEHICULOS!$F:$F,0))&" marca "&INDEX(VEHICULOS!$G:$G,MATCH($O43,VEHICULOS!$F:$F,0))&", color "&INDEX(VEHICULOS!$J:$J,MATCH($O43,VEHICULOS!$F:$F,0))&" con placas "&$O43&", por "&INDEX(VEHICULOS!$Q:$Q,MATCH($O43,VEHICULOS!$F:$F,0))&".","REVISAR: placa no encontrada en VEHICULOS")) -> Parte policial Nro. 2026050611324782113, Hoja de Ingreso y Salida Nro. 0002072, entregado al señor CAMACHO CAMACHO RENE WILFRIDO , con cédula 1707682702 del Vehiculo Tipo CAMIÓN marca HINO, color AMARILLO con placas KAA1690, por ACCIDENTE DE TRANSITO. | F43: =IF($O43="","",IFERROR(INDEX(VEHICULOS!$D:$D,MATCH($O43,VEHICULOS!$F:$F,0)),"")) -> 46148 | G43: =IF($O43="","",IFERROR(INDEX(VEHICULOS!$V:$V,MATCH($O43,VEHICULOS!$F:$F,0)),"")) -> 46162 | H43: 20 | I43: Eliminación | J43: Fisico | O43: KAA1690
A44: Retenciones Vehiculares | B44: 1 | C44: =TEXT(VALUE(LEFT(C43,4))+1,"0000")&"_2026" -> 0039_2026 | D44: 1/1 | E44: =IF($O44="","",IFERROR("Parte policial Nro. "&SUBSTITUTE(INDEX(VEHICULOS!$N:$N,MATCH($O44,VEHICULOS!$F:$F,0)),"´","")&", Hoja de Ingreso y Salida Nro. "&TEXT(INDEX(VEHICULOS!$E:$E,MATCH($O44,VEHICULOS!$F:$F,0)),"0000000")&", entregado al señor "&INDEX(VEHICULOS!$P:$P,MATCH($O44,VEHICULOS!$F:$F,0))&", con cédula "&INDEX(VEHICULOS!$Z:$Z,MATCH($O44,VEHICULOS!$F:$F,0))&" del Vehiculo Tipo "&INDEX(VEHICULOS!$H:$H,MATCH($O44,VEHICULOS!$F:$F,0))&" marca "&INDEX(VEHICULOS!$G:$G,MATCH($O44,VEHICULOS!$F:$F,0))&", color "&INDEX(VEHICULOS!$J:$J,MATCH($O44,VEHICULOS!$F:$F,0))&" con placas "&$O44&", por "&INDEX(VEHICULOS!$Q:$Q,MATCH($O44,VEHICULOS!$F:$F,0))&".","REVISAR: placa no encontrada en VEHICULOS")) -> Parte policial Nro. 2026050907541948413, Hoja de Ingreso y Salida Nro. 0002073, entregado al señor COQUE TONATO JUAN, con cédula 0500720537 del Vehiculo Tipo BUS marca HINO, color ROJO con placas JAA1756, por ACCIDENTE DE TRANSITO. | F44: =IF($O44="","",IFERROR(INDEX(VEHICULOS!$D:$D,MATCH($O44,VEHICULOS!$F:$F,0)),"")) -> 46150 | G44: =IF($O44="","",IFERROR(INDEX(VEHICULOS!$V:$V,MATCH($O44,VEHICULOS!$F:$F,0)),"")) -> 46157 | H44: 15 | I44: Eliminación | J44: Fisico | O44: JAA1756
A45: Retenciones Vehiculares | B45: 1 | C45: =TEXT(VALUE(LEFT(C44,4))+1,"0000")&"_2026" -> 0040_2026 | D45: 1/1 | E45: =IF($O45="","",IFERROR("Parte policial Nro. "&SUBSTITUTE(INDEX(VEHICULOS!$N:$N,MATCH($O45,VEHICULOS!$F:$F,0)),"´","")&", Hoja de Ingreso y Salida Nro. "&TEXT(INDEX(VEHICULOS!$E:$E,MATCH($O45,VEHICULOS!$F:$F,0)),"0000000")&", entregado al señor "&INDEX(VEHICULOS!$P:$P,MATCH($O45,VEHICULOS!$F:$F,0))&", con cédula "&INDEX(VEHICULOS!$Z:$Z,MATCH($O45,VEHICULOS!$F:$F,0))&" del Vehiculo Tipo "&INDEX(VEHICULOS!$H:$H,MATCH($O45,VEHICULOS!$F:$F,0))&" marca "&INDEX(VEHICULOS!$G:$G,MATCH($O45,VEHICULOS!$F:$F,0))&", color "&INDEX(VEHICULOS!$J:$J,MATCH($O45,VEHICULOS!$F:$F,0))&" con placas "&$O45&", por "&INDEX(VEHICULOS!$Q:$Q,MATCH($O45,VEHICULOS!$F:$F,0))&".","REVISAR: placa no encontrada en VEHICULOS")) -> Parte policial Nro. 20260512095053535006, Hoja de Ingreso y Salida Nro. 0002074, entregado al señor MEDRANO JARRIN FERNANDO, con cédula 1719633438 del Vehiculo Tipo TRACTO CAMIÓN marca FREIGHTLINER, color BLANCO con placas PUK0033, por ACCIDENTE DE TRANSITO. | F45: =IF($O45="","",IFERROR(INDEX(VEHICULOS!$D:$D,MATCH($O45,VEHICULOS!$F:$F,0)),"")) -> 46154 | G45: =IF($O45="","",IFERROR(INDEX(VEHICULOS!$V:$V,MATCH($O45,VEHICULOS!$F:$F,0)),"")) -> 46182 | H45: 30 | I45: Eliminación | J45: Fisico | O45: PUK0033
A46: Retenciones Vehiculares | B46: 1 | C46: =TEXT(VALUE(LEFT(C45,4))+1,"0000")&"_2026" -> 0041_2026 | D46: 1/1 | E46: =IF($O46="","",IFERROR("Parte policial Nro. "&SUBSTITUTE(INDEX(VEHICULOS!$N:$N,MATCH($O46,VEHICULOS!$F:$F,0)),"´","")&", Hoja de Ingreso y Salida Nro. "&TEXT(INDEX(VEHICULOS!$E:$E,MATCH($O46,VEHICULOS!$F:$F,0)),"0000000")&", entregado al señor "&INDEX(VEHICULOS!$P:$P,MATCH($O46,VEHICULOS!$F:$F,0))&", con cédula "&INDEX(VEHICULOS!$Z:$Z,MATCH($O46,VEHICULOS!$F:$F,0))&" del Vehiculo Tipo "&INDEX(VEHICULOS!$H:$H,MATCH($O46,VEHICULOS!$F:$F,0))&" marca "&INDEX(VEHICULOS!$G:$G,MATCH($O46,VEHICULOS!$F:$F,0))&", color "&INDEX(VEHICULOS!$J:$J,MATCH($O46,VEHICULOS!$F:$F,0))&" con placas "&$O46&", por "&INDEX(VEHICULOS!$Q:$Q,MATCH($O46,VEHICULOS!$F:$F,0))&".","REVISAR: placa no encontrada en VEHICULOS")) -> Parte policial Nro. 20260512095053535006, Hoja de Ingreso y Salida Nro. 0002075, entregado al señor MEDRANO JARRIN FERNANDO, con cédula 1307161321 del Vehiculo Tipo CAMIÓN marca HINO, color BLANCO con placas MBE7165, por ACCIDENTE DE TRANSITO. | F46: =IF($O46="","",IFERROR(INDEX(VEHICULOS!$D:$D,MATCH($O46,VEHICULOS!$F:$F,0)),"")) -> 46154 | G46: =IF($O46="","",IFERROR(INDEX(VEHICULOS!$V:$V,MATCH($O46,VEHICULOS!$F:$F,0)),"")) -> 46168 | H46: 31 | I46: Eliminación | J46: Fisico | O46: MBE7165
A47: Retenciones Vehiculares | B47: 1 | C47: =TEXT(VALUE(LEFT(C46,4))+1,"0000")&"_2026" -> 0042_2026 | D47: 1/1 | E47: =IF($O47="","",IFERROR("Parte policial Nro. "&SUBSTITUTE(INDEX(VEHICULOS!$N:$N,MATCH($O47,VEHICULOS!$F:$F,0)),"´","")&", Hoja de Ingreso y Salida Nro. "&TEXT(INDEX(VEHICULOS!$E:$E,MATCH($O47,VEHICULOS!$F:$F,0)),"0000000")&", entregado al señor "&INDEX(VEHICULOS!$P:$P,MATCH($O47,VEHICULOS!$F:$F,0))&", con cédula "&INDEX(VEHICULOS!$Z:$Z,MATCH($O47,VEHICULOS!$F:$F,0))&" del Vehiculo Tipo "&INDEX(VEHICULOS!$H:$H,MATCH($O47,VEHICULOS!$F:$F,0))&" marca "&INDEX(VEHICULOS!$G:$G,MATCH($O47,VEHICULOS!$F:$F,0))&", color "&INDEX(VEHICULOS!$J:$J,MATCH($O47,VEHICULOS!$F:$F,0))&" con placas "&$O47&", por "&INDEX(VEHICULOS!$Q:$Q,MATCH($O47,VEHICULOS!$F:$F,0))&".","REVISAR: placa no encontrada en VEHICULOS")) -> Parte policial Nro. 2026052210240013908, Hoja de Ingreso y Salida Nro. 0002076, entregado al señor ALARCON GUERRERO HUGO LANDIVER, con cédula 1250443957 del Vehiculo Tipo FURGON marca SINOTRUK, color BLANCO con placas PAD2382, por ART. 386 INCISO 2.1. | F47: =IF($O47="","",IFERROR(INDEX(VEHICULOS!$D:$D,MATCH($O47,VEHICULOS!$F:$F,0)),"")) -> 46164 | G47: =IF($O47="","",IFERROR(INDEX(VEHICULOS!$V:$V,MATCH($O47,VEHICULOS!$F:$F,0)),"")) -> 46184 | H47: 24 | I47: Eliminación | J47: Fisico | O47: PAD2382
... A51: Retenciones Vehiculares | B51: 1 | C51: =TEXT(VALUE(LEFT(C50,4))+1,"0000")&"_2026" -> 0046_2026 | D51: 1/1 | E51: =IF($O51="","",IFERROR("Parte policial Nro. "&SUBSTITUTE(INDEX(VEHICULOS!$N:$N,MATCH($O51,VEHICULOS!$F:$F,0)),"´","")&", Hoja de Ingreso y Salida Nro. "&TEXT(INDEX(VEHICULOS!$E:$E,MATCH($O51,VEHICULOS!$F:$F,0)),"0000000")&", entregado al señor "&INDEX(VEHICULOS!$P:$P,MATCH($O51,VEHICULOS!$F:$F,0))&", con cédula "&INDEX(VEHICULOS!$Z:$Z,MATCH($O51,VEHICULOS!$F:$F,0))&" del Vehiculo Tipo "&INDEX(VEHICULOS!$H:$H,MATCH($O51,VEHICULOS!$F:$F,0))&" marca "&INDEX(VEHICULOS!$G:$G,MATCH($O51,VEHICULOS!$F:$F,0))&", color "&INDEX(VEHICULOS!$J:$J,MATCH($O51,VEHICULOS!$F:$F,0))&" con placas "&$O51&", por "&INDEX(VEHICULOS!$Q:$Q,MATCH($O51,VEHICULOS!$F:$F,0))&".","REVISAR: placa no encontrada en VEHICULOS")) -> Parte policial Nro. 202606270306365907, Hoja de Ingreso y Salida Nro. 0002084, entregado al señor JOSE MARIO ZAMBRANO MENDOZA, con cédula 1715321350 del Vehiculo Tipo CAMIÓN marca HINO, color BLANCO con placas JBE1438, por ART. 160. | F51: =IF($O51="","",IFERROR(INDEX(VEHICULOS!$D:$D,MATCH($O51,VEHICULOS!$F:$F,0)),"")) -> 46200 | G51: =IF($O51="","",IFERROR(INDEX(VEHICULOS!$V:$V,MATCH($O51,VEHICULOS!$F:$F,0)),"")) -> 46202 | H51: 14 | I51: Eliminación | J51: Fisico | O51: JBE1438
A52: Retenciones Vehiculares | B52: 1 | C52: =TEXT(VALUE(LEFT(C51,4))+1,"0000")&"_2026" -> 0047_2026 | D52: 1/1 | E52: =IF($O52="","",IFERROR("Parte policial Nro. "&SUBSTITUTE(INDEX(VEHICULOS!$N:$N,MATCH($O52,VEHICULOS!$F:$F,0)),"´","")&", Hoja de Ingreso y Salida Nro. "&TEXT(INDEX(VEHICULOS!$E:$E,MATCH($O52,VEHICULOS!$F:$F,0)),"0000000")&", entregado al señor "&INDEX(VEHICULOS!$P:$P,MATCH($O52,VEHICULOS!$F:$F,0))&", con cédula "&INDEX(VEHICULOS!$Z:$Z,MATCH($O52,VEHICULOS!$F:$F,0))&" del Vehiculo Tipo "&INDEX(VEHICULOS!$H:$H,MATCH($O52,VEHICULOS!$F:$F,0))&" marca "&INDEX(VEHICULOS!$G:$G,MATCH($O52,VEHICULOS!$F:$F,0))&", color "&INDEX(VEHICULOS!$J:$J,MATCH($O52,VEHICULOS!$F:$F,0))&" con placas "&$O52&", por "&INDEX(VEHICULOS!$Q:$Q,MATCH($O52,VEHICULOS!$F:$F,0))&".","REVISAR: placa no encontrada en VEHICULOS")) -> Parte policial Nro. 2026062608132225302, Hoja de Ingreso y Salida Nro. 0002083, entregado al señor CEDEÑO YANEZ HUGO FABIAN, con cédula 1309276648 del Vehiculo Tipo BUS marca HINO, color AZUL con placas XAG0291, por ACCIDENTE DE TRANSITO. | F52: =IF($O52="","",IFERROR(INDEX(VEHICULOS!$D:$D,MATCH($O52,VEHICULOS!$F:$F,0)),"")) -> 46199 | G52: =IF($O52="","",IFERROR(INDEX(VEHICULOS!$V:$V,MATCH($O52,VEHICULOS!$F:$F,0)),"")) -> 46210 | I52: Eliminación | J52: Fisico | O52: XAG0291
A53: Retenciones Vehiculares | B53: 1 | C53: =TEXT(VALUE(LEFT(C52,4))+1,"0000")&"_2026" -> 0048_2026 | D53: 1/1 | E53: =IF($O53="","",IFERROR("Parte policial Nro. "&SUBSTITUTE(INDEX(VEHICULOS!$N:$N,MATCH($O53,VEHICULOS!$F:$F,0)),"´","")&", Hoja de Ingreso y Salida Nro. "&TEXT(INDEX(VEHICULOS!$E:$E,MATCH($O53,VEHICULOS!$F:$F,0)),"0000000")&", entregado al señor "&INDEX(VEHICULOS!$P:$P,MATCH($O53,VEHICULOS!$F:$F,0))&", con cédula "&INDEX(VEHICULOS!$Z:$Z,MATCH($O53,VEHICULOS!$F:$F,0))&" del Vehiculo Tipo "&INDEX(VEHICULOS!$H:$H,MATCH($O53,VEHICULOS!$F:$F,0))&" marca "&INDEX(VEHICULOS!$G:$G,MATCH($O53,VEHICULOS!$F:$F,0))&", color "&INDEX(VEHICULOS!$J:$J,MATCH($O53,VEHICULOS!$F:$F,0))&" con placas "&$O53&", por "&INDEX(VEHICULOS!$Q:$Q,MATCH($O53,VEHICULOS!$F:$F,0))&".","REVISAR: placa no encontrada en VEHICULOS")) -> Parte policial Nro. 2026063001540128411, Hoja de Ingreso y Salida Nro. 0002086, entregado al señor ARMIJOS GODOY JAHANNA NOEMI, con cédula 0703663534 del Vehiculo Tipo CAMIÓN marca SINOTRUK, color BLANCO con placas KAA2251, por ART. 160. | F53: =IF($O53="","",IFERROR(INDEX(VEHICULOS!$D:$D,MATCH($O53,VEHICULOS!$F:$F,0)),"")) -> 46203 | G53: =IF($O53="","",IFERROR(INDEX(VEHICULOS!$V:$V,MATCH($O53,VEHICULOS!$F:$F,0)),"")) -> 46211 | I53: Eliminación | J53: Fisico | O53: KAA2251
A54: Retenciones Vehiculares | B54: 1 | C54: =TEXT(VALUE(LEFT(C53,4))+1,"0000")&"_2026" -> 0049_2026 | D54: 1/1 | E54: =IF($O54="","",IFERROR("Parte policial Nro. "&SUBSTITUTE(INDEX(VEHICULOS!$N:$N,MATCH($O54,VEHICULOS!$F:$F,0)),"´","")&", Hoja de Ingreso y Salida Nro. "&TEXT(INDEX(VEHICULOS!$E:$E,MATCH($O54,VEHICULOS!$F:$F,0)),"0000000")&", entregado al señor "&INDEX(VEHICULOS!$P:$P,MATCH($O54,VEHICULOS!$F:$F,0))&", con cédula "&INDEX(VEHICULOS!$Z:$Z,MATCH($O54,VEHICULOS!$F:$F,0))&" del Vehiculo Tipo "&INDEX(VEHICULOS!$H:$H,MATCH($O54,VEHICULOS!$F:$F,0))&" marca "&INDEX(VEHICULOS!$G:$G,MATCH($O54,VEHICULOS!$F:$F,0))&", color "&INDEX(VEHICULOS!$J:$J,MATCH($O54,VEHICULOS!$F:$F,0))&" con placas "&$O54&", por "&INDEX(VEHICULOS!$Q:$Q,MATCH($O54,VEHICULOS!$F:$F,0))&".","REVISAR: placa no encontrada en VEHICULOS")) -> Parte policial Nro. 2026070610334185509, Hoja de Ingreso y Salida Nro. 0002087, entregado al señor GUERRA NARVAEZ YOLANDA ROSARIO, con cédula 0401069794 del Vehiculo Tipo TRACTO CAMIÓN marca KENWORTH, color AZUL con placas AAA2132, por ACCIDENTE DE TRANSITO. | F54: =IF($O54="","",IFERROR(INDEX(VEHICULOS!$D:$D,MATCH($O54,VEHICULOS!$F:$F,0)),"")) -> 46209 | G54: =IF($O54="","",IFERROR(INDEX(VEHICULOS!$V:$V,MATCH($O54,VEHICULOS!$F:$F,0)),"")) -> 46215 | I54: Eliminación | J54: Fisico | O54: AAA2132
A55: Retenciones Vehiculares | B55: 1 | C55: =TEXT(VALUE(LEFT(C54,4))+1,"0000")&"_2026" -> 0050_2026 | D55: 1/1 | E55: =IF($O55="","",IFERROR("Parte policial Nro. "&SUBSTITUTE(INDEX(VEHICULOS!$N:$N,MATCH($O55,VEHICULOS!$F:$F,0)),"´","")&", Hoja de Ingreso y Salida Nro. "&TEXT(INDEX(VEHICULOS!$E:$E,MATCH($O55,VEHICULOS!$F:$F,0)),"0000000")&", entregado al señor "&INDEX(VEHICULOS!$P:$P,MATCH($O55,VEHICULOS!$F:$F,0))&", con cédula "&INDEX(VEHICULOS!$Z:$Z,MATCH($O55,VEHICULOS!$F:$F,0))&" del Vehiculo Tipo "&INDEX(VEHICULOS!$H:$H,MATCH($O55,VEHICULOS!$F:$F,0))&" marca "&INDEX(VEHICULOS!$G:$G,MATCH($O55,VEHICULOS!$F:$F,0))&", color "&INDEX(VEHICULOS!$J:$J,MATCH($O55,VEHICULOS!$F:$F,0))&" con placas "&$O55&", por "&INDEX(VEHICULOS!$Q:$Q,MATCH($O55,VEHICULOS!$F:$F,0))&".","REVISAR: placa no encontrada en VEHICULOS")) -> Parte policial Nro. 2026070910554584516, Hoja de Ingreso y Salida Nro. 0002088, entregado al señor CABSCANGO CHAVEZ LUIS GERMAN, con cédula 1002879417 del Vehiculo Tipo CAMIÓN marca HINO, color BLANCO con placas PQQ0425, por ART. 160. | F55: =IF($O55="","",IFERROR(INDEX(VEHICULOS!$D:$D,MATCH($O55,VEHICULOS!$F:$F,0)),"")) -> 46212 | G55: =IF($O55="","",IFERROR(INDEX(VEHICULOS!$V:$V,MATCH($O55,VEHICULOS!$F:$F,0)),"")) -> 46223 | I55: Eliminación | J55: Fisico | O55: PQQ0425
A56: Retenciones Vehiculares | B56: 1 | C56: =TEXT(VALUE(LEFT(C55,4))+1,"0000")&"_2026" -> 0051_2026 | D56: 1/1 | E56: =IF($O56="","",IFERROR("Parte policial Nro. "&SUBSTITUTE(INDEX(VEHICULOS!$N:$N,MATCH($O56,VEHICULOS!$F:$F,0)),"´","")&", Hoja de Ingreso y Salida Nro. "&TEXT(INDEX(VEHICULOS!$E:$E,MATCH($O56,VEHICULOS!$F:$F,0)),"0000000")&", entregado al señor "&INDEX(VEHICULOS!$P:$P,MATCH($O56,VEHICULOS!$F:$F,0))&", con cédula "&INDEX(VEHICULOS!$Z:$Z,MATCH($O56,VEHICULOS!$F:$F,0))&" del Vehiculo Tipo "&INDEX(VEHICULOS!$H:$H,MATCH($O56,VEHICULOS!$F:$F,0))&" marca "&INDEX(VEHICULOS!$G:$G,MATCH($O56,VEHICULOS!$F:$F,0))&", color "&INDEX(VEHICULOS!$J:$J,MATCH($O56,VEHICULOS!$F:$F,0))&" con placas "&$O56&", por "&INDEX(VEHICULOS!$Q:$Q,MATCH($O56,VEHICULOS!$F:$F,0))&".","REVISAR: placa no encontrada en VEHICULOS")) -> Parte policial Nro. 2026070901480898413, Hoja de Ingreso y Salida Nro. 0002089, entregado al señor SIGMAEC CIA. LTDA., con cédula 1719633438 del Vehiculo Tipo FURGON marca CHEVROLET, color BLANCO con placas PDX5967, por ACCIDENTE DE TRANSITO. | F56: =IF($O56="","",IFERROR(INDEX(VEHICULOS!$D:$D,MATCH($O56,VEHICULOS!$F:$F,0)),"")) -> 46212 | G56: =IF($O56="","",IFERROR(INDEX(VEHICULOS!$V:$V,MATCH($O56,VEHICULOS!$F:$F,0)),"")) -> 46231 | I56: Eliminación | J56: Fisico | O56: PDX5967
A57: Retenciones Vehiculares | B57: 1 | C57: =TEXT(VALUE(LEFT(C56,4))+1,"0000")&"_2026" -> 0052_2026 | D57: 1/1 | E57: =IF($O57="","",IFERROR("Parte policial Nro. "&SUBSTITUTE(INDEX(VEHICULOS!$N:$N,MATCH($O57,VEHICULOS!$F:$F,0)),"´","")&", Hoja de Ingreso y Salida Nro. "&TEXT(INDEX(VEHICULOS!$E:$E,MATCH($O57,VEHICULOS!$F:$F,0)),"0000000")&", entregado al señor "&INDEX(VEHICULOS!$P:$P,MATCH($O57,VEHICULOS!$F:$F,0))&", con cédula "&INDEX(VEHICULOS!$Z:$Z,MATCH($O57,VEHICULOS!$F:$F,0))&" del Vehiculo Tipo "&INDEX(VEHICULOS!$H:$H,MATCH($O57,VEHICULOS!$F:$F,0))&" marca "&INDEX(VEHICULOS!$G:$G,MATCH($O57,VEHICULOS!$F:$F,0))&", color "&INDEX(VEHICULOS!$J:$J,MATCH($O57,VEHICULOS!$F:$F,0))&" con placas "&$O57&", por "&INDEX(VEHICULOS!$Q:$Q,MATCH($O57,VEHICULOS!$F:$F,0))&".","REVISAR: placa no encontrada en VEHICULOS")) -> Parte policial Nro. 2026071409104162713, Hoja de Ingreso y Salida Nro. 0002090, entregado al señor ROMERO ABARCA DENNISE ESTEFANIA, con cédula 1714988795 del Vehiculo Tipo BUS marca HINO, color AZUL con placas XAA4034, por ACCIDENTE DE TRANSITO. | F57: =IF($O57="","",IFERROR(INDEX(VEHICULOS!$D:$D,MATCH($O57,VEHICULOS!$F:$F,0)),"")) -> 46217 | G57: =IF($O57="","",IFERROR(INDEX(VEHICULOS!$V:$V,MATCH($O57,VEHICULOS!$F:$F,0)),"")) -> 46218 | I57: Eliminación | J57: Fisico | O57: XAA4034
A58: Retenciones Vehiculares | B58: 1 | C58: =TEXT(VALUE(LEFT(C57,4))+1,"0000")&"_2026" -> 0053_2026 | D58: 1/1 | E58: =IF($O58="","",IFERROR("Parte policial Nro. "&SUBSTITUTE(INDEX(VEHICULOS!$N:$N,MATCH($O58,VEHICULOS!$F:$F,0)),"´","")&", Hoja de Ingreso y Salida Nro. "&TEXT(INDEX(VEHICULOS!$E:$E,MATCH($O58,VEHICULOS!$F:$F,0)),"0000000")&", entregado al señor "&INDEX(VEHICULOS!$P:$P,MATCH($O58,VEHICULOS!$F:$F,0))&", con cédula "&INDEX(VEHICULOS!$Z:$Z,MATCH($O58,VEHICULOS!$F:$F,0))&" del Vehiculo Tipo "&INDEX(VEHICULOS!$H:$H,MATCH($O58,VEHICULOS!$F:$F,0))&" marca "&INDEX(VEHICULOS!$G:$G,MATCH($O58,VEHICULOS!$F:$F,0))&", color "&INDEX(VEHICULOS!$J:$J,MATCH($O58,VEHICULOS!$F:$F,0))&" con placas "&$O58&", por "&INDEX(VEHICULOS!$Q:$Q,MATCH($O58,VEHICULOS!$F:$F,0))&".","REVISAR: placa no encontrada en VEHICULOS")) -> Parte policial Nro. 2026071703415419318, Hoja de Ingreso y Salida Nro. 0002091, entregado al señor GUACHICULLCA ARIAS LUIS, con cédula 1723801773 del Vehiculo Tipo FURGON marca HYUNDAI, color BLANCO con placas PPC3401, por ART. 386 INCISO 2 #2. | F58: =IF($O58="","",IFERROR(INDEX(VEHICULOS!$D:$D,MATCH($O58,VEHICULOS!$F:$F,0)),"")) -> 46220 | G58: =IF($O58="","",IFERROR(INDEX(VEHICULOS!$V:$V,MATCH($O58,VEHICULOS!$F:$F,0)),"")) -> 46239 | I58: Eliminación | J58: Fisico | O58: PPC3401
A59: Retenciones Vehiculares | B59: 1 | C59: =TEXT(VALUE(LEFT(C58,4))+1,"0000")&"_2026" -> 0054_2026 | D59: 1/1 | E59: =IF($O59="","",IFERROR("Parte policial Nro. "&SUBSTITUTE(INDEX(VEHICULOS!$N:$N,MATCH($O59,VEHICULOS!$F:$F,0)),"´","")&", Hoja de Ingreso y Salida Nro. "&TEXT(INDEX(VEHICULOS!$E:$E,MATCH($O59,VEHICULOS!$F:$F,0)),"0000000")&", entregado al señor "&INDEX(VEHICULOS!$P:$P,MATCH($O59,VEHICULOS!$F:$F,0))&", con cédula "&INDEX(VEHICULOS!$Z:$Z,MATCH($O59,VEHICULOS!$F:$F,0))&" del Vehiculo Tipo "&INDEX(VEHICULOS!$H:$H,MATCH($O59,VEHICULOS!$F:$F,0))&" marca "&INDEX(VEHICULOS!$G:$G,MATCH($O59,VEHICULOS!$F:$F,0))&", color "&INDEX(VEHICULOS!$J:$J,MATCH($O59,VEHICULOS!$F:$F,0))&" con placas "&$O59&", por "&INDEX(VEHICULOS!$Q:$Q,MATCH($O59,VEHICULOS!$F:$F,0))&".","REVISAR: placa no encontrada en VEHICULOS")) -> Parte policial Nro. 2026061809194716316, Hoja de Ingreso y Salida Nro. 0002081, entregado al señor EXTRACTORA AGRICOLA RIO MANSO EXA S.A. , con cédula 1307482693 del Vehiculo Tipo VOLQUETA marca INTERNACIONAL, color BLANCO con placas PTL0970, por ACCIDENTE DE TRANSITO. | F59: =IF($O59="","",IFERROR(INDEX(VEHICULOS!$D:$D,MATCH($O59,VEHICULOS!$F:$F,0)),"")) -> 46191 | G59: =IF($O59="","",IFERROR(INDEX(VEHICULOS!$V:$V,MATCH($O59,VEHICULOS!$F:$F,0)),"")) -> 46235 | I59: Eliminación | J59: Fisico | O59: PTL0970
A60: Retenciones Vehiculares | B60: 1 | C60: =TEXT(VALUE(LEFT(C59,4))+1,"0000")&"_2026" -> 0055_2026 | D60: 1/1 | E60: =IF($O60="","",IFERROR("Parte policial Nro. "&SUBSTITUTE(INDEX(VEHICULOS!$N:$N,MATCH($O60,VEHICULOS!$F:$F,0)),"´","")&", Hoja de Ingreso y Salida Nro. "&TEXT(INDEX(VEHICULOS!$E:$E,MATCH($O60,VEHICULOS!$F:$F,0)),"0000000")&", entregado al señor "&INDEX(VEHICULOS!$P:$P,MATCH($O60,VEHICULOS!$F:$F,0))&", con cédula "&INDEX(VEHICULOS!$Z:$Z,MATCH($O60,VEHICULOS!$F:$F,0))&" del Vehiculo Tipo "&INDEX(VEHICULOS!$H:$H,MATCH($O60,VEHICULOS!$F:$F,0))&" marca "&INDEX(VEHICULOS!$G:$G,MATCH($O60,VEHICULOS!$F:$F,0))&", color "&INDEX(VEHICULOS!$J:$J,MATCH($O60,VEHICULOS!$F:$F,0))&" con placas "&$O60&", por "&INDEX(VEHICULOS!$Q:$Q,MATCH($O60,VEHICULOS!$F:$F,0))&".","REVISAR: placa no encontrada en VEHICULOS")) -> Parte policial Nro. 2026062708383249212, Hoja de Ingreso y Salida Nro. 0002085, entregado al señor MENDOZA RENDON ORLANDO ALEJANDRO, con cédula 0502246978 del Vehiculo Tipo AUTOBUS marca HINO, color AZUL con placas IAI3101, por ART. 389 NUMERAL 7. | F60: =IF($O60="","",IFERROR(INDEX(VEHICULOS!$D:$D,MATCH($O60,VEHICULOS!$F:$F,0)),"")) -> 46200 | G60: =IF($O60="","",IFERROR(INDEX(VEHICULOS!$V:$V,MATCH($O60,VEHICULOS!$F:$F,0)),"")) -> 46218 | I60: Eliminación | J60: Fisico | O60: IAI3101
A61: Retenciones Vehiculares | B61: 1 | C61: =TEXT(VALUE(LEFT(C60,4))+1,"0000")&"_2026" -> 0056_2026 | D61: 1/1 | E61: =IF($O61="","",IFERROR("Parte policial Nro. "&SUBSTITUTE(INDEX(VEHICULOS!$N:$N,MATCH($O61,VEHICULOS!$F:$F,0)),"´","")&", Hoja de Ingreso y Salida Nro. "&TEXT(INDEX(VEHICULOS!$E:$E,MATCH($O61,VEHICULOS!$F:$F,0)),"0000000")&", entregado al señor "&INDEX(VEHICULOS!$P:$P,MATCH($O61,VEHICULOS!$F:$F,0))&", con cédula "&INDEX(VEHICULOS!$Z:$Z,MATCH($O61,VEHICULOS!$F:$F,0))&" del Vehiculo Tipo "&INDEX(VEHICULOS!$H:$H,MATCH($O61,VEHICULOS!$F:$F,0))&" marca "&INDEX(VEHICULOS!$G:$G,MATCH($O61,VEHICULOS!$F:$F,0))&", color "&INDEX(VEHICULOS!$J:$J,MATCH($O61,VEHICULOS!$F:$F,0))&" con placas "&$O61&", por "&INDEX(VEHICULOS!$Q:$Q,MATCH($O61,VEHICULOS!$F:$F,0))&".","REVISAR: placa no encontrada en VEHICULOS")) | F61: =IF($O61="","",IFERROR(INDEX(VEHICULOS!$D:$D,MATCH($O61,VEHICULOS!$F:$F,0)),"")) | G61: =IF($O61="","",IFERROR(INDEX(VEHICULOS!$V:$V,MATCH($O61,VEHICULOS!$F:$F,0)),"")) | I61: Eliminación | J61: Fisico
A62: Retenciones Vehiculares | B62: 1 | C62: =TEXT(VALUE(LEFT(C61,4))+1,"0000")&"_2026" -> 0057_2026 | D62: 1/1 | E62: =IF($O62="","",IFERROR("Parte policial Nro. "&SUBSTITUTE(INDEX(VEHICULOS!$N:$N,MATCH($O62,VEHICULOS!$F:$F,0)),"´","")&", Hoja de Ingreso y Salida Nro. "&TEXT(INDEX(VEHICULOS!$E:$E,MATCH($O62,VEHICULOS!$F:$F,0)),"0000000")&", entregado al señor "&INDEX(VEHICULOS!$P:$P,MATCH($O62,VEHICULOS!$F:$F,0))&", con cédula "&INDEX(VEHICULOS!$Z:$Z,MATCH($O62,VEHICULOS!$F:$F,0))&" del Vehiculo Tipo "&INDEX(VEHICULOS!$H:$H,MATCH($O62,VEHICULOS!$F:$F,0))&" marca "&INDEX(VEHICULOS!$G:$G,MATCH($O62,VEHICULOS!$F:$F,0))&", color "&INDEX(VEHICULOS!$J:$J,MATCH($O62,VEHICULOS!$F:$F,0))&" con placas "&$O62&", por "&INDEX(VEHICULOS!$Q:$Q,MATCH($O62,VEHICULOS!$F:$F,0))&".","REVISAR: placa no encontrada en VEHICULOS")) | F62: =IF($O62="","",IFERROR(INDEX(VEHICULOS!$D:$D,MATCH($O62,VEHICULOS!$F:$F,0)),"")) | G62: =IF($O62="","",IFERROR(INDEX(VEHICULOS!$V:$V,MATCH($O62,VEHICULOS!$F:$F,0)),"")) | I62: Eliminación | J62: Fisico
A63: Retenciones Vehiculares | B63: 1 | C63: =TEXT(VALUE(LEFT(C62,4))+1,"0000")&"_2026" -> 0058_2026 | D63: 1/1 | E63: =IF($O63="","",IFERROR("Parte policial Nro. "&SUBSTITUTE(INDEX(VEHICULOS!$N:$N,MATCH($O63,VEHICULOS!$F:$F,0)),"´","")&", Hoja de Ingreso y Salida Nro. "&TEXT(INDEX(VEHICULOS!$E:$E,MATCH($O63,VEHICULOS!$F:$F,0)),"0000000")&", entregado al señor "&INDEX(VEHICULOS!$P:$P,MATCH($O63,VEHICULOS!$F:$F,0))&", con cédula "&INDEX(VEHICULOS!$Z:$Z,MATCH($O63,VEHICULOS!$F:$F,0))&" del Vehiculo Tipo "&INDEX(VEHICULOS!$H:$H,MATCH($O63,VEHICULOS!$F:$F,0))&" marca "&INDEX(VEHICULOS!$G:$G,MATCH($O63,VEHICULOS!$F:$F,0))&", color "&INDEX(VEHICULOS!$J:$J,MATCH($O63,VEHICULOS!$F:$F,0))&" con placas "&$O63&", por "&INDEX(VEHICULOS!$Q:$Q,MATCH($O63,VEHICULOS!$F:$F,0))&".","REVISAR: placa no encontrada en VEHICULOS")) | F63: =IF($O63="","",IFERROR(INDEX(VEHICULOS!$D:$D,MATCH($O63,VEHICULOS!$F:$F,0)),"")) | G63: =IF($O63="","",IFERROR(INDEX(VEHICULOS!$V:$V,MATCH($O63,VEHICULOS!$F:$F,0)),"")) | I63: Eliminación | J63: Fisico
A64: Retenciones Vehiculares | B64: 1 | C64: =TEXT(VALUE(LEFT(C63,4))+1,"0000")&"_2026" -> 0059_2026 | D64: 1/1 | E64: =IF($O64="","",IFERROR("Parte policial Nro. "&SUBSTITUTE(INDEX(VEHICULOS!$N:$N,MATCH($O64,VEHICULOS!$F:$F,0)),"´","")&", Hoja de Ingreso y Salida Nro. "&TEXT(INDEX(VEHICULOS!$E:$E,MATCH($O64,VEHICULOS!$F:$F,0)),"0000000")&", entregado al señor "&INDEX(VEHICULOS!$P:$P,MATCH($O64,VEHICULOS!$F:$F,0))&", con cédula "&INDEX(VEHICULOS!$Z:$Z,MATCH($O64,VEHICULOS!$F:$F,0))&" del Vehiculo Tipo "&INDEX(VEHICULOS!$H:$H,MATCH($O64,VEHICULOS!$F:$F,0))&" marca "&INDEX(VEHICULOS!$G:$G,MATCH($O64,VEHICULOS!$F:$F,0))&", color "&INDEX(VEHICULOS!$J:$J,MATCH($O64,VEHICULOS!$F:$F,0))&" con placas "&$O64&", por "&INDEX(VEHICULOS!$Q:$Q,MATCH($O64,VEHICULOS!$F:$F,0))&".","REVISAR: placa no encontrada en VEHICULOS")) | F64: =IF($O64="","",IFERROR(INDEX(VEHICULOS!$D:$D,MATCH($O64,VEHICULOS!$F:$F,0)),"")) | G64: =IF($O64="","",IFERROR(INDEX(VEHICULOS!$V:$V,MATCH($O64,VEHICULOS!$F:$F,0)),"")) | I64: Eliminación | J64: Fisico
A65: Retenciones Vehiculares | B65: 1 | C65: =TEXT(VALUE(LEFT(C64,4))+1,"0000")&"_2026" -> 0060_2026 | D65: 1/1 | E65: =IF($O65="","",IFERROR("Parte policial Nro. "&SUBSTITUTE(INDEX(VEHICULOS!$N:$N,MATCH($O65,VEHICULOS!$F:$F,0)),"´","")&", Hoja de Ingreso y Salida Nro. "&TEXT(INDEX(VEHICULOS!$E:$E,MATCH($O65,VEHICULOS!$F:$F,0)),"0000000")&", entregado al señor "&INDEX(VEHICULOS!$P:$P,MATCH($O65,VEHICULOS!$F:$F,0))&", con cédula "&INDEX(VEHICULOS!$Z:$Z,MATCH($O65,VEHICULOS!$F:$F,0))&" del Vehiculo Tipo "&INDEX(VEHICULOS!$H:$H,MATCH($O65,VEHICULOS!$F:$F,0))&" marca "&INDEX(VEHICULOS!$G:$G,MATCH($O65,VEHICULOS!$F:$F,0))&", color "&INDEX(VEHICULOS!$J:$J,MATCH($O65,VEHICULOS!$F:$F,0))&" con placas "&$O65&", por "&INDEX(VEHICULOS!$Q:$Q,MATCH($O65,VEHICULOS!$F:$F,0))&".","REVISAR: placa no encontrada en VEHICULOS")) | F65: =IF($O65="","",IFERROR(INDEX(VEHICULOS!$D:$D,MATCH($O65,VEHICULOS!$F:$F,0)),"")) | G65: =IF($O65="","",IFERROR(INDEX(VEHICULOS!$V:$V,MATCH($O65,VEHICULOS!$F:$F,0)),"")) | I65: Eliminación | J65: Fisico
A66: Retenciones Vehiculares | B66: 1 | C66: =TEXT(VALUE(LEFT(C65,4))+1,"0000")&"_2026" -> 0061_2026 | D66: 1/1 | E66: =IF($O66="","",IFERROR("Parte policial Nro. "&SUBSTITUTE(INDEX(VEHICULOS!$N:$N,MATCH($O66,VEHICULOS!$F:$F,0)),"´","")&", Hoja de Ingreso y Salida Nro. "&TEXT(INDEX(VEHICULOS!$E:$E,MATCH($O66,VEHICULOS!$F:$F,0)),"0000000")&", entregado al señor "&INDEX(VEHICULOS!$P:$P,MATCH($O66,VEHICULOS!$F:$F,0))&", con cédula "&INDEX(VEHICULOS!$Z:$Z,MATCH($O66,VEHICULOS!$F:$F,0))&" del Vehiculo Tipo "&INDEX(VEHICULOS!$H:$H,MATCH($O66,VEHICULOS!$F:$F,0))&" marca "&INDEX(VEHICULOS!$G:$G,MATCH($O66,VEHICULOS!$F:$F,0))&", color "&INDEX(VEHICULOS!$J:$J,MATCH($O66,VEHICULOS!$F:$F,0))&" con placas "&$O66&", por "&INDEX(VEHICULOS!$Q:$Q,MATCH($O66,VEHICULOS!$F:$F,0))&".","REVISAR: placa no encontrada en VEHICULOS")) | F66: =IF($O66="","",IFERROR(INDEX(VEHICULOS!$D:$D,MATCH($O66,VEHICULOS!$F:$F,0)),"")) | G66: =IF($O66="","",IFERROR(INDEX(VEHICULOS!$V:$V,MATCH($O66,VEHICULOS!$F:$F,0)),"")) | I66: Eliminación | J66: Fisico
A67: Retenciones Vehiculares | B67: 1 | C67: =TEXT(VALUE(LEFT(C66,4))+1,"0000")&"_2026" -> 0062_2026 | D67: 1/1 | E67: =IF($O67="","",IFERROR("Parte policial Nro. "&SUBSTITUTE(INDEX(VEHICULOS!$N:$N,MATCH($O67,VEHICULOS!$F:$F,0)),"´","")&", Hoja de Ingreso y Salida Nro. "&TEXT(INDEX(VEHICULOS!$E:$E,MATCH($O67,VEHICULOS!$F:$F,0)),"0000000")&", entregado al señor "&INDEX(VEHICULOS!$P:$P,MATCH($O67,VEHICULOS!$F:$F,0))&", con cédula "&INDEX(VEHICULOS!$Z:$Z,MATCH($O67,VEHICULOS!$F:$F,0))&" del Vehiculo Tipo "&INDEX(VEHICULOS!$H:$H,MATCH($O67,VEHICULOS!$F:$F,0))&" marca "&INDEX(VEHICULOS!$G:$G,MATCH($O67,VEHICULOS!$F:$F,0))&", color "&INDEX(VEHICULOS!$J:$J,MATCH($O67,VEHICULOS!$F:$F,0))&" con placas "&$O67&", por "&INDEX(VEHICULOS!$Q:$Q,MATCH($O67,VEHICULOS!$F:$F,0))&".","REVISAR: placa no encontrada en VEHICULOS")) | F67: =IF($O67="","",IFERROR(INDEX(VEHICULOS!$D:$D,MATCH($O67,VEHICULOS!$F:$F,0)),"")) | G67: =IF($O67="","",IFERROR(INDEX(VEHICULOS!$V:$V,MATCH($O67,VEHICULOS!$F:$F,0)),"")) | I67: Eliminación | J67: Fisico
A68: Retenciones Vehiculares | B68: 1 | C68: =TEXT(VALUE(LEFT(C67,4))+1,"0000")&"_2026" -> 0063_2026 | D68: 1/1 | E68: =IF($O68="","",IFERROR("Parte policial Nro. "&SUBSTITUTE(INDEX(VEHICULOS!$N:$N,MATCH($O68,VEHICULOS!$F:$F,0)),"´","")&", Hoja de Ingreso y Salida Nro. "&TEXT(INDEX(VEHICULOS!$E:$E,MATCH($O68,VEHICULOS!$F:$F,0)),"0000000")&", entregado al señor "&INDEX(VEHICULOS!$P:$P,MATCH($O68,VEHICULOS!$F:$F,0))&", con cédula "&INDEX(VEHICULOS!$Z:$Z,MATCH($O68,VEHICULOS!$F:$F,0))&" del Vehiculo Tipo "&INDEX(VEHICULOS!$H:$H,MATCH($O68,VEHICULOS!$F:$F,0))&" marca "&INDEX(VEHICULOS!$G:$G,MATCH($O68,VEHICULOS!$F:$F,0))&", color "&INDEX(VEHICULOS!$J:$J,MATCH($O68,VEHICULOS!$F:$F,0))&" con placas "&$O68&", por "&INDEX(VEHICULOS!$Q:$Q,MATCH($O68,VEHICULOS!$F:$F,0))&".","REVISAR: placa no encontrada en VEHICULOS")) | F68: =IF($O68="","",IFERROR(INDEX(VEHICULOS!$D:$D,MATCH($O68,VEHICULOS!$F:$F,0)),"")) | G68: =IF($O68="","",IFERROR(INDEX(VEHICULOS!$V:$V,MATCH($O68,VEHICULOS!$F:$F,0)),"")) | I68: Eliminación | J68: Fisico
B134: * General, de transferencia (primaria o secundaria) o baja documental
A137: Inventario Elaborado por: | E137: Transferencia o baja aprobada por: | K137: Transferencia o baja autorizado por:
A138: AMADA CONDDOY
A139: CBOP. DE POLICIA
A144: Firma | E144: Firma | K144: Firma
A145: Nombre | E145: Nombre | K145: Nombre
A146: Grado | E146: Grado | K146: Grado
A147: Cargo | E147: Cargo | K147: Cargo
A148: C.C. | E148: C.C. | K148: C.C.
N167: g

Sheet CARATULA DE EXPEDIENTE
C3: POLICÍA NACIONAL DEL ECUADOR
C4: FORMATO DE CARÁTULA DE EXPEDIENTE
B5: SECCIÓN DOCUMENTAL | C5: Jefatura Operativa de Control del Tránsito y Seguridad Vial
B6: SUBSECCIÓN DOCUMENTAL | C6: Patio de Vetención Vehicular
B7: SERIE DOCUMENTAL | C7: Retenciones Vehiculares | E7: SUBSERIE DOCUMENTAL | F7: N/A
B8: DESCRIPCIÓN DOCUMENTAL | C8: Parte policial Nro. 2025120602593551904, Hoja de Ingreso y Salida Nro. 0002030, al señor MANOSALVAS VENEGAS LUIS EDUARDO, con cédula 1201904164 del Tractocamión marca HINO color, blanco conplacas GPB2105, por Accidente de Transito.
B9: NUMERO DE EXPEDIENTE | C9: 0000-2026
B10: FECHA DE APERTURA | C10: 45997 | E10: FECHA DE CIERRE | F10: 46007
B11: VALOR DOCUMENTAL | C11: Primario | E11: CONDICIONES DE ACCESO | G11: RESERVADO
G12: CONFIDENCIAL | H12: X
G13: PÚBLICO
B14: PLAZO DE CONSERVACIÓN | C14: 7 años | D14: DESTINO FINAL | E14: CONSERVACIÓN | G14: N° DE FOJAS | H14: 29
E15: ELIMINACIÓN | F15: x | G15: N° DE TOMO | H15: 1/1
C18: POLICÍA NACIONAL DEL ECUADOR
C19: FORMATO DE CARÁTULA DE EXPEDIENTE
B20: SECCIÓN DOCUMENTAL | C20: Jefatura Operativa de Control del Tránsito y Seguridad Vial
B21: SUBSECCIÓN DOCUMENTAL | C21: Patio de Vetención Vehicular
B22: SERIE DOCUMENTAL | C22: Retenciones Vehiculares | E22: SUBSERIE DOCUMENTAL | F22: N/A
B23: DESCRIPCIÓN DOCUMENTAL | C23: Parte policial Nro. 20251207101848501, Hoja de Ingreso y Salida Nro. 0002031, al señor ONTANEDA YEPEZ JORGE ANIBAL, con cédula 1711325496 del Vehiculo Tipo cisterna marca FORD, color blanco con placas PQF0838, por Accidente de Transito.
B24: NUMERO DE EXPEDIENTE | C24: 0001-2026
B25: FECHA DE APERTURA | C25: 45998 | E25: FECHA DE CIERRE | F25: 46030
B26: VALOR DOCUMENTAL | C26: Primario | E26: CONDICIONES DE ACCESO | G26: RESERVADO
G27: CONFIDENCIAL | H27: X
G28: PÚBLICO
B29: PLAZO DE CONSERVACIÓN | C29: 7 años | D29: DESTINO FINAL | E29: CONSERVACIÓN | G29: N° DE FOJAS | H29: 18
E30: ELIMINACIÓN | F30: x | G30: N° DE TOMO | H30: 1/1
C33: POLICÍA NACIONAL DEL ECUADOR SUBJEFATURA DE TRÁNSITO PEDERNALES-JAMA
C34: FORMATO DE CARÁTULA DE EXPEDIENTE
B35: SECCIÓN DOCUMENTAL | C35: Jefatura Operativa de Control del Tránsito y Seguridad Vial
B36: SUBSECCIÓN DOCUMENTAL | C36: Patio de Vetención Vehicular
B37: SERIE DOCUMENTAL | C37: Retenciones Vehiculares | E37: SUBSERIE DOCUMENTAL | F37: N/A
B38: DESCRIPCIÓN DOCUMENTAL | C38: Parte policial Nro. 2026011204060520618, Hoja de Ingreso y Salida Nro. 0002034, al señor SABANDO ZAMBRANO MARIA FAVIOLA, con cédula 0802191395 del Vehiculo Tipo BUS marca VOLKSWAGEN, color VERDE con placas MAA3069, por Accidente de Transito.
B39: NUMERO DE EXPEDIENTE | C39: 0002-2026
B40: FECHA DE APERTURA | C40: 46034 | E40: FECHA DE CIERRE | F40: 46042
B41: VALOR DOCUMENTAL | C41: Primario | E41: CONDICIONES DE ACCESO | G41: RESERVADO
G42: CONFIDENCIAL | H42: X
G43: PÚBLICO
B44: PLAZO DE CONSERVACIÓN | C44: 7 años | D44: DESTINO FINAL | E44: CONSERVACIÓN | G44: N° DE FOJAS | H44: 21
E45: ELIMINACIÓN | F45: x | G45: N° DE TOMO | H45: 1/1
C48: POLICÍA NACIONAL DEL ECUADOR SUBJEFATURA DE TRÁNSITO PEDERNALES-JAMA
C49: FORMATO DE CARÁTULA DE EXPEDIENTE
B50: SECCIÓN DOCUMENTAL | C50: Jefatura Operativa de Control del Tránsito y Seguridad Vial
B51: SUBSECCIÓN DOCUMENTAL | C51: Patio de Vetención Vehicular
B52: SERIE DOCUMENTAL | C52: Retenciones Vehiculares | E52: SUBSERIE DOCUMENTAL | F52: N/A
B53: DESCRIPCIÓN DOCUMENTAL | C53: Parte policial Nro. 2026011602201191513, Hoja de Ingreso y Salida Nro. 0002035, al señor CALDERON BRIONES JORGE LUIS, con cédula 1714373246del Vehiculo Tipo VOLQUETA marca HINO, color AMARILLO con placas GBN5890, por Accidente de Transito.
B54: NUMERO DE EXPEDIENTE | C54: 0003-2026
B55: FECHA DE APERTURA | C55: 46038 | E55: FECHA DE CIERRE | F55: 46042
B56: VALOR DOCUMENTAL | C56: Primario | E56: CONDICIONES DE ACCESO | G56: RESERVADO
G57: CONFIDENCIAL | H57: X
G58: PÚBLICO
B59: PLAZO DE CONSERVACIÓN | C59: 7 años | D59: DESTINO FINAL | E59: CONSERVACIÓN | G59: N° DE FOJAS | H59: 21
E60: ELIMINACIÓN | F60: x | G60: N° DE TOMO | H60: 1/1
C63: POLICÍA NACIONAL DEL ECUADOR SUBJEFATURA DE TRÁNSITO PEDERNALES-JAMA
C64: FORMATO DE CARÁTULA DE EXPEDIENTE
B65: SECCIÓN DOCUMENTAL | C65: Jefatura Operativa de Control del Tránsito y Seguridad Vial
B66: SUBSECCIÓN DOCUMENTAL | C66: Patio de Vetención Vehicular
B67: SERIE DOCUMENTAL | C67: Retenciones Vehiculares | E67: SUBSERIE DOCUMENTAL | F67: N/A
B68: DESCRIPCIÓN DOCUMENTAL | C68: Parte policial Nro. 2026012408040460418, Hoja de Ingreso y Salida Nro. 0002036, al señor CAIZALUISA JURADO CARLOS, con cédula 170121200-1 del Vehiculo Tipo BUS marca HINO, color AZUL con placas JAA3356, por Accidente de Transito.
B69: NUMERO DE EXPEDIENTE | C69: 0004-2026
B70: FECHA DE APERTURA | C70: 46046 | E70: FECHA DE CIERRE | F70: 46058
B71: VALOR DOCUMENTAL | C71: Primario | E71: CONDICIONES DE ACCESO | G71: RESERVADO
G72: CONFIDENCIAL | H72: X
G73: PÚBLICO
B74: PLAZO DE CONSERVACIÓN | C74: 7 años | D74: DESTINO FINAL | E74: CONSERVACIÓN | G74: N° DE FOJAS | H74: 17
E75: ELIMINACIÓN | F75: x | G75: N° DE TOMO | H75: 1/1
C78: POLICÍA NACIONAL DEL ECUADOR SUBJEFATURA DE TRÁNSITO PEDERNALES-JAMA
C79: FORMATO DE CARÁTULA DE EXPEDIENTE
B80: SECCIÓN DOCUMENTAL | C80: Jefatura Operativa de Control del Tránsito y Seguridad Vial
B81: SUBSECCIÓN DOCUMENTAL | C81: Patio de Vetención Vehicular
B82: SERIE DOCUMENTAL | C82: Retenciones Vehiculares | E82: SUBSERIE DOCUMENTAL | F82: N/A
B83: DESCRIPCIÓN DOCUMENTAL | C83: Parte policial Nro. 2026012700585644911, Hoja de Ingreso y Salida Nro. 0002037, al señor QUIROGA VACA LUIS GONZALO, con cédula 1711739902del Vehiculo Tipo PLATAFORMA marca SINOTRUK, color BLANCO con placas PAD2356, por Accidente de Transito.
B84: NUMERO DE EXPEDIENTE | C84: 0005-2026
B85: FECHA DE APERTURA | C85: 46049 | E85: FECHA DE CIERRE | F85: 46066
B86: VALOR DOCUMENTAL | C86: Primario | E86: CONDICIONES DE ACCESO | G86: RESERVADO
G87: CONFIDENCIAL | H87: X
G88: PÚBLICO
B89: PLAZO DE CONSERVACIÓN | C89: 7 años | D89: DESTINO FINAL | E89: CONSERVACIÓN | G89: N° DE FOJAS | H89: 20
E90: ELIMINACIÓN | F90: x | G90: N° DE TOMO | H90: 1/1
C93: POLICÍA NACIONAL DEL ECUADOR SUBJEFATURA DE TRÁNSITO PEDERNALES-JAMA
C94: FORMATO DE CARÁTULA DE EXPEDIENTE
B95: SECCIÓN DOCUMENTAL | C95: Jefatura Operativa de Control del Tránsito y Seguridad Vial
B96: SUBSECCIÓN DOCUMENTAL | C96: Patio de Vetención Vehicular
B97: SERIE DOCUMENTAL | C97: Retenciones Vehiculares | E97: SUBSERIE DOCUMENTAL | F97: N/A
B98: DESCRIPCIÓN DOCUMENTAL | C98: Parte policial Nro. 2026012700585644911, Hoja de Ingreso y Salida Nro. 0002038, al señor COLCHA GUNSHA ERICK ALEXANDER, con cédula 0605787365del Vehiculo Tipo CAMIÓN marca HINO, color blanco con placas IAK0630, por Accidente de Transito.
B99: NUMERO DE EXPEDIENTE | C99: 0006-2026
B100: FECHA DE APERTURA | C100: 46049 | E100: FECHA DE CIERRE | F100: 46077
B101: VALOR DOCUMENTAL | C101: Primario | E101: CONDICIONES DE ACCESO | G101: RESERVADO
G102: CONFIDENCIAL | H102: X
G103: PÚBLICO
B104: PLAZO DE CONSERVACIÓN | C104: 7 años | D104: DESTINO FINAL | E104: CONSERVACIÓN | G104: N° DE FOJAS | H104: 17
E105: ELIMINACIÓN | F105: x | G105: N° DE TOMO | H105: 1/1
C108: POLICÍA NACIONAL DEL ECUADOR SUBJEFATURA DE TRÁNSITO PEDERNALES-JAMA
C109: FORMATO DE CARÁTULA DE EXPEDIENTE
B110: SECCIÓN DOCUMENTAL | C110: Jefatura Operativa de Control del Tránsito y Seguridad Vial
B111: SUBSECCIÓN DOCUMENTAL | C111: Patio de Vetención Vehicular
B112: SERIE DOCUMENTAL | C112: Retenciones Vehiculares | E112: SUBSERIE DOCUMENTAL | F112: N/A
B113: DESCRIPCIÓN DOCUMENTAL | C113: Parte policial Nro. 2026013009255363017, Hoja de Ingreso y Salida Nro. 0002040, al señor JAIME PATRICIO NUÑEZ MORENO, con cédula 1707104111 del Vehiculo Tipo FURGON marca HINO, color blanco con placas GBO7773, por Accidente de Transito.
B114: NUMERO DE EXPEDIENTE | C114: 0007-2026
B115: FECHA DE APERTURA | C115: 46052 | E115: FECHA DE CIERRE | F115: 46077
B116: VALOR DOCUMENTAL | C116: Primario | E116: CONDICIONES DE ACCESO | G116: RESERVADO
...

Sheet ETIQUETA DE CAJA
C2: POLICÍA NACIONAL DEL ECUADOR COMANDO GENERAL
C3: ETIQUETA DE CAJA
B4: CAJA N°1
B5: SECCIÓN DOCUMENTAL | C5: LOGISTICA
B6: SUBSECCIÓN DOCUMENTAL | C6: ACTIVOS FIJOS
B7: SERIE DOCUMENTAL | C7: OFICIOS | D7: SUBSERIE DOCUMENTAL | E7: RECIBIDOS
B8: Nro. DE EXPEDIENTES | C8: 43891 | D8: FECHA INICIO | E8: O1%O1/2015
D9: FECHA FIN | E9: 42155

Sheet INDICE DE F.A
B2: ÍNDICE DE FONDOS ACUMULADOS
B3: OFICIOS ENVIADOS ENERO 2015
B4: TOMO N° 000
A5: NÚMERO DE FOJAS | B5: FECHA | C5: ASUNTO | D5: TOTAL DE FOLIOS | E5: SOPORTE DOCUMENTAL
A6: 77-81 | B6: 42019 | C6: CASO 30S SGOP XXX | D6: 20 | E6: papel

Sheet DATOS
A1: Lista bancos | C1: Lista marcas | E1: Lista colores | G1: LISTA DE JEFES | I1: CUSTODIOS | K1: SERVIDORES POLICIALES | M1: CUSTODIOS | O1: PERITOS | Q1: ACCIONES PERITALES | S1: TARIFARIO | U1: CAUSAS | W1: LISTA TIPOS DE VEHICULO
A2: AGENCIA NACIONAL DE TRANSITO ANT PUNTO VENTA: ARY RECAUDACIONES | C2: AZUL | E2: AMARILLO | I2: POLI. TIPAN KEVIN | K2: CBOP. MEZA CARLOS | M2: POLI. TIPAN KEVIN | O2: CBOP. REA FREIRE JULIO ERNESTO | Q2: INORME TECNICO PERICIAL DE EVALUO TECNICO MECANICO Y RECONOCIMIENTO DE DAÑOS MATERIALES | S2: SERVICIO DE GARAJE LIVIANOS (HASTA 3,5 TN A EXCEPCIÓN DE MOTOCICLETAS) (DIARIOS) | U2: ACCIDENTE DE TRANSITO | W2: AUTOBUS
A3: BANCO DEL PACIFICO | C3: BAIC | E3: ANARANJADO | I3: SGOS. GUERRERO ALBERTO | K3: SGOP. LOPEZ RICHARD | M3: SGOS. GUERRERO ALBERTO | O3: CBOP. GAVILANEZ AZOGUE LENIN | Q3: N/A | S3: SERVICIO DE GARAJE PESADOS (DE 3,51 TN HASTA 12 TN) (DIARIOS) | U3: ART. 160 | W3: BUS
A4: BANCO DEL PACIFICO-BANCO DEL PACIFICO | C4: CHERRY | E4: AZUL | G4: CPTN. IZA VILLENA RODNEY ESTEBAN | I4: SGOS. CHASIPANTA XAVIER | K4: SGOP. INCA VICTOR | M4: SGOS. CHASIPANTA XAVIER | O4: AGENTE JONATHAN MAURICIO VAICILLAGAROFALO | S4: SERVICIO DE GARAJE (CENTROS DE RETENCIÓN) MOTOCICLETA | U4: ART. 386 INCISO 3 #1 | W4: CABEZAL
A5: BANCO DEL PACIFICO-MI NEGOCIO EFECTIVO | C5: CHERY | E5: BLANCO | G5: FISCAL. AB. ROLANDO SOLIZ SANCHEZ | I5: POLI. ESCOBAR NIXON | K5: POLI. MENDOZA LEONEL | M5: POLI. ESCOBAR NIXON | O5: N/A | S5: SERVICIO DE GARAJE EXTRA PESADOS (MÁS DE 12 TN) (DIARIOS) | U5: ART. 386 INCISO 2.1 | W5: CAMIÓN
A6: BANCO DEL PACIFICO/MI NEGOCIO EFECTIVO | C6: FREIGTHLINER | E6: CREMA | G6: TNTE. JORDAN STALIN JAYA VARGAS | I6: CBOP. SOLORZANO PEDRO | K6: CBOP. PASPUEL WILSON | O6: CBOP. SARANGO ROBERTO | W6: CANASTILLA
A7: BANCO DEL PICHINCHA | C7: CHEVROLET | E7: DORADO | G7: CBOS. MONAR GUAÑA GENESIS ELIZABETH | I7: CBOP. BRAULIO ACUÑA | K7: SGOS. PINZON DIEGO | M7: CBOS. ZAMBRANO JAVIER | W7: CISTERNA
A8: BANCO GUAYAQUIL | E8: NEGRO | G8: MAYOR. JARA POZO KERLEY EDUARDO | I8: POLI. LUNA XAVIER | K8: POLI. ZAMBRANO JEAN CARLOS | M8: CBOP. SOLORZANO PEDRO | O8: SGOS. BARCENES FREDY | W8: FURGON
A9: BANCO PACIFICO | C9: CITROEN | E9: PLATA | G9: TCRNL. GALEANO ANDRADE EDISON EDUARDO | I9: CBOP. ITALO CEDEÑO | K9: SGOP. CALAZACON CARLOS | M9: CBOP JARAMILLO CARLOS | O9: AGENTE GAROFALO ROBERTO | W9: PLATAFORMA
A10: BANCO PACIFICO - PAGO AGIL | C10: DFSK | E10: PLATEADO | G10: MAYOR SOLIS MAYORGA PABLO | I10: CBOS. CHALA ANDERSON | K10: SGOS. ALDAS ERAZO AMABLE | M10: CBO JARAMILLO CARLOS | O10: TCNO. MARTIN FRANCESCO AGUILLON AGUILLON | W10: TRACTO CAMIÓN
A11: BANCO PICHINCHA | C11: DONGFENG | E11: PLOMO | K11: CBOP. ROMERO PATRICIO | M11: POLI. LUNA XAVIER | O11: AGENTE 4 TNCO. MARTIN FRANCESCO AGUILLON AGUILLION | W11: TRAILER
A12: BANCO PICHINCHA - MI NEGOCIO EFECTIVO | C12: FAW | E12: ROJO | K12: SGOS. PILCO EDGAR | M12: CBOS. MUYULEMA WILLIAM | O12: CBOS. GUAMAN JEFFERSON | W12: VOLQUETA
A13: BANCO PICHINCHA Y BANCO PACIFICO | C13: FIAT | E13: VINO | K13: CBOP. GUERRERO DANIEL | M13: CBOP CARLOS JARAMILLO | O13: AB. ALVARO ADRIAN VARGAS VERA
A14: MI NEGOCIO EFECTIVO | C14: FORD | K14: CBOP. LARA WUILLIAN | M14: POLI.LICOA ROGGER | O14: CBOP. VICTOR DAMIAN ARIAS
A15: MI NEGOCIO EFECTIVO BANCO PACIFICO | C15: FOTON | K15: SGOP. PASTUÑA JAIME | M15: POLI. GOMEZ PAUL | O15: AGENTE CTE. AGUILLON MARTIN
A16: MI NEGOCIO EFECTIVO BANCO PICHINCHA | C16: GREAT WAIL | K16: SGOS. CASTRO CONCHA CARLOS ELIAS | M16: POLI. LICOA ROGGER | O16: MARTIN FRANCESCO AGUILLON
A17: MI NEGOCIO EFECTIVO Y PAGO AGIL | C17: GREAT WALL | K17: SGOS. BRAVO HENRY | M17: SGOS. RODRIGUEZ LUIS | O17: CBOP. ROBERTO FABRICIO SARANGO ROSADO
A18: MI NEGOCIO EFECTIVO-MI NEGOCIO EFECTIVO | C18: HINO | K18: CBOP. TUALOMBO GEOVANY | M18: SGOS. GAIBOR ELMER | O18: AGENTE EDER ALDAZ CTE
A19: MI NEGOCIO EFECTIVO-MI VECINO BANCO PICHINCHA-MI NEGOCIO EFECTIVO | C19: HIUNDAY | K19: CBOP. ABATA SANTIAGO | M19: CBOP. BRAULIO ACUÑA | O19: CBOP. ARIAS VICTOR
A20: PAGO AGIL | C20: HYUNDAI | K20: SGOP. RICHARD LOPEZ | O20: AGENTE 1 ABG.EDGAR OLMEDO VASQUEZ
A21: PAGO AGIL-PAGO EN LA PAGINA PAGOS EN LINEA ANT | C21: ISUZU | K21: SGOS. ALVARO ARIAS | O21: AGENTE CTE. VELA LUIS
A22: SERVIPAGOS AGENTE | C22: JAC | K22: CBOS. SANCHEZ MIGUEL | O22: AGENTE CTE LUIS VELA FLORES
A23: TRANSFERENCIA BANCARIA BANCO DEL PACIFICO | C23: KENWORTH | K23: SGOS. BONILLA PAUL | O23: CBOP. LENIN ORLANDO GAVILANEZ AZOGUE
A24: WESTERN UNION | C24: KIA | K24: CBOS. SANCHEZ ANGEL | O24: CBOS. GUAMAN FREIRE JEFFERSON GUILLERMO
A25: NO LEGIBLE | C25: KYC | K25: SGOS. CARCHI WILBER | O25: TILZO NEYARROYO BORJA
C26: MAXUS | K26: SGOS. CASTELLANO LUIS | O26: AGENTE MACIAS GUERRA JORGE
C27: MAZDA | K27: SGOP. GUERRERO SANTIAGO | O27: ROBERT GAROFALO RAMOS
C28: MITSUBISHI | K28: SGOP. BENALCAZAR LUIS | O28: CBOP SARANGO ROBERTO
C29: NISSAN | K29: SGOS. CURICHO FRANKLIN | O29: RAMIREZ VELASTEGUI SANTIAGO
C30: PLOMO | K30: SGOS. CARLOSCALAZACON | O30: MILTON ANTONIO BRAVO BRIONES
C31: RENAULT | K31: SGOS. MOLINA JAIME
C32: ROJO | K32: CBOP. SEGOVIA MARCOS | O32: CPTN. RAMIREZ VELASTEGUI SANTIAGO RUBEN
C33: SINOTRUK | K33: CBOP SEGOVIA MARCOS | O33: CESAR ERNESTO GUINGLA ARRA
C34: SOUEAST | K34: CBOP. HERRERA HERMEL | O34: CBOS. JIMENEZ JORGE
C35: SUZUKI | K35: CBOP. LOPEZ WASHINGTON | O35: CBOP. JULIO REA FREIRE
C36: TOYOTA | K36: SGOS. WILSON LOJAN | O36: CBOP. REA JULIO
C37: VOLKSWAGEN | K37: SBOS. CAICEDO ULBER | O37: POLI. HERRERA ORDOÑEZ ANTHONY STEEVEN
C38: MERCEDEZ BENZ | K38: CPTN. IZA ESTEBAN | O38: CBOS. JONATHAN ISMAEL ARMIJOS MEJIA
C39: YUTONG | K39: CBOP. LOPEZ CHIMBORAZO WASHINGTON | O39: CBOP. FRANCISCO WLADIMIR NASIMBA GUALPA
C40: INTERNACIONAL | K40: SGOS. FERNADO TOAZA TINTUÑA | O40: CBOP. ESTALIN PATRICIO DIAZ FUENTES
K41: SGOS. LOJAN WILSON | O41: SGOS. CRUZ CALDERON DANILO FABRICIO
K42: CBOS. MADRUÑERO ALEX
K43: CBOP. TANDALLA MIGUEL
K44: SGOP.MUÑOZ VERA EDWIN JAVIER
K45: POLI. MORAN KEVIN
K46: SGO.VARGAS SOLANO FREDDY
K47: CBOP. MARIN ANGEL
K48: SGOS. PABLO TOAZA
K49: SGOS. EDGAR PILCO
K50: SGOS. VILLACRES GUAPILEMA DARWIN DUVAL
K51: CBOP. IZURIETA MERINO DENNIS
K52: SGOS. PUCHA BYRON
K53: CBOP. BRIONES INTRIAGO JONATHAN DAVID
... K72: SGOS. ROJAS ROSAS GANDY DANIEL

Sheet MOTOCICLETAS
A1: POLICÍA NACIONAL DE ECUADOR
A2: DIRECCIÓN NACIONAL DE CONTROL DE TRÁNSITO Y SEGURIDAD VIAL
A3: CENTRO DE RETENCIÓN VEHICULAR "TRES MARIAS PORTOVIEJO 2024"
B5: INGRESO DEL VEHICULO | U5: SALIDA DE VEHICULO | AE5: ALCOHOCHECK | AG5: INVESTIGACIÓN
A6: ORD. | B6: SUBZONA | C6: CENTRO DE RETENCION VEHICULAR | D6: FECHA DE INGRESO | E6: NÚMERO DE FORMULARIO DE INGRESO VEHICULAR | F6: PLACA | G6: MARCA | H6: MODELO | I6: COLOR | J6: AÑO DE FABRICACIÓN | K6: NÚMERO DE CHASIS | L6: NÚMERO DE MOTOR | M6: NÚMERO DE PARTE | N6: PARTE ELABORADO POR (QUIEN TOMA PROCEDIMIENTO) | O6: NOMBRE PROPIETARIO/RESPONSABLE DEL VEHICULO | P6: SITUACIÓN LEGAL (Infracción tránsito) | Q6: AUTORIDAD QUE CONOCE (Juzgado Y/O fiscalia que avocó conocimiento) | R6: PLACA-GRUA | S6: NOMBRES CONDUCTOR GRUA | T6: NOMBRE SERVIDOR POLICIAL QUE RECIBE LA CUSTODIA DEL VEHÍCULO | U6: FECHA EGRESO | V6: ORDEN DE LIBERTAD EMITIDA AUTORIDAD COMPETENTE | W6: NOMBRE DEL SEÑOR JEFE QUE EMITE LIBERTAD | X6: NOMBRES DE PERSONA A QUIEN SE ENTREGA | Y6: NÚMERO DE CEDULA | Z6: NÚMERO DE ORDEN DE PAGO (GARAGE) | AA6: DIAS DE PARQUEO | AB6: VALOR CANCELADO POR PARQUEO | AC6: NÚMERO DE FORMULARIO DE EGRESO VEHICULAR | AD6: NOMBRE SERVIDOR POLICIAL QUE ENTREGA EL VEHÍCULO (CUSTODIO) | AE6: NÚMERO DE ORDEN DE PAGO POR ALCOHOCHECK | AF6: VALOR CANCELADO POR ALCOHOCHEK | AG6: PERICIAS REALIZADAS | AH6: NOMBRE DEL PERITO | AI6: FECHA DE PAGO EN LA ENTIDAD FINANCIERA | AJ6: NRO. DE COMPROBANTE DE PAGO DE LA ENTIDAD FINANCIERA | AK6: INSTITUCIÓN FINANCIERA (BANCO-COOPERATIVA)
A7: 1 | B7: SANTO DOMINGO | C7: LA BURNEO | D7: 45793 | E7: 1048 | F7: AB499Z | G7: YAMAHA | H7: MTN320 | I7: PLATEADO | J7: 2018 | K7: MH3RH07P3JK005283 | L7: H402E0053030 | M7: 2025051708374536802 | N7: CBOP. CEDEÑO MARLON | O7: CABRERA JURADO NARCISA DE JESUS | P7: ACCIDENTE TRANSITO | Q7: FISCALIA | R7: N/A | S7: N/A | T7: CBOS. ZAMBRANO JAVIER | U7: 45806 | V7: OFICIO No. FPSD-FEAT2-0608-2025-002034-O | W7: FISCAL. VASQUES SANABRIA ANA PATRICIAA | X7: CABRERA JURADO NARCISA DE JESUS | Y7: 0801652009 | Z7: 89293497 | AA7: 13 | AB7: 13 | AC7: 1048 | AD7: CBOS. ZAMBRANO JAVIER | AE7: N/A | AF7: N/A | AG7: N/A | AH7: N/A | AI7: 45805 | AJ7: 250528000631 | AK7: BANCO PICHINCHA
A8: 2 | B8: SANTO DOMINGO | C8: LA BURNEO | D8: 45795 | E8: 1050 | F8: JX808Z | G8: ICS | H8: 150S | I8: AZUL | J8: 2023 | K8: LV7MGZ400PA901558 | L8: 162FMJQQ23001090 | M8: 2025051907375146207 | N8: CBOP. NAJERA HENRY | O8: GARCIA BARRE FLERIDA CLARA | P8: ART. 160 | Q8: N/A | R8: N/A | S8: N/A | T8: CBOS. ZAMBRANO JAVIER | U8: 45967 | V8: MEMORANDO N.- PN-SZSDT-JCTSV-DESP-2025-847-M. | W8: MAYOR. GALIANO ANDRADE EDISON EDUARDO | X8: GARCIA BARRE FLERIDA CLARA | Y8: 1311600751 | Z8: 94171204 | AA8: 173 | AB8: 173 | AC8: 1050 | AD8: CBOS. MUYULEMA MUYULEMA WILLIAM PATRICIO | AE8: N/A | AF8: N/A | AG8: N/A | AH8: N/A | AI8: 45967 | AJ8: 16768863 | AK8: MI NEGOCIO EFECTIVO
A9: 3 | B9: SANTO DOMINGO | C9: LA BURNEO | D9: 45802 | E9: 1058 | F9: IX172Z | G9: IGM | H9: IM250DB | I9: ROJO | J9: 2020 | K9: LY4YCNLV6L0B17803 | L9: 166FMMLM016109 | M9: 2025052506440661510 | N9: CBOS. YANKUR ROMEL | O9: BRAVO VACA ELVIS | P9: ART. 160 | Q9: N/A | R9: N/A | S9: N/A | T9: POLI. TIPAN KEVIN | U9: 45803 | V9: MEMORANDO No. PN-SZSDT-JPCTSV-LI-2025-005-M | W9: SUBS. CAICEDO SEGURA ULBER CARLOS | X9: BRAVO VACA ELVIS | Y9: 1724277015 | Z9: 89226240 | AA9: 2 | AB9: 2 | AC9: 1058 | AD9: POLI. TIPAN KEVIN | AE9: N/A | AF9: N/A | AG9: N/A | AH9: N/A | AI9: 45803 | AJ9: 250526002491 | AK9: BANCO PICHINCHA
A10: 4 | B10: SANTO DOMINGO | C10: LA BURNEO | D10: 45802 | E10: 1059 | F10: IA833Y | G10: LONCIN | H10: LX250GY-3G | I10: ROJO | J10: 2025 | K10: LLCLGM3M0SA500132 | L10: LC171YMM380364Q3 | M10: 2025052510020915500 | N10: CBOP. NAJERA HENRY | O10: AGREDA PINEDA AMERICA | P10: ART. 160 | Q10: N/A | R10: N/A | S10: N/A | T10: POLI. TIPAN KEVIN | U10: 45826 | V10: MEMORANDO No. PN-SZSDT-JPCTSV-2025-212-M | W10: MAYOR. SUAREZ JACOME JUAN CARLOS | X10: AGREDA INEDA AMERICA | Y10: 0703240234 | Z10: 89697765 | AA10: 25 | AB10: 25 | AC10: 1059 | AD10: CBOP. SOLORZANO PEDRO | AE10: N/A | AF10: N/A | AG10: N/A | AH10: N/A | AI10: 45826 | AJ10: 202506182712420 | AK10: BANCO DEL PACIFICO
A11: 5 | B11: SANTO DOMINGO | C11: LA BURNEO | D11: 45802 | E11: 1060 | F11: AE370D | G11: YAMAHA | H11: YB125 | I11: ROJO | J11: 2018 | K11: LBPKE0977J0510782 | L11: JYM154FMI18060633 | M11: 2025052507542287317 | N11: CBOP. NAJERA HENRY | O11: YOLANDA MARIBEL CALDERON BAÑO | P11: ART. 160 | Q11: N/A | R11: N/A | S11: N/A | T11: POLI. TIPAN KEVIN | U11: 45804 | V11: MEMORANDO No. PN-SZSDT-JPCTSV-LI-2025-006-M | W11: MAYOR. SUAREZ JACOME JUAN CARLOS | X11: YOLANDA MARIBEL CALDERON BAÑO | Y11: 0801828211 | Z11: 89295106 | AA11: 3 | AB11: 3 | AC11: 1060 | AD11: POLI. TIPAN KEVIN | AE11: N/A | AF11: N/A | AG11: N/A | AH11: N/A | AI11: 45804 | AJ11: 56587022 | AK11: BANCO PICHINCHA
A12: 6 | B12: SANTO DOMINGO | C12: LA BURNEO | D12: 45806 | E12: 1061 | F12: KM281F | G12: TUNDRA | H12: CROSSX200I | I12: NEGRO | J12: 2025 | K12: 8LRYCML09S0016294 | L12: AD163FMLS0016202 | M12: 2025052903593518210 | N12: CPTN. IZA RODNEY | O12: JIMENEZ ARAUJO NIEVES CONSUELO | P12: ART. 160 | Q12: N/A | R12: N/A | S12: N/A | T12: CBOS. ZAMBRANO JAVIER | U12: 45808 | V12: MEMORANDO No. PN-SZSDT-JPCTSV-2025-153-M | W12: MAYOR. SUAREZ JACOME JUAN CARLOS | X12: JIMENEZ ARAUJO NIEVES CONSUELO | Y12: 1722034749 | Z12: 89313151 | AA12: 3 | AB12: 3 | AC12: 1061 | AD12: CBOS. ZAMBRANO JAVIER | AE12: N/A | AF12: N/A | AG12: N/A | AH12: N/A | AI12: 45808 | AJ12: 202505315630320 | AK12: BANCO DEL PACIFICO
A13: 7 | B13: SANTO DOMINGO | C13: LA BURNEO | D13: 45806 | E13: 1062 | F13: JP472V | G13: TVS | H13: TVS APACHE RTR 160 4V | I13: NEGRO | J13: 2022 | K13: MD637AE74N2AB2143 | L13: CE7AN29S0113 | M13: 2025053001363154509 | N13: SGOS. PINZON DIEGO | O13: GAIBOR FIGUEROA DAVID | P13: ACCIDENTE TRANSITO | Q13: FISCALIA | R13: N/A | S13: N/A | T13: CBOS. ZAMBRANO JAVIER | U13: 45832 | V13: MEMORANDO No. PN-SZSDT-JPCTSV-2025-228-M | W13: CPTN. RODNEY IZA VILLENA | X13: GAIBOR FIGUEROA DAVID | Y13: 1724881717 | Z13: 89879240 | AA13: 27 | AB13: 27 | AC13: 1062 | AD13: CBOP. SOLORZANO PEDRO | AE13: N/A | AF13: N/A | AG13: N/A | AH13: N/A | AI13: 45832 | AJ13: 2750287194 | AK13: MI NEGOCIO EFECTIVO
A14: 8 | B14: SANTO DOMINGO | C14: LA BURNEO | D14: 45808 | E14: 1064 | F14: HD569W | G14: SUZUKI | H14: AX100 | I14: AZUL | J14: 2006 | K14: 9FSBE11A36C184075 | L14: 1E50FMGS0010209 | M14: 2025053109404766307 | N14: CBOP. ARELLANO JUAN | O14: VILLA CHUMO JEFFERSON | P14: ART. 160 | Q14: N/A | R14: N/A | S14: N/A | T14: CBOS. ZAMBRANO JAVIER
A15: 9 | B15: SANTO DOMINGO | C15: LA BURNEO | D15: 45816 | E15: 1066 | F15: KA329R | G15: BENELLI | H15: 180S | I15: VERDE | J15: 2023 | K15: LBBM62005PBE29805 | L15: BJ164MKA12122887 | M15: 2025060806152991300 | N15: SGOS. PILCO CARRAZCO | O15: PERALTA SARANGO DYLAN | P15: ACCIDENTE TRANSITO | Q15: FISCALIA | R15: N/A | S15: N/A | T15: POLI. TIPAN KEVIN | U15: 45833 | V15: OFICIO No. FPSD-FEAT3-0609-2025-001591-O | W15: MAYOR. SUAREZ JACOME JUAN CARLOS | X15: PERALTA CAIZA LUIS GEOVANNY | Y15: 1713632634 | Z15: 89943243 | AA15: 18 | AB15: 18 | AC15: 1066 | AD15: POLI. TIPAN KEVIN | AE15: N/A | AF15: N/A | AG15: INFORME TECNICO PERICIALDE DAÑOS MATERIALES Y MECANICOS FORENSES (TIPO B) | AH15: SGOS. CALDERON CRUZ DANILO | AI15: 45833 | AJ15: 2760325966 | AK15: MI NEGOCIO EFECTIVO
A16: 10 | B16: SANTO DOMINGO | C16: LA BURNEO | D16: 45823 | E16: 1070 | F16: KC770E | G16: THUNDER | H16: FALCON | I16: BLANCO | J16: 2024 | K16: 8LMC120M1RMA06216 | L16: OP162FMJT0000645 | M16: 202506150805504501 | N16: CBOP. ROMERO PATRICIO | O16: VARGAS CASTRO VERONICA | P16: ACCIDENTE TRANSITO | Q16: FISCALIA | R16: N/A | S16: N/A | T16: CBOP. SOLORZANO PEDRO | U16: 45841 | V16: OFICIO No. FPSD-FEAT2-0608-2025-002460-O | W16: CPTN. RODNEY IZA VILLENA | X16: VARGAS CASTRO VERONICA ALEXANDRA | Y16: 1717401481 | Z16: 90176686 | AA16: 19 | AB16: 19 | AC16: 1070 | AD16: POLI. TIPAN KEVIN | AE16: N/A | AF16: N/A | AG16: INFORME TECNICO PERICIALDE DAÑOS MATERIALES Y MECANICOS FORENSES (TIPO B) | AH16: SGOS. BARCENES RAMIREZ FREDDY EDUARDO | AI16: 45841 | AJ16: 16125676 | AK16: SERVIAGOS AGENTE
A17: 11 | B17: SANTO DOMINGO | C17: LA BURNEO | D17: 45827 | E17: 1074 | F17: IZ136M | G17: BAJAJ | H17: PULSAR 180 | I17: NEGRO | J17: 2020 | K17: MD2A12DYXLCE00497 | L17: DJYCKE00459 | M17: 2025061911115351311 | N17: SGOP. CALAZACON CARLOS | O17: LOOR LOOR MARIELA | P17: ACCIDENTE TRANSITO | Q17: FISCALIA | R17: N/A | S17: N/A | T17: POLI. TIPAN KEVIN | U17: 45860 | V17: OFICIO No. FPSD-FEAT1-0258-2025-002971-O | W17: MAYOR. SUAREZ JACOME JUAN CARLOS | X17: LOOR LOOR MARIELA | Y17: 1312106204 | Z17: 91474387 | AA17: 70 | AB17: 70 | AC17: 1074 | AD17: CBOP. SOLORZANO PEDRO | AE17: N/A | AF17: N/A | AG17: INFORME TECNICO PERICIALDE DE AVALUO TECNICO MECANICO Y RECONOCIMIENTO DEDAÑOS MATERIALES | AH17: SGOS. BARSENES FREDDY | AI17: 45891 | AJ17: 16386356 | AK17: MI NEGOCIO EFECTIVO
A18: 12 | B18: SANTO DOMINGO | C18: LA BURNEO | D18: 45829 | E18: 1076 | F18: HX970B | G18: THUNDER | H18: TGN150 | I18: NEGRO | J18: 2014 | K18: LWPPCK3A6E8205336 | L18: YH162FMJE8205336 | M18: 2025062109503949105 | N18: CBOP. ROMERO PATRICIO | O18: CEDEÑO MARQUINEZ JORGE LUIS | P18: ACCIDENTE TRANSITO | Q18: FISCALIA | R18: N/A | S18: N/A | T18: POLI. TIPAN KEVIN
A19: 13 | B19: SANTO DOMINGO | C19: LA BURNEO | D19: 45832 | E19: 1080 | F19: IL304H | G19: TUKO | H19: TK150-H | I19: NEGRO | J19: 2016 | K19: LLCLPJ2H5G1500119 | L19: LC162FMJNQ377776 | M19: 2025062403061325116 | N19: SGOS. GUERRERO ALBERTO | O19: MEDINA ROMERO BOLIVAR | P19: ART. 160 | Q19: N/A | R19: N/A | S19: N/A | T19: CBOP. SOLORZANO PEDRO
A20: 14 | B20: SANTO DOMINGO | C20: LA BURNEO | D20: 45833 | E20: 1081 | F20: IZ127C | G20: BAJAJ | H20: PULSAR 180 | I20: ROJO | J20: 2020 | K20: MD2A12DY7LCC00712 | L20: DJYCKC79845 | M20: 2025062510562446006 | N20: SGOS. BRAVO HENRY | O20: GUAMAN GONGORA JOSE | P20: ART 385 #3 | Q20: FISCALIA | R20: N/A | S20: N/A | T20: POLI. TIPAN KEVIN
A21: 15 | B21: SANTO DOMINGO | C21: LA BURNEO | D21: 45838 | E21: 1084 | F21: KA668G | G21: THUNDER | H21: MIG20 | I21: NEGRO | J21: 2024 | K21: 8LMC127N2RMA02390 | L21: TDR163FML23W90169 | M21: 2025063009471514903 | N21: SGOS. CARCHI WIBER | O21: ARRAGA QUIJIJE EDWIN | P21: ACCIDENTE TRANSITO | Q21: FISCALIA | R21: N/A | S21: N/A | T21: CBOP. SOLORZANO PEDRO
A22: 16 | B22: SANTO DOMINGO | C22: LA BURNEO | D22: 45838 | E22: 1085 | F22: IA833Y | G22: AXXO | H22: AX200 | I22: NEGRO | J22: 2013 | K22: LHJYCLLA8DB416209 | L22: 169FML13A02668 | M22: 2025063002213566106 | N22: CBOP. CAIZA OBANDO JORGE | O22: HERNANDEZ SOLARTE ROSA | P22: ACCIDENTE TRANSITO | Q22: FISCALIA | R22: N/A | S22: N/A | T22: CBOP. SOLORZANO PEDRO | U22: 45871 | V22: OFICIO No. FSD-FEAT2-0608-2025-002825-O | W22: MAYOR. GALIANO ANDRADE EDISON EDUARDO | X22: HERNANDEZ SOLARTE ROSA ELVIRA | Y22: 2300063209 | Z22: 90952047 | AA22: 34 | AB22: 34 | AC22: 1085 | AD22: POLI. TIPAN KEVIN | AE22: N/A | AF22: N/A | AG22: INFORME TECNICO PERICIALDE DE AVALUO TECNICO MECANICO Y RECONOCIMIENTO DEDAÑOS MATERIALES (TIPO B) | AH22: SGOS. BARCENES RAMIREZ FREDDY EDUARDO | AI22: 45871 | AJ22: 202508024867820 | AK22: BANCO DEL PACIFICO
A23: 17 | B23: SANTO DOMINGO | C23: LA BURNEO | D23: 45844 | E23: 1090 | F23: FA979L | G23: HONDA | H23: XR250 TORNADO | I23: BLANCO | J23: 2012 | K23: 9C2MD3400CR515935 | L23: MD34EC512681 | M23: 2025070608412051511 | N23: SGOS. ALDAZ ERAZO AMABLE | O23: GOYA MENDOZA ALEX | P23: ACCIDENTE TRANSITO | Q23: FISCALIA | R23: N/A | S23: N/A | T23: POLI. TIPAN KEVIN | U23: 45874 | V23: OFICIO No. FPSD-FEAT3-0609-2025-001939-O | W23: MAYOR. SUAREZ JACOME JUAN CARLOS | X23: GOYA MENDOZA ALEX | Y23: 0942038308 | Z23: 91002916 | AA23: 31 | AB23: 31 | AC23: 1090 | AD23: CBOP. SOLORZANO PEDRO | AE23: N/A | AF23: N/A | AG23: INFORME TECNICO PERICIALDE DE AVALUO TECNICO MECANICO Y RECONOCIMIENTO DEDAÑOS MATERIALES | AH23: SGOS. CRUZ DANILO | AI23: 45874 | AJ23: 250805003093 | AK23: BANCO PICHINCHA
A24: 18 | B24: SANTO DOMINGO | C24: LA BURNEO | D24: 45844 | E24: 1091 | F24: JO173K | G24: SUZUKI | H24: GD115 | I24: NEGRO | J24: 2022 | K24: 9FSNE43B3NC192597 | L24: E467312942 | M24: 2025070601151329317 | N24: CBOP. GUERREO DANIEL | O24: FARINANGO RUIZ LUIS GERARDO | P24: ART. 389 #7 | Q24: N/A | R24: N/A | S24: N/A | T24: POLI. TIPAN KEVIN | U24: 46058 | V24: No.23281-2025-13562-OFICIO-01380-2026 | W24: MAYOR. SUAREZ JACOME JUAN CARLOS | X24: FARINANGO RUIZ LUIS GERARDO | Y24: 1719177014 | Z24: 96297634 | AA24: 215 | AB24: 215 | AC24: 1091 | AD24: CBOP. SOLORZANO PEDRO | AE24: N/A | AF24: N/A | AG24: N/A | AH24: N/A | AI24: 46239 | AJ24: 0056536955 | AK24: BANCO PICHINCHA
A25: 19 | B25: SANTO DOMINGO | C25: LA BURNEO | D25: 45844 | E25: 2410 | F25: JE680Y | G25: Z1 | H25: Z1 GN150S | I25: ROJO | J25: 2021 | K25: LWPPCK3A7M8271201 | L25: YH162FMJM8271201 | M25: 2025070601375312912 | N25: CBOP. GUERREO DANIEL | O25: VARELA LOEZ SARA CAROLINA | P25: ART 160 | Q25: N/A | R25: N/A | S25: N/A | T25: POLI. TIPAN KEVIN
A26: 20 | B26: SANTO DOMINGO | C26: LA BURNEO | D26: 45844 | E26: 2411 | F26: IT749M | G26: DAYTONA | H26: DY150 ZERO | I26: BLANCO | J26: 2018 | K26: LB5PM8S19JZ400365 | L26: FT162FMJ2J1772515 | M26: 2025070606162079018 | N26: SGOS. ALDAZ ERAZO AMABLE | O26: ANGULO AGUAS BRYAN | P26: ACCIDENTE TRANSITO | Q26: FISCALIA | R26: N/A | S26: N/A | T26: POLI. TIPAN KEVIN
A27: 21 | B27: SANTO DOMINGO | C27: LA BURNEO | D27: 45845 | E27: 2413 | F27: AC871R | G27: MOTOR 1 | H27: SK200 FX200 | I27: ROJO | J27: 2013 | K27: LP6PCM3B7D0F00232 | L27: 163FMLD5100844 | M27: 2025070802451954709 | N27: SGOS. ARIAS EDISON | O27: MOROCHO POGO CESAR MIGUEL | P27: ART. 160 | Q27: N/A | R27: N/A | S27: N/A | T27: POLI. TIPAN KEVIN
